Workbook

Sheet Hoja 1 - Supabase Transcripts
A1: Session Deep Dives | X1: General Data | AA1: Survey Data | AG1: Text Segregation by Topic | AM1: Text Processing & Engagement | AW1: Sentiment Topics | BU1: Sentiment Analysis | CB1: Negative Issue Detection | CF1: Reflection & Thinking Depth | CJ1: Emotion Analysis | CQ1: AI Disclosure gap | CZ1: Reviwerer 1 Disclosure Gap | DP1: Audit Week | DQ1: Cohens k | EC1: Second Reviewer | ES1: Extra
A2: session_id | B2: audit_id | C2: employee_id | D2: channel | E2: started_at | F2: ended_at | G2: status | H2: duration_sec | I2: media_uri | J2: eleven_conversation_id | K2: eleven_agent_id | L2: transcription | M2: aud_id | N2: summary | O2: caller_phone | P2: called_phone | Q2: source_provider | R2: survey_result_ids | S2: interview_tag | T2: interview_tag_source | U2: interview_tag_updated_at | V2: interview_tag_updated_by | W2: ai_analysis_complete | X2: week_number | Y2: participant_text_clean | Z2: session_number_per_employee | AA2: pre-survey_response_json | AB2: pre-survey_submitted_at | AC2: post-survey_response_json | AD2: post-survey_submitted_at | AE2: post_feedback_topic | AF2: post_feedback_sentiment | AG2: text_overall_experience | AH2: text_workload_sustainability | AI2: text_client_value | AJ2: text_leadership_engagement | AK2: text_additional_topic | AL2: text_closing | AM2: word_count_total | AN2: word_count_overall | AO2: word_count_workload_sustainability | AP2: word_count_client_value | AQ2: word_count_leadership_engagement | AR2: word_count_additional_topic | AS2: word_count_closing | AT2: participant_turn_count | AU2: avg_words_per_turn | AV2: longest_response_words | AW2: sentiment_overall experience | AX2: soe_pos | AY2: soe_neu | AZ2: soe_neg | BA2: sentiment_workload | BB2: sw_pos | BC2: sw_neu | BD2: sw_neg | BE2: sentiment_client_value | BF2: scv_pos | BG2: scv_neu | BH2: scv_neg | BI2: sentiment_leadership | BJ2: sl_pos | BK2: sl_neu | BL2: sl_neg | BM2: sentiment_additional_ topic | BN2: sat_pos | BO2: sat_neu | BP2: sat_neg | BQ2: sentiment_closing | BR2: sc_pos | BS2: sc_neu | BT2: sc_neg | BU2: sentiment_positive_avg | BV2: sentiment_neutral_avg | BW2: sentiment_negative_avg | BX2: sentiment_negative_max | BY2: sentiment_label_dominant | BZ2: sentiment_complete_interview | CA2: sentiment_manual_negative | CB2: negative_issue_auto | CC2: negative_issue_keyword_count | CD2: deep_dive_negative_issue | CE2: negative_issue_manual | CF2: causal_marker_count (e.g., because, due to, led to) | CG2: consequence_marker_count (e.g., resulted in, impact) (e.g., resulted in, impact) | CH2: improvement_marker_count (e.g., should, need to, could) | CI2: reflection_depth_manual | CJ2: emotion_general | CK2: emotion_overall_experience | CL2: emotion_workload_sustainability | CM2: emotion_client_value | CN2: emotion_leadership_engagement | CO2: emotion_additional_topic | CP2: emotion_closing | CQ2: Disclosure gap | CR2: gap_overall_expierience | CS2: reason_o_e | CT2: gap_workload_sust | CU2: reason_w_s | CV2: gap_client_value | CW2: reason_c_v | CX2: gap_leadership_eng | CY2: reason_l_e | CZ2: manual_gap_overall_experience | DA2: manual_likert_overall_experience | DB2: gap_segmentation_overall experience | DC2: negative_issue_overall_experience | DD2: manual_gap_workload_sust | DE2: manual_likert_workload_sust | DF2: gap_segmentation_workload_sust | DG2: negative_issue_workload_sust | DH2: manual_gap_client_value | DI2: manual_likert_client_value | DJ2: gap_segmentation_client_value | DK2: negative_issue_client_value | DL2: manual_gap_leadership | DM2: manual_likert_leadership | DN2: gap_segmentation_leadership | DO2: negative_issue_leadership | DP2: audit_week | DQ2: da_1 | DR2: dm_1 | DS2: da_2 | DT2: dm_2 | DU2: da_3 | DV2: dm_3 | DW2: da_4 | DX2: dm_4 | DY2: diif_1 | DZ2: diif_2 | EA2: diif_3 | EB2: diif_4 | EC2: manual_gap_overall_experience_2 | ED2: manual_likert_overall_experience_2 | EE2: gap_segmentation_overall experience_2 | EF2: negative_issue_overall_experience_2 | EG2: manual_gap_workload_sust_2 | EH2: manual_likert_workload_sust_2 | EI2: gap_segmentation_workload_sust_2 | EJ2: negative_issue_workload_sust_2 | EK2: manual_gap_client_value_2 | EL2: manual_likert_client_value_2 | EM2: gap_segmentation_client_value_2 | EN2: negative_issue_client_value_2 | EO2: manual_gap_leadership_2 | EP2: manual_likert_leadership_2 | EQ2: gap_segmentation_leadership_2 | ER2: negative_issue_leadership_2 | ES2: Willingess-to-repeat | ET2: Gap Manual | EU2: Gap Prevalence by Threshold workload sustainability | EV2: Gap Prevalence by Threshold client value | EW2: Gap Prevalence by Threshold leadership engagement | EX2: Top Box - Gap Prevalence by Threshold workload sustainability | EY2: Top Box - Gap Prevalence by Threshold client value | EZ2: Top Box - Gap Prevalence by Threshold leadership engagement | FA2: Top Box - Gap | GP2: Disclaimer: All field in grey must be filled wth ElevenLabs-Data before running the scripts.
DQ3: =CR3 -> 0 | DR3: =DB3 -> 0 | DS3: =CT3 -> 0 | DT3: =DF3 -> 0 | DU3: =CV3 -> 0 | DV3: =DJ3 -> 0 | DW3: =CX3 -> 0 | DX3: =DN3 -> 0 | DY3: {=_xlfn.LET( _xlpm.a,LOWER(TRIM(DQ3&"")), _xlpm.b,LOWER(TRIM(DR3&"")), _xlpm.x,_xlfn.IFS(_xlpm.a="0",0,_xlpm.a="none",0,_xlpm.a="moderate",1,_xlpm.a="strong",2), _xlpm.y,_xlfn.IFS(_xlpm.b="0",0,_xlpm.b="none",0,_xlpm.b="moderate",1,_xlpm.b="strong",2), _xlpm.d,ABS(_xlpm.x-_xlpm.y), IF(_xlpm.d=0,"green",IF(_xlpm.d=1,"orange",IF(_xlpm.d=2,"red","check"))) )} -> green | DZ3: {=_xlfn.LET( _xlpm.a,LOWER(TRIM(DS3&"")), _xlpm.b,LOWER(TRIM(DT3&"")), _xlpm.x,_xlfn.IFS(_xlpm.a="0",0,_xlpm.a="none",0,_xlpm.a="moderate",1,_xlpm.a="strong",2), _xlpm.y,_xlfn.IFS(_xlpm.b="0",0,_xlpm.b="none",0,_xlpm.b="moderate",1,_xlpm.b="strong",2), _xlpm.d,ABS(_xlpm.x-_xlpm.y), IF(_xlpm.d=0,"green",IF(_xlpm.d=1,"orange",IF(_xlpm.d=2,"red","check"))) )} -> green | EA3: {=_xlfn.LET( _xlpm.a,LOWER(TRIM(DU3&"")), _xlpm.b,LOWER(TRIM(DV3&"")), _xlpm.x,_xlfn.IFS(_xlpm.a="0",0,_xlpm.a="none",0,_xlpm.a="moderate",1,_xlpm.a="strong",2), _xlpm.y,_xlfn.IFS(_xlpm.b="0",0,_xlpm.b="none",0,_xlpm.b="moderate",1,_xlpm.b="strong",2), _xlpm.d,ABS(_xlpm.x-_xlpm.y), IF(_xlpm.d=0,"green",IF(_xlpm.d=1,"orange",IF(_xlpm.d=2,"red","check"))) )} -> green | EB3: {=_xlfn.LET( _xlpm.a,LOWER(TRIM(DW3&"")), _xlpm.b,LOWER(TRIM(DX3&"")), _xlpm.x,_xlfn.IFS(_xlpm.a="0",0,_xlpm.a="none",0,_xlpm.a="moderate",1,_xlpm.a="strong",2), _xlpm.y,_xlfn.IFS(_xlpm.b="0",0,_xlpm.b="none",0,_xlpm.b="moderate",1,_xlpm.b="strong",2), _xlpm.d,ABS(_xlpm.x-_xlpm.y), IF(_xlpm.d=0,"green",IF(_xlpm.d=1,"orange",IF(_xlpm.d=2,"red","check"))) )} -> green | ES3: =IFERROR(VALUE(_xlfn.TEXTBEFORE(_xlfn.TEXTAFTER(AC3,"""84a544d4-0c20-4f9f-bb4b-dd698a9b0c0b"":"),",")),IFERROR(VALUE(_xlfn.TEXTBEFORE(_xlfn.TEXTAFTER(AC3,"""84a544d4-0c20-4f9f-bb4b-dd698a9b0c0b"":"),"}")),IFERROR(VALUE(_xlfn.TEXTBEFORE(_xlfn.TEXTAFTER(AC3,"""784c5905-6667-4dcd-906c-8b405a6572b6"":"),",")),IFERROR(VALUE(_xlfn.TEXTBEFORE(_xlfn.TEXTAFTER(AC3,"""784c5905-6667-4dcd-906c-8b405a6572b6"":"),"}")),"")))) | ET3: =IF(OR(DF3="Strong",DF3="Moderate",DJ3="Strong",DJ3="Moderate",DN3="Strong",DN3="Moderate"),"Yes","No") -> No | EU3: =IF(AND(DE3>=3,DD3=1),"Positive concordance",IF(AND(DE3>=3,DD3>=2),"Gap",IF(AND(DE3<=2,DD3>=2),"Negative concordance","Uninformative"))) -> Uninformative | EV3: =IF(AND(DI3>=3,DH3=1),"Positive concordance",IF(AND(DI3>=3,DH3>=2),"Gap",IF(AND(DI3<=2,DH3>=2),"Negative concordance","Uninformative"))) -> Uninformative | EW3: =IF(AND(DM3>=3,DL3=1),"Positive concordance",IF(AND(DM3>=3,DL3>=2),"Gap",IF(AND(DM3<=2,DL3>=2),"Negative concordance","Uninformative"))) -> Uninformative | EX3: =IF(AND(DE3=4,DD3=1),"Positive concordance",IF(AND(DE3=4,DD3>=2),"Gap",IF(AND(DE3<=3,DD3>=2),"Negative concordance","Uninformative"))) -> Uninformative | EY3: =IF(AND(DI3=4,DH3=1),"Positive concordance",IF(AND(DI3=4,DH3>=2),"Gap",IF(AND(DI3<=3,DH3>=2),"Negative concordance","Uninformative"))) -> Uninformative | EZ3: =IF(AND(DM3=4,DL3=1),"Positive concordance",IF(AND(DM3=4,DL3>=2),"Gap",IF(AND(DM3<=3,DL3>=2),"Negative concordance","Uninformative"))) -> Uninformative | FA3: =IF(OR(EX3="Gap",EY3="Gap",EZ3="Gap"),"Yes","No") -> No
DQ4: =CR4 -> 0 | DR4: =DB4 -> 0 | DS4: =CT4 -> 0 | DT4: =DF4 -> 0 | DU4: =CV4 -> 0 | DV4: =DJ4 -> 0 | DW4: =CX4 -> 0 | DX4: =DN4 -> 0 | DY4: {=_xlfn.LET( _xlpm.a,LOWER(TRIM(DQ4&"")), _xlpm.b,LOWER(TRIM(DR4&"")), _xlpm.x,_xlfn.IFS(_xlpm.a="0",0,_xlpm.a="none",0,_xlpm.a="moderate",1,_xlpm.a="strong",2), _xlpm.y,_xlfn.IFS(_xlpm.b="0",0,_xlpm.b="none",0,_xlpm.b="moderate",1,_xlpm.b="strong",2), _xlpm.d,ABS(_xlpm.x-_xlpm.y), IF(_xlpm.d=0,"green",IF(_xlpm.d=1,"orange",IF(_xlpm.d=2,"red","check"))) )} -> green | DZ4: {=_xlfn.LET( _xlpm.a,LOWER(TRIM(DS4&"")), _xlpm.b,LOWER(TRIM(DT4&"")), _xlpm.x,_xlfn.IFS(_xlpm.a="0",0,_xlpm.a="none",0,_xlpm.a="moderate",1,_xlpm.a="strong",2), _xlpm.y,_xlfn.IFS(_xlpm.b="0",0,_xlpm.b="none",0,_xlpm.b="moderate",1,_xlpm.b="strong",2), _xlpm.d,ABS(_xlpm.x-_xlpm.y), IF(_xlpm.d=0,"green",IF(_xlpm.d=1,"orange",IF(_xlpm.d=2,"red","check"))) )} -> green | EA4: {=_xlfn.LET( _xlpm.a,LOWER(TRIM(DU4&"")), _xlpm.b,LOWER(TRIM(DV4&"")), _xlpm.x,_xlfn.IFS(_xlpm.a="0",0,_xlpm.a="none",0,_xlpm.a="moderate",1,_xlpm.a="strong",2), _xlpm.y,_xlfn.IFS(_xlpm.b="0",0,_xlpm.b="none",0,_xlpm.b="moderate",1,_xlpm.b="strong",2), _xlpm.d,ABS(_xlpm.x-_xlpm.y), IF(_xlpm.d=0,"green",IF(_xlpm.d=1,"orange",IF(_xlpm.d=2,"red","check"))) )} -> green | EB4: {=_xlfn.LET( _xlpm.a,LOWER(TRIM(DW4&"")), _xlpm.b,LOWER(TRIM(DX4&"")), _xlpm.x,_xlfn.IFS(_xlpm.a="0",0,_xlpm.a="none",0,_xlpm.a="moderate",1,_xlpm.a="strong",2), _xlpm.y,_xlfn.IFS(_xlpm.b="0",0,_xlpm.b="none",0,_xlpm.b="moderate",1,_xlpm.b="strong",2), _xlpm.d,ABS(_xlpm.x-_xlpm.y), IF(_xlpm.d=0,"green",IF(_xlpm.d=1,"orange",IF(_xlpm.d=2,"red","check"))) )} -> green | ES4: =IFERROR(VALUE(_xlfn.TEXTBEFORE(_xlfn.TEXTAFTER(AC4,"""84a544d4-0c20-4f9f-bb4b-dd698a9b0c0b"":"),",")),IFERROR(VALUE(_xlfn.TEXTBEFORE(_xlfn.TEXTAFTER(AC4,"""84a544d4-0c20-4f9f-bb4b-dd698a9b0c0b"":"),"}")),IFERROR(VALUE(_xlfn.TEXTBEFORE(_xlfn.TEXTAFTER(AC4,"""784c5905-6667-4dcd-906c-8b405a6572b6"":"),",")),IFERROR(VALUE(_xlfn.TEXTBEFORE(_xlfn.TEXTAFTER(AC4,"""784c5905-6667-4dcd-906c-8b405a6572b6"":"),"}")),"")))) | ET4: =IF(OR(DF4="Strong",DF4="Moderate",DJ4="Strong",DJ4="Moderate",DN4="Strong",DN4="Moderate"),"Yes","No") -> No | EU4: =IF(AND(DE4>=3,DD4=1),"Positive concordance",IF(AND(DE4>=3,DD4>=2),"Gap",IF(AND(DE4<=2,DD4>=2),"Negative concordance","Uninformative"))) -> Uninformative | EV4: =IF(AND(DI4>=3,DH4=1),"Positive concordance",IF(AND(DI4>=3,DH4>=2),"Gap",IF(AND(DI4<=2,DH4>=2),"Negative concordance","Uninformative"))) -> Uninformative | EW4: =IF(AND(DM4>=3,DL4=1),"Positive concordance",IF(AND(DM4>=3,DL4>=2),"Gap",IF(AND(DM4<=2,DL4>=2),"Negative concordance","Uninformative"))) -> Uninformative | EX4: =IF(AND(DE4=4,DD4=1),"Positive concordance",IF(AND(DE4=4,DD4>=2),"Gap",IF(AND(DE4<=3,DD4>=2),"Negative concordance","Uninformative"))) -> Uninformative | EY4: =IF(AND(DI4=4,DH4=1),"Positive concordance",IF(AND(DI4=4,DH4>=2),"Gap",IF(AND(DI4<=3,DH4>=2),"Negative concordance","Uninformative"))) -> Uninformative | EZ4: =IF(AND(DM4=4,DL4=1),"Positive concordance",IF(AND(DM4=4,DL4>=2),"Gap",IF(AND(DM4<=3,DL4>=2),"Negative concordance","Uninformative"))) -> Uninformative | FA4: =IF(OR(EX4="Gap",EY4="Gap",EZ4="Gap"),"Yes","No") -> No
DQ5: =CR5 -> 0 | DR5: =DB5 -> 0 | DS5: =CT5 -> 0 | DT5: =DF5 -> 0 | DU5: =CV5 -> 0 | DV5: =DJ5 -> 0 | DW5: =CX5 -> 0 | DX5: =DN5 -> 0 | DY5: {=_xlfn.LET( _xlpm.a,LOWER(TRIM(DQ5&"")), _xlpm.b,LOWER(TRIM(DR5&"")), _xlpm.x,_xlfn.IFS(_xlpm.a="0",0,_xlpm.a="none",0,_xlpm.a="moderate",1,_xlpm.a="strong",2), _xlpm.y,_xlfn.IFS(_xlpm.b="0",0,_xlpm.b="none",0,_xlpm.b="moderate",1,_xlpm.b="strong",2), _xlpm.d,ABS(_xlpm.x-_xlpm.y), IF(_xlpm.d=0,"green",IF(_xlpm.d=1,"orange",IF(_xlpm.d=2,"red","check"))) )} -> green | DZ5: {=_xlfn.LET( _xlpm.a,LOWER(TRIM(DS5&"")), _xlpm.b,LOWER(TRIM(DT5&"")), _xlpm.x,_xlfn.IFS(_xlpm.a="0",0,_xlpm.a="none",0,_xlpm.a="moderate",1,_xlpm.a="strong",2), _xlpm.y,_xlfn.IFS(_xlpm.b="0",0,_xlpm.b="none",0,_xlpm.b="moderate",1,_xlpm.b="strong",2), _xlpm.d,ABS(_xlpm.x-_xlpm.y), IF(_xlpm.d=0,"green",IF(_xlpm.d=1,"orange",IF(_xlpm.d=2,"red","check"))) )} -> green | EA5: {=_xlfn.LET( _xlpm.a,LOWER(TRIM(DU5&"")), _xlpm.b,LOWER(TRIM(DV5&"")), _xlpm.x,_xlfn.IFS(_xlpm.a="0",0,_xlpm.a="none",0,_xlpm.a="moderate",1,_xlpm.a="strong",2), _xlpm.y,_xlfn.IFS(_xlpm.b="0",0,_xlpm.b="none",0,_xlpm.b="moderate",1,_xlpm.b="strong",2), _xlpm.d,ABS(_xlpm.x-_xlpm.y), IF(_xlpm.d=0,"green",IF(_xlpm.d=1,"orange",IF(_xlpm.d=2,"red","check"))) )} -> green | EB5: {=_xlfn.LET( _xlpm.a,LOWER(TRIM(DW5&"")), _xlpm.b,LOWER(TRIM(DX5&"")), _xlpm.x,_xlfn.IFS(_xlpm.a="0",0,_xlpm.a="none",0,_xlpm.a="moderate",1,_xlpm.a="strong",2), _xlpm.y,_xlfn.IFS(_xlpm.b="0",0,_xlpm.b="none",0,_xlpm.b="moderate",1,_xlpm.b="strong",2), _xlpm.d,ABS(_xlpm.x-_xlpm.y), IF(_xlpm.d=0,"green",IF(_xlpm.d=1,"orange",IF(_xlpm.d=2,"red","check"))) )} -> green | ES5: =IFERROR(VALUE(_xlfn.TEXTBEFORE(_xlfn.TEXTAFTER(AC5,"""84a544d4-0c20-4f9f-bb4b-dd698a9b0c0b"":"),",")),IFERROR(VALUE(_xlfn.TEXTBEFORE(_xlfn.TEXTAFTER(AC5,"""84a544d4-0c20-4f9f-bb4b-dd698a9b0c0b"":"),"}")),IFERROR(VALUE(_xlfn.TEXTBEFORE(_xlfn.TEXTAFTER(AC5,"""784c5905-6667-4dcd-906c-8b405a6572b6"":"),",")),IFERROR(VALUE(_xlfn.TEXTBEFORE(_xlfn.TEXTAFTER(AC5,"""784c5905-6667-4dcd-906c-8b405a6572b6"":"),"}")),"")))) | ET5: =IF(OR(DF5="Strong",DF5="Moderate",DJ5="Strong",DJ5="Moderate",DN5="Strong",DN5="Moderate"),"Yes","No") -> No | EU5: =IF(AND(DE5>=3,DD5=1),"Positive concordance",IF(AND(DE5>=3,DD5>=2),"Gap",IF(AND(DE5<=2,DD5>=2),"Negative concordance","Uninformative"))) -> Uninformative | EV5: =IF(AND(DI5>=3,DH5=1),"Positive concordance",IF(AND(DI5>=3,DH5>=2),"Gap",IF(AND(DI5<=2,DH5>=2),"Negative concordance","Uninformative"))) -> Uninformative | EW5: =IF(AND(DM5>=3,DL5=1),"Positive concordance",IF(AND(DM5>=3,DL5>=2),"Gap",IF(AND(DM5<=2,DL5>=2),"Negative concordance","Uninformative"))) -> Uninformative | EX5: =IF(AND(DE5=4,DD5=1),"Positive concordance",IF(AND(DE5=4,DD5>=2),"Gap",IF(AND(DE5<=3,DD5>=2),"Negative concordance","Uninformative"))) -> Uninformative | EY5: =IF(AND(DI5=4,DH5=1),"Positive concordance",IF(AND(DI5=4,DH5>=2),"Gap",IF(AND(DI5<=3,DH5>=2),"Negative concordance","Uninformative"))) -> Uninformative | EZ5: =IF(AND(DM5=4,DL5=1),"Positive concordance",IF(AND(DM5=4,DL5>=2),"Gap",IF(AND(DM5<=3,DL5>=2),"Negative concordance","Uninformative"))) -> Uninformative | FA5: =IF(OR(EX5="Gap",EY5="Gap",EZ5="Gap"),"Yes","No") -> No
DQ6: =CR6 -> 0 | DR6: =DB6 -> 0 | DS6: =CT6 -> 0 | DT6: =DF6 -> 0 | DU6: =CV6 -> 0 | DV6: =DJ6 -> 0 | DW6: =CX6 -> 0 | DX6: =DN6 -> 0 | DY6: {=_xlfn.LET( _xlpm.a,LOWER(TRIM(DQ6&"")), _xlpm.b,LOWER(TRIM(DR6&"")), _xlpm.x,_xlfn.IFS(_xlpm.a="0",0,_xlpm.a="none",0,_xlpm.a="moderate",1,_xlpm.a="strong",2), _xlpm.y,_xlfn.IFS(_xlpm.b="0",0,_xlpm.b="none",0,_xlpm.b="moderate",1,_xlpm.b="strong",2), _xlpm.d,ABS(_xlpm.x-_xlpm.y), IF(_xlpm.d=0,"green",IF(_xlpm.d=1,"orange",IF(_xlpm.d=2,"red","check"))) )} -> green | DZ6: {=_xlfn.LET( _xlpm.a,LOWER(TRIM(DS6&"")), _xlpm.b,LOWER(TRIM(DT6&"")), _xlpm.x,_xlfn.IFS(_xlpm.a="0",0,_xlpm.a="none",0,_xlpm.a="moderate",1,_xlpm.a="strong",2), _xlpm.y,_xlfn.IFS(_xlpm.b="0",0,_xlpm.b="none",0,_xlpm.b="moderate",1,_xlpm.b="strong",2), _xlpm.d,ABS(_xlpm.x-_xlpm.y), IF(_xlpm.d=0,"green",IF(_xlpm.d=1,"orange",IF(_xlpm.d=2,"red","check"))) )} -> green | EA6: {=_xlfn.LET( _xlpm.a,LOWER(TRIM(DU6&"")), _xlpm.b,LOWER(TRIM(DV6&"")), _xlpm.x,_xlfn.IFS(_xlpm.a="0",0,_xlpm.a="none",0,_xlpm.a="moderate",1,_xlpm.a="strong",2), _xlpm.y,_xlfn.IFS(_xlpm.b="0",0,_xlpm.b="none",0,_xlpm.b="moderate",1,_xlpm.b="strong",2), _xlpm.d,ABS(_xlpm.x-_xlpm.y), IF(_xlpm.d=0,"green",IF(_xlpm.d=1,"orange",IF(_xlpm.d=2,"red","check"))) )} -> green | EB6: {=_xlfn.LET( _xlpm.a,LOWER(TRIM(DW6&"")), _xlpm.b,LOWER(TRIM(DX6&"")), _xlpm.x,_xlfn.IFS(_xlpm.a="0",0,_xlpm.a="none",0,_xlpm.a="moderate",1,_xlpm.a="strong",2), _xlpm.y,_xlfn.IFS(_xlpm.b="0",0,_xlpm.b="none",0,_xlpm.b="moderate",1,_xlpm.b="strong",2), _xlpm.d,ABS(_xlpm.x-_xlpm.y), IF(_xlpm.d=0,"green",IF(_xlpm.d=1,"orange",IF(_xlpm.d=2,"red","check"))) )} -> green | ES6: =IFERROR(VALUE(_xlfn.TEXTBEFORE(_xlfn.TEXTAFTER(AC6,"""84a544d4-0c20-4f9f-bb4b-dd698a9b0c0b"":"),",")),IFERROR(VALUE(_xlfn.TEXTBEFORE(_xlfn.TEXTAFTER(AC6,"""84a544d4-0c20-4f9f-bb4b-dd698a9b0c0b"":"),"}")),IFERROR(VALUE(_xlfn.TEXTBEFORE(_xlfn.TEXTAFTER(AC6,"""784c5905-6667-4dcd-906c-8b405a6572b6"":"),",")),IFERROR(VALUE(_xlfn.TEXTBEFORE(_xlfn.TEXTAFTER(AC6,"""784c5905-6667-4dcd-906c-8b405a6572b6"":"),"}")),"")))) | ET6: =IF(OR(DF6="Strong",DF6="Moderate",DJ6="Strong",DJ6="Moderate",DN6="Strong",DN6="Moderate"),"Yes","No") -> No | EU6: =IF(AND(DE6>=3,DD6=1),"Positive concordance",IF(AND(DE6>=3,DD6>=2),"Gap",IF(AND(DE6<=2,DD6>=2),"Negative concordance","Uninformative"))) -> Uninformative | EV6: =IF(AND(DI6>=3,DH6=1),"Positive concordance",IF(AND(DI6>=3,DH6>=2),"Gap",IF(AND(DI6<=2,DH6>=2),"Negative concordance","Uninformative"))) -> Uninformative | EW6: =IF(AND(DM6>=3,DL6=1),"Positive concordance",IF(AND(DM6>=3,DL6>=2),"Gap",IF(AND(DM6<=2,DL6>=2),"Negative concordance","Uninformative"))) -> Uninformative | EX6: =IF(AND(DE6=4,DD6=1),"Positive concordance",IF(AND(DE6=4,DD6>=2),"Gap",IF(AND(DE6<=3,DD6>=2),"Negative concordance","Uninformative"))) -> Uninformative | EY6: =IF(AND(DI6=4,DH6=1),"Positive concordance",IF(AND(DI6=4,DH6>=2),"Gap",IF(AND(DI6<=3,DH6>=2),"Negative concordance","Uninformative"))) -> Uninformative | EZ6: =IF(AND(DM6=4,DL6=1),"Positive concordance",IF(AND(DM6=4,DL6>=2),"Gap",IF(AND(DM6<=3,DL6>=2),"Negative concordance","Uninformative"))) -> Uninformative | FA6: =IF(OR(EX6="Gap",EY6="Gap",EZ6="Gap"),"Yes","No") -> No
DQ7: =CR7 -> 0 | DR7: =DB7 -> 0 | DS7: =CT7 -> 0 | DT7: =DF7 -> 0 | DU7: =CV7 -> 0 | DV7: =DJ7 -> 0 | DW7: =CX7 -> 0 | DX7: =DN7 -> 0 | DY7: {=_xlfn.LET( _xlpm.a,LOWER(TRIM(DQ7&"")), _xlpm.b,LOWER(TRIM(DR7&"")), _xlpm.x,_xlfn.IFS(_xlpm.a="0",0,_xlpm.a="none",0,_xlpm.a="moderate",1,_xlpm.a="strong",2), _xlpm.y,_xlfn.IFS(_xlpm.b="0",0,_xlpm.b="none",0,_xlpm.b="moderate",1,_xlpm.b="strong",2), _xlpm.d,ABS(_xlpm.x-_xlpm.y), IF(_xlpm.d=0,"green",IF(_xlpm.d=1,"orange",IF(_xlpm.d=2,"red","check"))) )} -> green | DZ7: {=_xlfn.LET( _xlpm.a,LOWER(TRIM(DS7&"")), _xlpm.b,LOWER(TRIM(DT7&"")), _xlpm.x,_xlfn.IFS(_xlpm.a="0",0,_xlpm.a="none",0,_xlpm.a="moderate",1,_xlpm.a="strong",2), _xlpm.y,_xlfn.IFS(_xlpm.b="0",0,_xlpm.b="none",0,_xlpm.b="moderate",1,_xlpm.b="strong",2), _xlpm.d,ABS(_xlpm.x-_xlpm.y), IF(_xlpm.d=0,"green",IF(_xlpm.d=1,"orange",IF(_xlpm.d=2,"red","check"))) )} -> green | EA7: {=_xlfn.LET( _xlpm.a,LOWER(TRIM(DU7&"")), _xlpm.b,LOWER(TRIM(DV7&"")), _xlpm.x,_xlfn.IFS(_xlpm.a="0",0,_xlpm.a="none",0,_xlpm.a="moderate",1,_xlpm.a="strong",2), _xlpm.y,_xlfn.IFS(_xlpm.b="0",0,_xlpm.b="none",0,_xlpm.b="moderate",1,_xlpm.b="strong",2), _xlpm.d,ABS(_xlpm.x-_xlpm.y), IF(_xlpm.d=0,"green",IF(_xlpm.d=1,"orange",IF(_xlpm.d=2,"red","check"))) )} -> green | EB7: {=_xlfn.LET( _xlpm.a,LOWER(TRIM(DW7&"")), _xlpm.b,LOWER(TRIM(DX7&"")), _xlpm.x,_xlfn.IFS(_xlpm.a="0",0,_xlpm.a="none",0,_xlpm.a="moderate",1,_xlpm.a="strong",2), _xlpm.y,_xlfn.IFS(_xlpm.b="0",0,_xlpm.b="none",0,_xlpm.b="moderate",1,_xlpm.b="strong",2), _xlpm.d,ABS(_xlpm.x-_xlpm.y), IF(_xlpm.d=0,"green",IF(_xlpm.d=1,"orange",IF(_xlpm.d=2,"red","check"))) )} -> green | ES7: =IFERROR(VALUE(_xlfn.TEXTBEFORE(_xlfn.TEXTAFTER(AC7,"""84a544d4-0c20-4f9f-bb4b-dd698a9b0c0b"":"),",")),IFERROR(VALUE(_xlfn.TEXTBEFORE(_xlfn.TEXTAFTER(AC7,"""84a544d4-0c20-4f9f-bb4b-dd698a9b0c0b"":"),"}")),IFERROR(VALUE(_xlfn.TEXTBEFORE(_xlfn.TEXTAFTER(AC7,"""784c5905-6667-4dcd-906c-8b405a6572b6"":"),",")),IFERROR(VALUE(_xlfn.TEXTBEFORE(_xlfn.TEXTAFTER(AC7,"""784c5905-6667-4dcd-906c-8b405a6572b6"":"),"}")),"")))) | ET7: =IF(OR(DF7="Strong",DF7="Moderate",DJ7="Strong",DJ7="Moderate",DN7="Strong",DN7="Moderate"),"Yes","No") -> No | EU7: =IF(AND(DE7>=3,DD7=1),"Positive concordance",IF(AND(DE7>=3,DD7>=2),"Gap",IF(AND(DE7<=2,DD7>=2),"Negative concordance","Uninformative"))) -> Uninformative | EV7: =IF(AND(DI7>=3,DH7=1),"Positive concordance",IF(AND(DI7>=3,DH7>=2),"Gap",IF(AND(DI7<=2,DH7>=2),"Negative concordance","Uninformative"))) -> Uninformative | EW7: =IF(AND(DM7>=3,DL7=1),"Positive concordance",IF(AND(DM7>=3,DL7>=2),"Gap",IF(AND(DM7<=2,DL7>=2),"Negative concordance","Uninformative"))) -> Uninformative | EX7: =IF(AND(DE7=4,DD7=1),"Positive concordance",IF(AND(DE7=4,DD7>=2),"Gap",IF(AND(DE7<=3,DD7>=2),"Negative concordance","Uninformative"))) -> Uninformative | EY7: =IF(AND(DI7=4,DH7=1),"Positive concordance",IF(AND(DI7=4,DH7>=2),"Gap",IF(AND(DI7<=3,DH7>=2),"Negative concordance","Uninformative"))) -> Uninformative | EZ7: =IF(AND(DM7=4,DL7=1),"Positive concordance",IF(AND(DM7=4,DL7>=2),"Gap",IF(AND(DM7<=3,DL7>=2),"Negative concordance","Uninformative"))) -> Uninformative | FA7: =IF(OR(EX7="Gap",EY7="Gap",EZ7="Gap"),"Yes","No") -> No
DQ8: =CR8 -> 0 | DR8: =DB8 -> 0 | DS8: =CT8 -> 0 | DT8: =DF8 -> 0 | DU8: =CV8 -> 0 | DV8: =DJ8 -> 0 | DW8: =CX8 -> 0 | DX8: =DN8 -> 0 | DY8: {=_xlfn.LET( _xlpm.a,LOWER(TRIM(DQ8&"")), _xlpm.b,LOWER(TRIM(DR8&"")), _xlpm.x,_xlfn.IFS(_xlpm.a="0",0,_xlpm.a="none",0,_xlpm.a="moderate",1,_xlpm.a="strong",2), _xlpm.y,_xlfn.IFS(_xlpm.b="0",0,_xlpm.b="none",0,_xlpm.b="moderate",1,_xlpm.b="strong",2), _xlpm.d,ABS(_xlpm.x-_xlpm.y), IF(_xlpm.d=0,"green",IF(_xlpm.d=1,"orange",IF(_xlpm.d=2,"red","check"))) )} -> green | DZ8: {=_xlfn.LET( _xlpm.a,LOWER(TRIM(DS8&"")), _xlpm.b,LOWER(TRIM(DT8&"")), _xlpm.x,_xlfn.IFS(_xlpm.a="0",0,_xlpm.a="none",0,_xlpm.a="moderate",1,_xlpm.a="strong",2), _xlpm.y,_xlfn.IFS(_xlpm.b="0",0,_xlpm.b="none",0,_xlpm.b="moderate",1,_xlpm.b="strong",2), _xlpm.d,ABS(_xlpm.x-_xlpm.y), IF(_xlpm.d=0,"green",IF(_xlpm.d=1,"orange",IF(_xlpm.d=2,"red","check"))) )} -> green | EA8: {=_xlfn.LET( _xlpm.a,LOWER(TRIM(DU8&"")), _xlpm.b,LOWER(TRIM(DV8&"")), _xlpm.x,_xlfn.IFS(_xlpm.a="0",0,_xlpm.a="none",0,_xlpm.a="moderate",1,_xlpm.a="strong",2), _xlpm.y,_xlfn.IFS(_xlpm.b="0",0,_xlpm.b="none",0,_xlpm.b="moderate",1,_xlpm.b="strong",2), _xlpm.d,ABS(_xlpm.x-_xlpm.y), IF(_xlpm.d=0,"green",IF(_xlpm.d=1,"orange",IF(_xlpm.d=2,"red","check"))) )} -> green | EB8: {=_xlfn.LET( _xlpm.a,LOWER(TRIM(DW8&"")), _xlpm.b,LOWER(TRIM(DX8&"")), _xlpm.x,_xlfn.IFS(_xlpm.a="0",0,_xlpm.a="none",0,_xlpm.a="moderate",1,_xlpm.a="strong",2), _xlpm.y,_xlfn.IFS(_xlpm.b="0",0,_xlpm.b="none",0,_xlpm.b="moderate",1,_xlpm.b="strong",2), _xlpm.d,ABS(_xlpm.x-_xlpm.y), IF(_xlpm.d=0,"green",IF(_xlpm.d=1,"orange",IF(_xlpm.d=2,"red","check"))) )} -> green | ES8: =IFERROR(VALUE(_xlfn.TEXTBEFORE(_xlfn.TEXTAFTER(AC8,"""84a544d4-0c20-4f9f-bb4b-dd698a9b0c0b"":"),",")),IFERROR(VALUE(_xlfn.TEXTBEFORE(_xlfn.TEXTAFTER(AC8,"""84a544d4-0c20-4f9f-bb4b-dd698a9b0c0b"":"),"}")),IFERROR(VALUE(_xlfn.TEXTBEFORE(_xlfn.TEXTAFTER(AC8,"""784c5905-6667-4dcd-906c-8b405a6572b6"":"),",")),IFERROR(VALUE(_xlfn.TEXTBEFORE(_xlfn.TEXTAFTER(AC8,"""784c5905-6667-4dcd-906c-8b405a6572b6"":"),"}")),"")))) | ET8: =IF(OR(DF8="Strong",DF8="Moderate",DJ8="Strong",DJ8="Moderate",DN8="Strong",DN8="Moderate"),"Yes","No") -> No | EU8: =IF(AND(DE8>=3,DD8=1),"Positive concordance",IF(AND(DE8>=3,DD8>=2),"Gap",IF(AND(DE8<=2,DD8>=2),"Negative concordance","Uninformative"))) -> Uninformative | EV8: =IF(AND(DI8>=3,DH8=1),"Positive concordance",IF(AND(DI8>=3,DH8>=2),"Gap",IF(AND(DI8<=2,DH8>=2),"Negative concordance","Uninformative"))) -> Uninformative | EW8: =IF(AND(DM8>=3,DL8=1),"Positive concordance",IF(AND(DM8>=3,DL8>=2),"Gap",IF(AND(DM8<=2,DL8>=2),"Negative concordance","Uninformative"))) -> Uninformative | EX8: =IF(AND(DE8=4,DD8=1),"Positive concordance",IF(AND(DE8=4,DD8>=2),"Gap",IF(AND(DE8<=3,DD8>=2),"Negative concordance","Uninformative"))) -> Uninformative | EY8: =IF(AND(DI8=4,DH8=1),"Positive concordance",IF(AND(DI8=4,DH8>=2),"Gap",IF(AND(DI8<=3,DH8>=2),"Negative concordance","Uninformative"))) -> Uninformative | EZ8: =IF(AND(DM8=4,DL8=1),"Positive concordance",IF(AND(DM8=4,DL8>=2),"Gap",IF(AND(DM8<=3,DL8>=2),"Negative concordance","Uninformative"))) -> Uninformative | FA8: =IF(OR(EX8="Gap",EY8="Gap",EZ8="Gap"),"Yes","No") -> No
DQ9: =CR9 -> 0 | DR9: =DB9 -> 0 | DS9: =CT9 -> 0 | DT9: =DF9 -> 0 | DU9: =CV9 -> 0 | DV9: =DJ9 -> 0 | DW9: =CX9 -> 0 | DX9: =DN9 -> 0 | DY9: {=_xlfn.LET( _xlpm.a,LOWER(TRIM(DQ9&"")), _xlpm.b,LOWER(TRIM(DR9&"")), _xlpm.x,_xlfn.IFS(_xlpm.a="0",0,_xlpm.a="none",0,_xlpm.a="moderate",1,_xlpm.a="strong",2), _xlpm.y,_xlfn.IFS(_xlpm.b="0",0,_xlpm.b="none",0,_xlpm.b="moderate",1,_xlpm.b="strong",2), _xlpm.d,ABS(_xlpm.x-_xlpm.y), IF(_xlpm.d=0,"green",IF(_xlpm.d=1,"orange",IF(_xlpm.d=2,"red","check"))) )} -> green | DZ9: {=_xlfn.LET( _xlpm.a,LOWER(TRIM(DS9&"")), _xlpm.b,LOWER(TRIM(DT9&"")), _xlpm.x,_xlfn.IFS(_xlpm.a="0",0,_xlpm.a="none",0,_xlpm.a="moderate",1,_xlpm.a="strong",2), _xlpm.y,_xlfn.IFS(_xlpm.b="0",0,_xlpm.b="none",0,_xlpm.b="moderate",1,_xlpm.b="strong",2), _xlpm.d,ABS(_xlpm.x-_xlpm.y), IF(_xlpm.d=0,"green",IF(_xlpm.d=1,"orange",IF(_xlpm.d=2,"red","check"))) )} -> green | EA9: {=_xlfn.LET( _xlpm.a,LOWER(TRIM(DU9&"")), _xlpm.b,LOWER(TRIM(DV9&"")), _xlpm.x,_xlfn.IFS(_xlpm.a="0",0,_xlpm.a="none",0,_xlpm.a="moderate",1,_xlpm.a="strong",2), _xlpm.y,_xlfn.IFS(_xlpm.b="0",0,_xlpm.b="none",0,_xlpm.b="moderate",1,_xlpm.b="strong",2), _xlpm.d,ABS(_xlpm.x-_xlpm.y), IF(_xlpm.d=0,"green",IF(_xlpm.d=1,"orange",IF(_xlpm.d=2,"red","check"))) )} -> green | EB9: {=_xlfn.LET( _xlpm.a,LOWER(TRIM(DW9&"")), _xlpm.b,LOWER(TRIM(DX9&"")), _xlpm.x,_xlfn.IFS(_xlpm.a="0",0,_xlpm.a="none",0,_xlpm.a="moderate",1,_xlpm.a="strong",2), _xlpm.y,_xlfn.IFS(_xlpm.b="0",0,_xlpm.b="none",0,_xlpm.b="moderate",1,_xlpm.b="strong",2), _xlpm.d,ABS(_xlpm.x-_xlpm.y), IF(_xlpm.d=0,"green",IF(_xlpm.d=1,"orange",IF(_xlpm.d=2,"red","check"))) )} -> green | ES9: =IFERROR(VALUE(_xlfn.TEXTBEFORE(_xlfn.TEXTAFTER(AC9,"""84a544d4-0c20-4f9f-bb4b-dd698a9b0c0b"":"),",")),IFERROR(VALUE(_xlfn.TEXTBEFORE(_xlfn.TEXTAFTER(AC9,"""84a544d4-0c20-4f9f-bb4b-dd698a9b0c0b"":"),"}")),IFERROR(VALUE(_xlfn.TEXTBEFORE(_xlfn.TEXTAFTER(AC9,"""784c5905-6667-4dcd-906c-8b405a6572b6"":"),",")),IFERROR(VALUE(_xlfn.TEXTBEFORE(_xlfn.TEXTAFTER(AC9,"""784c5905-6667-4dcd-906c-8b405a6572b6"":"),"}")),"")))) | ET9: =IF(OR(DF9="Strong",DF9="Moderate",DJ9="Strong",DJ9="Moderate",DN9="Strong",DN9="Moderate"),"Yes","No") -> No | EU9: =IF(AND(DE9>=3,DD9=1),"Positive concordance",IF(AND(DE9>=3,DD9>=2),"Gap",IF(AND(DE9<=2,DD9>=2),"Negative concordance","Uninformative"))) -> Uninformative | EV9: =IF(AND(DI9>=3,DH9=1),"Positive concordance",IF(AND(DI9>=3,DH9>=2),"Gap",IF(AND(DI9<=2,DH9>=2),"Negative concordance","Uninformative"))) -> Uninformative | EW9: =IF(AND(DM9>=3,DL9=1),"Positive concordance",IF(AND(DM9>=3,DL9>=2),"Gap",IF(AND(DM9<=2,DL9>=2),"Negative concordance","Uninformative"))) -> Uninformative | EX9: =IF(AND(DE9=4,DD9=1),"Positive concordance",IF(AND(DE9=4,DD9>=2),"Gap",IF(AND(DE9<=3,DD9>=2),"Negative concordance","Uninformative"))) -> Uninformative | EY9: =IF(AND(DI9=4,DH9=1),"Positive concordance",IF(AND(DI9=4,DH9>=2),"Gap",IF(AND(DI9<=3,DH9>=2),"Negative concordance","Uninformative"))) -> Uninformative | EZ9: =IF(AND(DM9=4,DL9=1),"Positive concordance",IF(AND(DM9=4,DL9>=2),"Gap",IF(AND(DM9<=3,DL9>=2),"Negative concordance","Uninformative"))) -> Uninformative | FA9: =IF(OR(EX9="Gap",EY9="Gap",EZ9="Gap"),"Yes","No") -> No
DQ10: =CR10 -> 0 | DR10: =DB10 -> 0 | DS10: =CT10 -> 0 | DT10: =DF10 -> 0 | DU10: =CV10 -> 0 | DV10: =DJ10 -> 0 | DW10: =CX10 -> 0 | DX10: =DN10 -> 0 | DY10: {=_xlfn.LET( _xlpm.a,LOWER(TRIM(DQ10&"")), _xlpm.b,LOWER(TRIM(DR10&"")), _xlpm.x,_xlfn.IFS(_xlpm.a="0",0,_xlpm.a="none",0,_xlpm.a="moderate",1,_xlpm.a="strong",2), _xlpm.y,_xlfn.IFS(_xlpm.b="0",0,_xlpm.b="none",0,_xlpm.b="moderate",1,_xlpm.b="strong",2), _xlpm.d,ABS(_xlpm.x-_xlpm.y), IF(_xlpm.d=0,"green",IF(_xlpm.d=1,"orange",IF(_xlpm.d=2,"red","check"))) )} -> green | DZ10: {=_xlfn.LET( _xlpm.a,LOWER(TRIM(DS10&"")), _xlpm.b,LOWER(TRIM(DT10&"")), _xlpm.x,_xlfn.IFS(_xlpm.a="0",0,_xlpm.a="none",0,_xlpm.a="moderate",1,_xlpm.a="strong",2), _xlpm.y,_xlfn.IFS(_xlpm.b="0",0,_xlpm.b="none",0,_xlpm.b="moderate",1,_xlpm.b="strong",2), _xlpm.d,ABS(_xlpm.x-_xlpm.y), IF(_xlpm.d=0,"green",IF(_xlpm.d=1,"orange",IF(_xlpm.d=2,"red","check"))) )} -> green | EA10: {=_xlfn.LET( _xlpm.a,LOWER(TRIM(DU10&"")), _xlpm.b,LOWER(TRIM(DV10&"")), _xlpm.x,_xlfn.IFS(_xlpm.a="0",0,_xlpm.a="none",0,_xlpm.a="moderate",1,_xlpm.a="strong",2), _xlpm.y,_xlfn.IFS(_xlpm.b="0",0,_xlpm.b="none",0,_xlpm.b="moderate",1,_xlpm.b="strong",2), _xlpm.d,ABS(_xlpm.x-_xlpm.y), IF(_xlpm.d=0,"green",IF(_xlpm.d=1,"orange",IF(_xlpm.d=2,"red","check"))) )} -> green | EB10: {=_xlfn.LET( _xlpm.a,LOWER(TRIM(DW10&"")), _xlpm.b,LOWER(TRIM(DX10&"")), _xlpm.x,_xlfn.IFS(_xlpm.a="0",0,_xlpm.a="none",0,_xlpm.a="moderate",1,_xlpm.a="strong",2), _xlpm.y,_xlfn.IFS(_xlpm.b="0",0,_xlpm.b="none",0,_xlpm.b="moderate",1,_xlpm.b="strong",2), _xlpm.d,ABS(_xlpm.x-_xlpm.y), IF(_xlpm.d=0,"green",IF(_xlpm.d=1,"orange",IF(_xlpm.d=2,"red","check"))) )} -> green | ES10: =IFERROR(VALUE(_xlfn.TEXTBEFORE(_xlfn.TEXTAFTER(AC10,"""84a544d4-0c20-4f9f-bb4b-dd698a9b0c0b"":"),",")),IFERROR(VALUE(_xlfn.TEXTBEFORE(_xlfn.TEXTAFTER(AC10,"""84a544d4-0c20-4f9f-bb4b-dd698a9b0c0b"":"),"}")),IFERROR(VALUE(_xlfn.TEXTBEFORE(_xlfn.TEXTAFTER(AC10,"""784c5905-6667-4dcd-906c-8b405a6572b6"":"),",")),IFERROR(VALUE(_xlfn.TEXTBEFORE(_xlfn.TEXTAFTER(AC10,"""784c5905-6667-4dcd-906c-8b405a6572b6"":"),"}")),"")))) | ET10: =IF(OR(DF10="Strong",DF10="Moderate",DJ10="Strong",DJ10="Moderate",DN10="Strong",DN10="Moderate"),"Yes","No") -> No | EU10: =IF(AND(DE10>=3,DD10=1),"Positive concordance",IF(AND(DE10>=3,DD10>=2),"Gap",IF(AND(DE10<=2,DD10>=2),"Negative concordance","Uninformative"))) -> Uninformative | EV10: =IF(AND(DI10>=3,DH10=1),"Positive concordance",IF(AND(DI10>=3,DH10>=2),"Gap",IF(AND(DI10<=2,DH10>=2),"Negative concordance","Uninformative"))) -> Uninformative | EW10: =IF(AND(DM10>=3,DL10=1),"Positive concordance",IF(AND(DM10>=3,DL10>=2),"Gap",IF(AND(DM10<=2,DL10>=2),"Negative concordance","Uninformative"))) -> Uninformative | EX10: =IF(AND(DE10=4,DD10=1),"Positive concordance",IF(AND(DE10=4,DD10>=2),"Gap",IF(AND(DE10<=3,DD10>=2),"Negative concordance","Uninformative"))) -> Uninformative | EY10: =IF(AND(DI10=4,DH10=1),"Positive concordance",IF(AND(DI10=4,DH10>=2),"Gap",IF(AND(DI10<=3,DH10>=2),"Negative concordance","Uninformative"))) -> Uninformative | EZ10: =IF(AND(DM10=4,DL10=1),"Positive concordance",IF(AND(DM10=4,DL10>=2),"Gap",IF(AND(DM10<=3,DL10>=2),"Negative concordance","Uninformative"))) -> Uninformative | FA10: =IF(OR(EX10="Gap",EY10="Gap",EZ10="Gap"),"Yes","No") -> No
DQ11: =CR11 -> 0 | DR11: =DB11 -> 0 | DS11: =CT11 -> 0 | DT11: =DF11 -> 0 | DU11: =CV11 -> 0 | DV11: =DJ11 -> 0 | DW11: =CX11 -> 0 | DX11: =DN11 -> 0 | DY11: {=_xlfn.LET( _xlpm.a,LOWER(TRIM(DQ11&"")), _xlpm.b,LOWER(TRIM(DR11&"")), _xlpm.x,_xlfn.IFS(_xlpm.a="0",0,_xlpm.a="none",0,_xlpm.a="moderate",1,_xlpm.a="strong",2), _xlpm.y,_xlfn.IFS(_xlpm.b="0",0,_xlpm.b="none",0,_xlpm.b="moderate",1,_xlpm.b="strong",2), _xlpm.d,ABS(_xlpm.x-_xlpm.y), IF(_xlpm.d=0,"green",IF(_xlpm.d=1,"orange",IF(_xlpm.d=2,"red","check"))) )} -> green | DZ11: {=_xlfn.LET( _xlpm.a,LOWER(TRIM(DS11&"")), _xlpm.b,LOWER(TRIM(DT11&"")), _xlpm.x,_xlfn.IFS(_xlpm.a="0",0,_xlpm.a="none",0,_xlpm.a="moderate",1,_xlpm.a="strong",2), _xlpm.y,_xlfn.IFS(_xlpm.b="0",0,_xlpm.b="none",0,_xlpm.b="moderate",1,_xlpm.b="strong",2), _xlpm.d,ABS(_xlpm.x-_xlpm.y), IF(_xlpm.d=0,"green",IF(_xlpm.d=1,"orange",IF(_xlpm.d=2,"red","check"))) )} -> green | EA11: {=_xlfn.LET( _xlpm.a,LOWER(TRIM(DU11&"")), _xlpm.b,LOWER(TRIM(DV11&"")), _xlpm.x,_xlfn.IFS(_xlpm.a="0",0,_xlpm.a="none",0,_xlpm.a="moderate",1,_xlpm.a="strong",2), _xlpm.y,_xlfn.IFS(_xlpm.b="0",0,_xlpm.b="none",0,_xlpm.b="moderate",1,_xlpm.b="strong",2), _xlpm.d,ABS(_xlpm.x-_xlpm.y), IF(_xlpm.d=0,"green",IF(_xlpm.d=1,"orange",IF(_xlpm.d=2,"red","check"))) )} -> green | EB11: {=_xlfn.LET( _xlpm.a,LOWER(TRIM(DW11&"")), _xlpm.b,LOWER(TRIM(DX11&"")), _xlpm.x,_xlfn.IFS(_xlpm.a="0",0,_xlpm.a="none",0,_xlpm.a="moderate",1,_xlpm.a="strong",2), _xlpm.y,_xlfn.IFS(_xlpm.b="0",0,_xlpm.b="none",0,_xlpm.b="moderate",1,_xlpm.b="strong",2), _xlpm.d,ABS(_xlpm.x-_xlpm.y), IF(_xlpm.d=0,"green",IF(_xlpm.d=1,"orange",IF(_xlpm.d=2,"red","check"))) )} -> green | ES11: =IFERROR(VALUE(_xlfn.TEXTBEFORE(_xlfn.TEXTAFTER(AC11,"""84a544d4-0c20-4f9f-bb4b-dd698a9b0c0b"":"),",")),IFERROR(VALUE(_xlfn.TEXTBEFORE(_xlfn.TEXTAFTER(AC11,"""84a544d4-0c20-4f9f-bb4b-dd698a9b0c0b"":"),"}")),IFERROR(VALUE(_xlfn.TEXTBEFORE(_xlfn.TEXTAFTER(AC11,"""784c5905-6667-4dcd-906c-8b405a6572b6"":"),",")),IFERROR(VALUE(_xlfn.TEXTBEFORE(_xlfn.TEXTAFTER(AC11,"""784c5905-6667-4dcd-906c-8b405a6572b6"":"),"}")),"")))) | ET11: =IF(OR(DF11="Strong",DF11="Moderate",DJ11="Strong",DJ11="Moderate",DN11="Strong",DN11="Moderate"),"Yes","No") -> No | EU11: =IF(AND(DE11>=3,DD11=1),"Positive concordance",IF(AND(DE11>=3,DD11>=2),"Gap",IF(AND(DE11<=2,DD11>=2),"Negative concordance","Uninformative"))) -> Uninformative | EV11: =IF(AND(DI11>=3,DH11=1),"Positive concordance",IF(AND(DI11>=3,DH11>=2),"Gap",IF(AND(DI11<=2,DH11>=2),"Negative concordance","Uninformative"))) -> Uninformative | EW11: =IF(AND(DM11>=3,DL11=1),"Positive concordance",IF(AND(DM11>=3,DL11>=2),"Gap",IF(AND(DM11<=2,DL11>=2),"Negative concordance","Uninformative"))) -> Uninformative | EX11: =IF(AND(DE11=4,DD11=1),"Positive concordance",IF(AND(DE11=4,DD11>=2),"Gap",IF(AND(DE11<=3,DD11>=2),"Negative concordance","Uninformative"))) -> Uninformative | EY11: =IF(AND(DI11=4,DH11=1),"Positive concordance",IF(AND(DI11=4,DH11>=2),"Gap",IF(AND(DI11<=3,DH11>=2),"Negative concordance","Uninformative"))) -> Uninformative | EZ11: =IF(AND(DM11=4,DL11=1),"Positive concordance",IF(AND(DM11=4,DL11>=2),"Gap",IF(AND(DM11<=3,DL11>=2),"Negative concordance","Uninformative"))) -> Uninformative | FA11: =IF(OR(EX11="Gap",EY11="Gap",EZ11="Gap"),"Yes","No") -> No
DQ12: =CR12 -> 0 | DR12: =DB12 -> 0 | DS12: =CT12 -> 0 | DT12: =DF12 -> 0 | DU12: =CV12 -> 0 | DV12: =DJ12 -> 0 | DW12: =CX12 -> 0 | DX12: =DN12 -> 0 | DY12: {=_xlfn.LET( _xlpm.a,LOWER(TRIM(DQ12&"")), _xlpm.b,LOWER(TRIM(DR12&"")), _xlpm.x,_xlfn.IFS(_xlpm.a="0",0,_xlpm.a="none",0,_xlpm.a="moderate",1,_xlpm.a="strong",2), _xlpm.y,_xlfn.IFS(_xlpm.b="0",0,_xlpm.b="none",0,_xlpm.b="moderate",1,_xlpm.b="strong",2), _xlpm.d,ABS(_xlpm.x-_xlpm.y), IF(_xlpm.d=0,"green",IF(_xlpm.d=1,"orange",IF(_xlpm.d=2,"red","check"))) )} -> green | DZ12: {=_xlfn.LET( _xlpm.a,LOWER(TRIM(DS12&"")), _xlpm.b,LOWER(TRIM(DT12&"")), _xlpm.x,_xlfn.IFS(_xlpm.a="0",0,_xlpm.a="none",0,_xlpm.a="moderate",1,_xlpm.a="strong",2), _xlpm.y,_xlfn.IFS(_xlpm.b="0",0,_xlpm.b="none",0,_xlpm.b="moderate",1,_xlpm.b="strong",2), _xlpm.d,ABS(_xlpm.x-_xlpm.y), IF(_xlpm.d=0,"green",IF(_xlpm.d=1,"orange",IF(_xlpm.d=2,"red","check"))) )} -> green | EA12: {=_xlfn.LET( _xlpm.a,LOWER(TRIM(DU12&"")), _xlpm.b,LOWER(TRIM(DV12&"")), _xlpm.x,_xlfn.IFS(_xlpm.a="0",0,_xlpm.a="none",0,_xlpm.a="moderate",1,_xlpm.a="strong",2), _xlpm.y,_xlfn.IFS(_xlpm.b="0",0,_xlpm.b="none",0,_xlpm.b="moderate",1,_xlpm.b="strong",2), _xlpm.d,ABS(_xlpm.x-_xlpm.y), IF(_xlpm.d=0,"green",IF(_xlpm.d=1,"orange",IF(_xlpm.d=2,"red","check"))) )} -> green | EB12: {=_xlfn.LET( _xlpm.a,LOWER(TRIM(DW12&"")), _xlpm.b,LOWER(TRIM(DX12&"")), _xlpm.x,_xlfn.IFS(_xlpm.a="0",0,_xlpm.a="none",0,_xlpm.a="moderate",1,_xlpm.a="strong",2), _xlpm.y,_xlfn.IFS(_xlpm.b="0",0,_xlpm.b="none",0,_xlpm.b="moderate",1,_xlpm.b="strong",2), _xlpm.d,ABS(_xlpm.x-_xlpm.y), IF(_xlpm.d=0,"green",IF(_xlpm.d=1,"orange",IF(_xlpm.d=2,"red","check"))) )} -> green | ES12: =IFERROR(VALUE(_xlfn.TEXTBEFORE(_xlfn.TEXTAFTER(AC12,"""84a544d4-0c20-4f9f-bb4b-dd698a9b0c0b"":"),",")),IFERROR(VALUE(_xlfn.TEXTBEFORE(_xlfn.TEXTAFTER(AC12,"""84a544d4-0c20-4f9f-bb4b-dd698a9b0c0b"":"),"}")),IFERROR(VALUE(_xlfn.TEXTBEFORE(_xlfn.TEXTAFTER(AC12,"""784c5905-6667-4dcd-906c-8b405a6572b6"":"),",")),IFERROR(VALUE(_xlfn.TEXTBEFORE(_xlfn.TEXTAFTER(AC12,"""784c5905-6667-4dcd-906c-8b405a6572b6"":"),"}")),"")))) | ET12: =IF(OR(DF12="Strong",DF12="Moderate",DJ12="Strong",DJ12="Moderate",DN12="Strong",DN12="Moderate"),"Yes","No") -> No | EU12: =IF(AND(DE12>=3,DD12=1),"Positive concordance",IF(AND(DE12>=3,DD12>=2),"Gap",IF(AND(DE12<=2,DD12>=2),"Negative concordance","Uninformative"))) -> Uninformative | EV12: =IF(AND(DI12>=3,DH12=1),"Positive concordance",IF(AND(DI12>=3,DH12>=2),"Gap",IF(AND(DI12<=2,DH12>=2),"Negative concordance","Uninformative"))) -> Uninformative | EW12: =IF(AND(DM12>=3,DL12=1),"Positive concordance",IF(AND(DM12>=3,DL12>=2),"Gap",IF(AND(DM12<=2,DL12>=2),"Negative concordance","Uninformative"))) -> Uninformative | EX12: =IF(AND(DE12=4,DD12=1),"Positive concordance",IF(AND(DE12=4,DD12>=2),"Gap",IF(AND(DE12<=3,DD12>=2),"Negative concordance","Uninformative"))) -> Uninformative | EY12: =IF(AND(DI12=4,DH12=1),"Positive concordance",IF(AND(DI12=4,DH12>=2),"Gap",IF(AND(DI12<=3,DH12>=2),"Negative concordance","Uninformative"))) -> Uninformative | EZ12: =IF(AND(DM12=4,DL12=1),"Positive concordance",IF(AND(DM12=4,DL12>=2),"Gap",IF(AND(DM12<=3,DL12>=2),"Negative concordance","Uninformative"))) -> Uninformative | FA12: =IF(OR(EX12="Gap",EY12="Gap",EZ12="Gap"),"Yes","No") -> No
DQ13: =CR13 -> 0 | DR13: =DB13 -> 0 | DS13: =CT13 -> 0 | DT13: =DF13 -> 0 | DU13: =CV13 -> 0 | DV13: =DJ13 -> 0 | DW13: =CX13 -> 0 | DX13: =DN13 -> 0 | DY13: {=_xlfn.LET( _xlpm.a,LOWER(TRIM(DQ13&"")), _xlpm.b,LOWER(TRIM(DR13&"")), _xlpm.x,_xlfn.IFS(_xlpm.a="0",0,_xlpm.a="none",0,_xlpm.a="moderate",1,_xlpm.a="strong",2), _xlpm.y,_xlfn.IFS(_xlpm.b="0",0,_xlpm.b="none",0,_xlpm.b="moderate",1,_xlpm.b="strong",2), _xlpm.d,ABS(_xlpm.x-_xlpm.y), IF(_xlpm.d=0,"green",IF(_xlpm.d=1,"orange",IF(_xlpm.d=2,"red","check"))) )} -> green | DZ13: {=_xlfn.LET( _xlpm.a,LOWER(TRIM(DS13&"")), _xlpm.b,LOWER(TRIM(DT13&"")), _xlpm.x,_xlfn.IFS(_xlpm.a="0",0,_xlpm.a="none",0,_xlpm.a="moderate",1,_xlpm.a="strong",2), _xlpm.y,_xlfn.IFS(_xlpm.b="0",0,_xlpm.b="none",0,_xlpm.b="moderate",1,_xlpm.b="strong",2), _xlpm.d,ABS(_xlpm.x-_xlpm.y), IF(_xlpm.d=0,"green",IF(_xlpm.d=1,"orange",IF(_xlpm.d=2,"red","check"))) )} -> green | EA13: {=_xlfn.LET( _xlpm.a,LOWER(TRIM(DU13&"")), _xlpm.b,LOWER(TRIM(DV13&"")), _xlpm.x,_xlfn.IFS(_xlpm.a="0",0,_xlpm.a="none",0,_xlpm.a="moderate",1,_xlpm.a="strong",2), _xlpm.y,_xlfn.IFS(_xlpm.b="0",0,_xlpm.b="none",0,_xlpm.b="moderate",1,_xlpm.b="strong",2), _xlpm.d,ABS(_xlpm.x-_xlpm.y), IF(_xlpm.d=0,"green",IF(_xlpm.d=1,"orange",IF(_xlpm.d=2,"red","check"))) )} -> green | EB13: {=_xlfn.LET( _xlpm.a,LOWER(TRIM(DW13&"")), _xlpm.b,LOWER(TRIM(DX13&"")), _xlpm.x,_xlfn.IFS(_xlpm.a="0",0,_xlpm.a="none",0,_xlpm.a="moderate",1,_xlpm.a="strong",2), _xlpm.y,_xlfn.IFS(_xlpm.b="0",0,_xlpm.b="none",0,_xlpm.b="moderate",1,_xlpm.b="strong",2), _xlpm.d,ABS(_xlpm.x-_xlpm.y), IF(_xlpm.d=0,"green",IF(_xlpm.d=1,"orange",IF(_xlpm.d=2,"red","check"))) )} -> green | ES13: =IFERROR(VALUE(_xlfn.TEXTBEFORE(_xlfn.TEXTAFTER(AC13,"""84a544d4-0c20-4f9f-bb4b-dd698a9b0c0b"":"),",")),IFERROR(VALUE(_xlfn.TEXTBEFORE(_xlfn.TEXTAFTER(AC13,"""84a544d4-0c20-4f9f-bb4b-dd698a9b0c0b"":"),"}")),IFERROR(VALUE(_xlfn.TEXTBEFORE(_xlfn.TEXTAFTER(AC13,"""784c5905-6667-4dcd-906c-8b405a6572b6"":"),",")),IFERROR(VALUE(_xlfn.TEXTBEFORE(_xlfn.TEXTAFTER(AC13,"""784c5905-6667-4dcd-906c-8b405a6572b6"":"),"}")),"")))) | ET13: =IF(OR(DF13="Strong",DF13="Moderate",DJ13="Strong",DJ13="Moderate",DN13="Strong",DN13="Moderate"),"Yes","No") -> No | EU13: =IF(AND(DE13>=3,DD13=1),"Positive concordance",IF(AND(DE13>=3,DD13>=2),"Gap",IF(AND(DE13<=2,DD13>=2),"Negative concordance","Uninformative"))) -> Uninformative | EV13: =IF(AND(DI13>=3,DH13=1),"Positive concordance",IF(AND(DI13>=3,DH13>=2),"Gap",IF(AND(DI13<=2,DH13>=2),"Negative concordance","Uninformative"))) -> Uninformative | EW13: =IF(AND(DM13>=3,DL13=1),"Positive concordance",IF(AND(DM13>=3,DL13>=2),"Gap",IF(AND(DM13<=2,DL13>=2),"Negative concordance","Uninformative"))) -> Uninformative | EX13: =IF(AND(DE13=4,DD13=1),"Positive concordance",IF(AND(DE13=4,DD13>=2),"Gap",IF(AND(DE13<=3,DD13>=2),"Negative concordance","Uninformative"))) -> Uninformative | EY13: =IF(AND(DI13=4,DH13=1),"Positive concordance",IF(AND(DI13=4,DH13>=2),"Gap",IF(AND(DI13<=3,DH13>=2),"Negative concordance","Uninformative"))) -> Uninformative | EZ13: =IF(AND(DM13=4,DL13=1),"Positive concordance",IF(AND(DM13=4,DL13>=2),"Gap",IF(AND(DM13<=3,DL13>=2),"Negative concordance","Uninformative"))) -> Uninformative | FA13: =IF(OR(EX13="Gap",EY13="Gap",EZ13="Gap"),"Yes","No") -> No
DQ14: =CR14 -> 0 | DR14: =DB14 -> 0 | DS14: =CT14 -> 0 | DT14: =DF14 -> 0 | DU14: =CV14 -> 0 | DV14: =DJ14 -> 0 | DW14: =CX14 -> 0 | DX14: =DN14 -> 0 | DY14: {=_xlfn.LET( _xlpm.a,LOWER(TRIM(DQ14&"")), _xlpm.b,LOWER(TRIM(DR14&"")), _xlpm.x,_xlfn.IFS(_xlpm.a="0",0,_xlpm.a="none",0,_xlpm.a="moderate",1,_xlpm.a="strong",2), _xlpm.y,_xlfn.IFS(_xlpm.b="0",0,_xlpm.b="none",0,_xlpm.b="moderate",1,_xlpm.b="strong",2), _xlpm.d,ABS(_xlpm.x-_xlpm.y), IF(_xlpm.d=0,"green",IF(_xlpm.d=1,"orange",IF(_xlpm.d=2,"red","check"))) )} -> green | DZ14: {=_xlfn.LET( _xlpm.a,LOWER(TRIM(DS14&"")), _xlpm.b,LOWER(TRIM(DT14&"")), _xlpm.x,_xlfn.IFS(_xlpm.a="0",0,_xlpm.a="none",0,_xlpm.a="moderate",1,_xlpm.a="strong",2), _xlpm.y,_xlfn.IFS(_xlpm.b="0",0,_xlpm.b="none",0,_xlpm.b="moderate",1,_xlpm.b="strong",2), _xlpm.d,ABS(_xlpm.x-_xlpm.y), IF(_xlpm.d=0,"green",IF(_xlpm.d=1,"orange",IF(_xlpm.d=2,"red","check"))) )} -> green | EA14: {=_xlfn.LET( _xlpm.a,LOWER(TRIM(DU14&"")), _xlpm.b,LOWER(TRIM(DV14&"")), _xlpm.x,_xlfn.IFS(_xlpm.a="0",0,_xlpm.a="none",0,_xlpm.a="moderate",1,_xlpm.a="strong",2), _xlpm.y,_xlfn.IFS(_xlpm.b="0",0,_xlpm.b="none",0,_xlpm.b="moderate",1,_xlpm.b="strong",2), _xlpm.d,ABS(_xlpm.x-_xlpm.y), IF(_xlpm.d=0,"green",IF(_xlpm.d=1,"orange",IF(_xlpm.d=2,"red","check"))) )} -> green | EB14: {=_xlfn.LET( _xlpm.a,LOWER(TRIM(DW14&"")), _xlpm.b,LOWER(TRIM(DX14&"")), _xlpm.x,_xlfn.IFS(_xlpm.a="0",0,_xlpm.a="none",0,_xlpm.a="moderate",1,_xlpm.a="strong",2), _xlpm.y,_xlfn.IFS(_xlpm.b="0",0,_xlpm.b="none",0,_xlpm.b="moderate",1,_xlpm.b="strong",2), _xlpm.d,ABS(_xlpm.x-_xlpm.y), IF(_xlpm.d=0,"green",IF(_xlpm.d=1,"orange",IF(_xlpm.d=2,"red","check"))) )} -> green | ES14: =IFERROR(VALUE(_xlfn.TEXTBEFORE(_xlfn.TEXTAFTER(AC14,"""84a544d4-0c20-4f9f-bb4b-dd698a9b0c0b"":"),",")),IFERROR(VALUE(_xlfn.TEXTBEFORE(_xlfn.TEXTAFTER(AC14,"""84a544d4-0c20-4f9f-bb4b-dd698a9b0c0b"":"),"}")),IFERROR(VALUE(_xlfn.TEXTBEFORE(_xlfn.TEXTAFTER(AC14,"""784c5905-6667-4dcd-906c-8b405a6572b6"":"),",")),IFERROR(VALUE(_xlfn.TEXTBEFORE(_xlfn.TEXTAFTER(AC14,"""784c5905-6667-4dcd-906c-8b405a6572b6"":"),"}")),"")))) | ET14: =IF(OR(DF14="Strong",DF14="Moderate",DJ14="Strong",DJ14="Moderate",DN14="Strong",DN14="Moderate"),"Yes","No") -> No | EU14: =IF(AND(DE14>=3,DD14=1),"Positive concordance",IF(AND(DE14>=3,DD14>=2),"Gap",IF(AND(DE14<=2,DD14>=2),"Negative concordance","Uninformative"))) -> Uninformative | EV14: =IF(AND(DI14>=3,DH14=1),"Positive concordance",IF(AND(DI14>=3,DH14>=2),"Gap",IF(AND(DI14<=2,DH14>=2),"Negative concordance","Uninformative"))) -> Uninformative | EW14: =IF(AND(DM14>=3,DL14=1),"Positive concordance",IF(AND(DM14>=3,DL14>=2),"Gap",IF(AND(DM14<=2,DL14>=2),"Negative concordance","Uninformative"))) -> Uninformative | EX14: =IF(AND(DE14=4,DD14=1),"Positive concordance",IF(AND(DE14=4,DD14>=2),"Gap",IF(AND(DE14<=3,DD14>=2),"Negative concordance","Uninformative"))) -> Uninformative | EY14: =IF(AND(DI14=4,DH14=1),"Positive concordance",IF(AND(DI14=4,DH14>=2),"Gap",IF(AND(DI14<=3,DH14>=2),"Negative concordance","Uninformative"))) -> Uninformative | EZ14: =IF(AND(DM14=4,DL14=1),"Positive concordance",IF(AND(DM14=4,DL14>=2),"Gap",IF(AND(DM14<=3,DL14>=2),"Negative concordance","Uninformative"))) -> Uninformative | FA14: =IF(OR(EX14="Gap",EY14="Gap",EZ14="Gap"),"Yes","No") -> No
... DQ105: =CR105 -> 0 | DR105: =DB105 -> 0 | DS105: =CT105 -> 0 | DT105: =DF105 -> 0 | DU105: =CV105 -> 0 | DV105: =DJ105 -> 0 | DW105: =CX105 -> 0 | DX105: =DN105 -> 0 | DY105: {=_xlfn.LET( _xlpm.a,LOWER(TRIM(DQ105&"")), _xlpm.b,LOWER(TRIM(DR105&"")), _xlpm.x,_xlfn.IFS(_xlpm.a="0",0,_xlpm.a="none",0,_xlpm.a="moderate",1,_xlpm.a="strong",2), _xlpm.y,_xlfn.IFS(_xlpm.b="0",0,_xlpm.b="none",0,_xlpm.b="moderate",1,_xlpm.b="strong",2), _xlpm.d,ABS(_xlpm.x-_xlpm.y), IF(_xlpm.d=0,"green",IF(_xlpm.d=1,"orange",IF(_xlpm.d=2,"red","check"))) )} -> green | DZ105: {=_xlfn.LET( _xlpm.a,LOWER(TRIM(DS105&"")), _xlpm.b,LOWER(TRIM(DT105&"")), _xlpm.x,_xlfn.IFS(_xlpm.a="0",0,_xlpm.a="none",0,_xlpm.a="moderate",1,_xlpm.a="strong",2), _xlpm.y,_xlfn.IFS(_xlpm.b="0",0,_xlpm.b="none",0,_xlpm.b="moderate",1,_xlpm.b="strong",2), _xlpm.d,ABS(_xlpm.x-_xlpm.y), IF(_xlpm.d=0,"green",IF(_xlpm.d=1,"orange",IF(_xlpm.d=2,"red","check"))) )} -> green | EA105: {=_xlfn.LET( _xlpm.a,LOWER(TRIM(DU105&"")), _xlpm.b,LOWER(TRIM(DV105&"")), _xlpm.x,_xlfn.IFS(_xlpm.a="0",0,_xlpm.a="none",0,_xlpm.a="moderate",1,_xlpm.a="strong",2), _xlpm.y,_xlfn.IFS(_xlpm.b="0",0,_xlpm.b="none",0,_xlpm.b="moderate",1,_xlpm.b="strong",2), _xlpm.d,ABS(_xlpm.x-_xlpm.y), IF(_xlpm.d=0,"green",IF(_xlpm.d=1,"orange",IF(_xlpm.d=2,"red","check"))) )} -> green | EB105: {=_xlfn.LET( _xlpm.a,LOWER(TRIM(DW105&"")), _xlpm.b,LOWER(TRIM(DX105&"")), _xlpm.x,_xlfn.IFS(_xlpm.a="0",0,_xlpm.a="none",0,_xlpm.a="moderate",1,_xlpm.a="strong",2), _xlpm.y,_xlfn.IFS(_xlpm.b="0",0,_xlpm.b="none",0,_xlpm.b="moderate",1,_xlpm.b="strong",2), _xlpm.d,ABS(_xlpm.x-_xlpm.y), IF(_xlpm.d=0,"green",IF(_xlpm.d=1,"orange",IF(_xlpm.d=2,"red","check"))) )} -> green | ES105: =IFERROR(VALUE(_xlfn.TEXTBEFORE(_xlfn.TEXTAFTER(AC105,"""84a544d4-0c20-4f9f-bb4b-dd698a9b0c0b"":"),",")),IFERROR(VALUE(_xlfn.TEXTBEFORE(_xlfn.TEXTAFTER(AC105,"""84a544d4-0c20-4f9f-bb4b-dd698a9b0c0b"":"),"}")),IFERROR(VALUE(_xlfn.TEXTBEFORE(_xlfn.TEXTAFTER(AC105,"""784c5905-6667-4dcd-906c-8b405a6572b6"":"),",")),IFERROR(VALUE(_xlfn.TEXTBEFORE(_xlfn.TEXTAFTER(AC105,"""784c5905-6667-4dcd-906c-8b405a6572b6"":"),"}")),"")))) | ET105: =IF(OR(DF105="Strong",DF105="Moderate",DJ105="Strong",DJ105="Moderate",DN105="Strong",DN105="Moderate"),"Yes","No") -> No | EU105: =IF(AND(DE105>=3,DD105=1),"Positive concordance",IF(AND(DE105>=3,DD105>=2),"Gap",IF(AND(DE105<=2,DD105>=2),"Negative concordance","Uninformative"))) -> Uninformative | EV105: =IF(AND(DI105>=3,DH105=1),"Positive concordance",IF(AND(DI105>=3,DH105>=2),"Gap",IF(AND(DI105<=2,DH105>=2),"Negative concordance","Uninformative"))) -> Uninformative | EW105: =IF(AND(DM105>=3,DL105=1),"Positive concordance",IF(AND(DM105>=3,DL105>=2),"Gap",IF(AND(DM105<=2,DL105>=2),"Negative concordance","Uninformative"))) -> Uninformative | EX105: =IF(AND(DE105=4,DD105=1),"Positive concordance",IF(AND(DE105=4,DD105>=2),"Gap",IF(AND(DE105<=3,DD105>=2),"Negative concordance","Uninformative"))) -> Uninformative | EY105: =IF(AND(DI105=4,DH105=1),"Positive concordance",IF(AND(DI105=4,DH105>=2),"Gap",IF(AND(DI105<=3,DH105>=2),"Negative concordance","Uninformative"))) -> Uninformative | EZ105: =IF(AND(DM105=4,DL105=1),"Positive concordance",IF(AND(DM105=4,DL105>=2),"Gap",IF(AND(DM105<=3,DL105>=2),"Negative concordance","Uninformative"))) -> Uninformative | FA105: =IF(OR(EX105="Gap",EY105="Gap",EZ105="Gap"),"Yes","No") -> No

Sheet Qualitative Analysis
A1: Session_ID | B1: Interview_Number | C1: Response_JSON | D1: Quote | E1: Topic | F1: Flaggin_Reason | G1: First_Code_Label | H1: Confidence_Score | I1: Second_Order | J1: Second_Order_Clustered | K1: Third_Order | L1: My_Manual_Code | M1: Include_Flag | N1: Gap (Yes/No)
A2: 01fe93a8-8723-48be-9311-b6d08c34a13d | B2: 1 | C2: {"session_id": "01fe93a8-8723-48be-9311-b6d08c34a13d", "quotes": [{"quote_text": "I was a little bit sick, but not too bad. Just wanted not to overdo it.", "topic": "workload_sustainability", "first_order_code": "minimizing illness to avoid overdoing it", "flagging_reason": "Participant softens being sick with 'not too bad' while explaining a self-protective boundary around workload.", "confidence": 0.75}, {"quote_text": "especially because our project lead was in the US. Um, so we could align, uh, on the, uh, associate and consultant level a lot better on tasks that we needed to do. Um, and by the time that he was awake in Pacific time, we could already iterate documents with him.", "topic": "overall_experience", "first_order_code": "working around time zone gap with project lead", "flagging_reason": "Describes a workaround necessitated by the project lead's remote location and time difference, indicating a friction point.", "confidence": 0.7}, {"quote_text": "I think the senior leadership, the more sen- the senior partners, they are more hands-off, which is totally okay and acceptable because the project has been going on for such a long time, so there's not a lot that they need to escalate.", "topic": "leadership_engagement", "first_order_code": "justifying senior partners being hands-off", "flagging_reason": "Participant describes limited senior partner involvement but immediately rationalizes it as acceptable, suggesting potential concern being defused.", "confidence": 0.65}]} | D2: I think the senior leadership, the more sen- the senior partners, they are more hands-off, which is totally okay and acceptable because the project has been going on for such a long time, so there's not a lot that they need to escalate. | E2: leadership | F2: Participant describes limited senior partner involvement but immediately rationalizes it as acceptable, suggesting potential concern being defused. | G2: justifying senior partners being hands-off | H2: 0.65 | I2: Rationalizing leadership absence | J2: =IF(OR(I2="Epistemic hedging",I2="Qualifying severity while disclosing",I2="Downgrading emotional intensity"),"Hedged, qualified disclosure",IF(OR(I2="Externalizing accountability",I2="Self-attributing structural problems"),"Protective attribution shifting",IF(OR(I2="Refusal to elaborate under probing",I2="Retracting or qualifying disclosure"),"Withholding under probing",IF(OR(I2="Managing traceability and exposure",I2="Compartmentalizing the AI channel"),"Channel exposure management",IF(OR(I2="Skepticism toward remedy",I2="Anticipating dismissal or misrecognition"),"Anticipated futility of voice",IF(OR(I2="Calling out known but unaddressed issues",I2="Silence within expression"),"Recognized but unescalated concerns",I2)))))) -> Rationalizing leadership absence | K2: =_xlfn.XLOOKUP(J2,#REF!,#REF!,"0",0,1) -> #REF! | N2: =IFERROR(INDEX('Hoja 1 - Supabase Transcripts'!$A:$DN,MATCH(A2,'Hoja 1 - Supabase Transcripts'!$A:$A,0),MATCH("gap_segmentation_"&E2,'Hoja 1 - Supabase Transcripts'!$2:$2,0)),"not found") -> not found | R2: =COUNTA(_xlfn.UNIQUE(A2:A429)) -> 79
A3: 01fe93a8-8723-48be-9311-b6d08c34a13d | B3: 1 | C3: {"session_id": "01fe93a8-8723-48be-9311-b6d08c34a13d", "quotes": [{"quote_text": "I was a little bit sick, but not too bad. Just wanted not to overdo it.", "topic": "workload_sustainability", "first_order_code": "minimizing illness to avoid overdoing it", "flagging_reason": "Participant softens being sick with 'not too bad' while explaining a self-protective boundary around workload.", "confidence": 0.75}, {"quote_text": "especially because our project lead was in the US. Um, so we could align, uh, on the, uh, associate and consultant level a lot better on tasks that we needed to do. Um, and by the time that he was awake in Pacific time, we could already iterate documents with him.", "topic": "overall_experience", "first_order_code": "working around time zone gap with project lead", "flagging_reason": "Describes a workaround necessitated by the project lead's remote location and time difference, indicating a friction point.", "confidence": 0.7}, {"quote_text": "I think the senior leadership, the more sen- the senior partners, they are more hands-off, which is totally okay and acceptable because the project has been going on for such a long time, so there's not a lot that they need to escalate.", "topic": "leadership_engagement", "first_order_code": "justifying senior partners being hands-off", "flagging_reason": "Participant describes limited senior partner involvement but immediately rationalizes it as acceptable, suggesting potential concern being defused.", "confidence": 0.65}]} | D3: especially because our project lead was in the US. Um, so we could align, uh, on the, uh, associate and consultant level a lot better on tasks that we needed to do. Um, and by the time that he was awake in Pacific time, we could already iterate documents with him. | E3: overall_experience | F3: Describes a workaround necessitated by the project lead's remote location and time difference, indicating a friction point. | G3: working around time zone gap with project lead | H3: 0.7 | I3: Concern content - FAMILY A | J3: =IF(OR(I3="Epistemic hedging",I3="Qualifying severity while disclosing",I3="Downgrading emotional intensity"),"Hedged, qualified disclosure",IF(OR(I3="Externalizing accountability",I3="Self-attributing structural problems"),"Protective attribution shifting",IF(OR(I3="Refusal to elaborate under probing",I3="Retracting or qualifying disclosure"),"Withholding under probing",IF(OR(I3="Managing traceability and exposure",I3="Compartmentalizing the AI channel"),"Channel exposure management",IF(OR(I3="Skepticism toward remedy",I3="Anticipating dismissal or misrecognition"),"Anticipated futility of voice",IF(OR(I3="Calling out known but unaddressed issues",I3="Silence within expression"),"Recognized but unescalated concerns",I3)))))) -> Concern content - FAMILY A | N3: =IFERROR(INDEX('Hoja 1 - Supabase Transcripts'!$A:$DN,MATCH(A3,'Hoja 1 - Supabase Transcripts'!$A:$A,0),MATCH("gap_segmentation_"&E3,'Hoja 1 - Supabase Transcripts'!$2:$2,0)),"not found") -> not found
A4: 01fe93a8-8723-48be-9311-b6d08c34a13d | B4: 1 | C4: {"session_id": "01fe93a8-8723-48be-9311-b6d08c34a13d", "quotes": [{"quote_text": "I was a little bit sick, but not too bad. Just wanted not to overdo it.", "topic": "workload_sustainability", "first_order_code": "minimizing illness to avoid overdoing it", "flagging_reason": "Participant softens being sick with 'not too bad' while explaining a self-protective boundary around workload.", "confidence": 0.75}, {"quote_text": "especially because our project lead was in the US. Um, so we could align, uh, on the, uh, associate and consultant level a lot better on tasks that we needed to do. Um, and by the time that he was awake in Pacific time, we could already iterate documents with him.", "topic": "overall_experience", "first_order_code": "working around time zone gap with project lead", "flagging_reason": "Describes a workaround necessitated by the project lead's remote location and time difference, indicating a friction point.", "confidence": 0.7}, {"quote_text": "I think the senior leadership, the more sen- the senior partners, they are more hands-off, which is totally okay and acceptable because the project has been going on for such a long time, so there's not a lot that they need to escalate.", "topic": "leadership_engagement", "first_order_code": "justifying senior partners being hands-off", "flagging_reason": "Participant describes limited senior partner involvement but immediately rationalizes it as acceptable, suggesting potential concern being defused.", "confidence": 0.65}]} | D4: I was a little bit sick, but not too bad. Just wanted not to overdo it. | E4: workload_sust | F4: Participant softens being sick with 'not too bad' while explaining a self-protective boundary around workload. | G4: minimizing illness to avoid overdoing it | H4: 0.75 | I4: Downgrading emotional intensity | J4: =IF(OR(I4="Epistemic hedging",I4="Qualifying severity while disclosing",I4="Downgrading emotional intensity"),"Hedged, qualified disclosure",IF(OR(I4="Externalizing accountability",I4="Self-attributing structural problems"),"Protective attribution shifting",IF(OR(I4="Refusal to elaborate under probing",I4="Retracting or qualifying disclosure"),"Withholding under probing",IF(OR(I4="Managing traceability and exposure",I4="Compartmentalizing the AI channel"),"Channel exposure management",IF(OR(I4="Skepticism toward remedy",I4="Anticipating dismissal or misrecognition"),"Anticipated futility of voice",IF(OR(I4="Calling out known but unaddressed issues",I4="Silence within expression"),"Recognized but unescalated concerns",I4)))))) -> Hedged, qualified disclosure | K4: =_xlfn.XLOOKUP(J4,#REF!,#REF!,"0",0,1) -> #REF! | N4: =IFERROR(INDEX('Hoja 1 - Supabase Transcripts'!$A:$DN,MATCH(A4,'Hoja 1 - Supabase Transcripts'!$A:$A,0),MATCH("gap_segmentation_"&E4,'Hoja 1 - Supabase Transcripts'!$2:$2,0)),"not found") -> not found
A5: 0585f9f4-9f77-4a6f-a791-93110d73cf76 | B5: 1 | C5: {"session_id": "0585f9f4-9f77-4a6f-a791-93110d73cf76", "quotes": [{"quote_text": "on the other side, especially from Monday to Wednesday, we had really intense working hours, working very late, after midnight. So yeah, I think there is still room for improvement.", "topic": "overall_experience", "first_order_code": "working after midnight with room for improvement", "flagging_reason": "Discloses a work concern about extreme hours but softens it with understated phrasing 'room for improvement.'", "confidence": 0.95}, {"quote_text": "we need, or we have a delivery, which is the... Or we had a delivery last Friday. We have an additional delivery this Friday. So there are a lot of deliverables, and especially the finance team covers a lot of topics for these deliverables. So therefore, the working hours are very intense.", "topic": "overall_experience", "first_order_code": "explaining intense hours by volume of deliverables", "flagging_reason": "Attributes the problem to project demands rather than management decisions, showing how the concern is framed.", "confidence": 0.85}, {"quote_text": "I think in general, it's not really sustainable what we're doing at the moment because we're working very late and nearly every day, we finish far after midnight.", "topic": "workload_sustainability", "first_order_code": "finishing after midnight nearly every day is not sustainable", "flagging_reason": "Directly states a work concern about unsustainability of current working pattern.", "confidence": 1.0}, {"quote_text": "it's not possible to get enough sleep during the week. I think during most of the days within the week, we just get five or six hours of sleep or even less, and I think that's not sustainable to keep it that way over a long period.", "topic": "workload_sustainability", "first_order_code": "getting five to six hours of sleep or less most days", "flagging_reason": "Discloses a specific personal impact of the workload concern with concrete detail about sleep deprivation.", "confidence": 1.0}, {"quote_text": "I think the weeks before, they didn't engage that much.", "topic": "leadership_engagement", "first_order_code": "leadership not engaging much in prior weeks", "flagging_reason": "States a concern about leadership behavior in a straightforward but mildly hedged way.", "confidence": 0.9}, {"quote_text": "we also discussed our working hours and the work intensity and what we could do better, but it was more of a reasoning why the working hours are that intense, but not really a plan forward on how we can improve the working hours or how we can distribute it a little bit more.", "topic": "leadership_engagement", "first_order_code": "discussion produced reasons not a plan to improve hours", "flagging_reason": "Reveals frustration that a leadership discussion about the workload problem did not lead to actionable solutions.", "confidence": 0.95}, {"quote_text": "I think they think about ways to improve it, that's for sure. So I think they definitely noticed that something's not going that well. But yeah, hopefully, we can see some results of these discussions.", "topic": "leadership_engagement", "first_order_code": "hoping to see results from leadership noticing the problem", "flagging_reason": "Expresses uncertainty about whether leadership awareness will translate into actual change, hedged with hopefulness.", "confidence": 0.85}, {"quote_text": "I think the MDPs could value our work a little bit more. I think they're doing that in the last couple of days more and more.", "topic": "leadership_engagement", "first_order_code": "MDPs could value our work more than they have", "flagging_reason": "Raises a concern about recognition from senior leaders but immediately softens it by noting recent improvement.", "confidence": 0.9}]} | D5: I think the MDPs could value our work a little bit more. I think they're doing that in the last couple of days more and more. | E5: leadership | F5: Raises a concern about recognition from senior leaders but immediately softens it by noting recent improvement. | G5: MDPs could value our work more than they have | H5: 0.9 | I5: FAMILY_A_CONCERN_CONTENT | J5: =IF(OR(I5="Epistemic hedging",I5="Qualifying severity while disclosing",I5="Downgrading emotional intensity"),"Hedged, qualified disclosure",IF(OR(I5="Externalizing accountability",I5="Self-attributing structural problems"),"Protective attribution shifting",IF(OR(I5="Refusal to elaborate under probing",I5="Retracting or qualifying disclosure"),"Withholding under probing",IF(OR(I5="Managing traceability and exposure",I5="Compartmentalizing the AI channel"),"Channel exposure management",IF(OR(I5="Skepticism toward remedy",I5="Anticipating dismissal or misrecognition"),"Anticipated futility of voice",IF(OR(I5="Calling out known but unaddressed issues",I5="Silence within expression"),"Recognized but unescalated concerns",I5)))))) -> FAMILY_A_CONCERN_CONTENT | N5: =IFERROR(INDEX('Hoja 1 - Supabase Transcripts'!$A:$DN,MATCH(A5,'Hoja 1 - Supabase Transcripts'!$A:$A,0),MATCH("gap_segmentation_"&E5,'Hoja 1 - Supabase Transcripts'!$2:$2,0)),"not found") -> not found
A6: 0585f9f4-9f77-4a6f-a791-93110d73cf76 | B6: 1 | C6: {"session_id": "0585f9f4-9f77-4a6f-a791-93110d73cf76", "quotes": [{"quote_text": "on the other side, especially from Monday to Wednesday, we had really intense working hours, working very late, after midnight. So yeah, I think there is still room for improvement.", "topic": "overall_experience", "first_order_code": "working after midnight with room for improvement", "flagging_reason": "Discloses a work concern about extreme hours but softens it with understated phrasing 'room for improvement.'", "confidence": 0.95}, {"quote_text": "we need, or we have a delivery, which is the... Or we had a delivery last Friday. We have an additional delivery this Friday. So there are a lot of deliverables, and especially the finance team covers a lot of topics for these deliverables. So therefore, the working hours are very intense.", "topic": "overall_experience", "first_order_code": "explaining intense hours by volume of deliverables", "flagging_reason": "Attributes the problem to project demands rather than management decisions, showing how the concern is framed.", "confidence": 0.85}, {"quote_text": "I think in general, it's not really sustainable what we're doing at the moment because we're working very late and nearly every day, we finish far after midnight.", "topic": "workload_sustainability", "first_order_code": "finishing after midnight nearly every day is not sustainable", "flagging_reason": "Directly states a work concern about unsustainability of current working pattern.", "confidence": 1.0}, {"quote_text": "it's not possible to get enough sleep during the week. I think during most of the days within the week, we just get five or six hours of sleep or even less, and I think that's not sustainable to keep it that way over a long period.", "topic": "workload_sustainability", "first_order_code": "getting five to six hours of sleep or less most days", "flagging_reason": "Discloses a specific personal impact of the workload concern with concrete detail about sleep deprivation.", "confidence": 1.0}, {"quote_text": "I think the weeks before, they didn't engage that much.", "topic": "leadership_engagement", "first_order_code": "leadership not engaging much in prior weeks", "flagging_reason": "States a concern about leadership behavior in a straightforward but mildly hedged way.", "confidence": 0.9}, {"quote_text": "we also discussed our working hours and the work intensity and what we could do better, but it was more of a reasoning why the working hours are that intense, but not really a plan forward on how we can improve the working hours or how we can distribute it a little bit more.", "topic": "leadership_engagement", "first_order_code": "discussion produced reasons not a plan to improve hours", "flagging_reason": "Reveals frustration that a leadership discussion about the workload problem did not lead to actionable solutions.", "confidence": 0.95}, {"quote_text": "I think they think about ways to improve it, that's for sure. So I think they definitely noticed that something's not going that well. But yeah, hopefully, we can see some results of these discussions.", "topic": "leadership_engagement", "first_order_code": "hoping to see results from leadership noticing the problem", "flagging_reason": "Expresses uncertainty about whether leadership awareness will translate into actual change, hedged with hopefulness.", "confidence": 0.85}, {"quote_text": "I think the MDPs could value our work a little bit more. I think they're doing that in the last couple of days more and more.", "topic": "leadership_engagement", "first_order_code": "MDPs could value our work more than they have", "flagging_reason": "Raises a concern about recognition from senior leaders but immediately softens it by noting recent improvement.", "confidence": 0.9}]} | D6: I think the weeks before, they didn't engage that much. | E6: leadership | F6: States a concern about leadership behavior in a straightforward but mildly hedged way. | G6: leadership not engaging much in prior weeks | H6: 0.9 | I6: Concern content - FAMILY A | J6: =IF(OR(I6="Epistemic hedging",I6="Qualifying severity while disclosing",I6="Downgrading emotional intensity"),"Hedged, qualified disclosure",IF(OR(I6="Externalizing accountability",I6="Self-attributing structural problems"),"Protective attribution shifting",IF(OR(I6="Refusal to elaborate under probing",I6="Retracting or qualifying disclosure"),"Withholding under probing",IF(OR(I6="Managing traceability and exposure",I6="Compartmentalizing the AI channel"),"Channel exposure management",IF(OR(I6="Skepticism toward remedy",I6="Anticipating dismissal or misrecognition"),"Anticipated futility of voice",IF(OR(I6="Calling out known but unaddressed issues",I6="Silence within expression"),"Recognized but unescalated concerns",I6)))))) -> Concern content - FAMILY A | N6: =IFERROR(INDEX('Hoja 1 - Supabase Transcripts'!$A:$DN,MATCH(A6,'Hoja 1 - Supabase Transcripts'!$A:$A,0),MATCH("gap_segmentation_"&E6,'Hoja 1 - Supabase Transcripts'!$2:$2,0)),"not found") -> not found
A7: 0585f9f4-9f77-4a6f-a791-93110d73cf76 | B7: 1 | C7: {"session_id": "0585f9f4-9f77-4a6f-a791-93110d73cf76", "quotes": [{"quote_text": "on the other side, especially from Monday to Wednesday, we had really intense working hours, working very late, after midnight. So yeah, I think there is still room for improvement.", "topic": "overall_experience", "first_order_code": "working after midnight with room for improvement", "flagging_reason": "Discloses a work concern about extreme hours but softens it with understated phrasing 'room for improvement.'", "confidence": 0.95}, {"quote_text": "we need, or we have a delivery, which is the... Or we had a delivery last Friday. We have an additional delivery this Friday. So there are a lot of deliverables, and especially the finance team covers a lot of topics for these deliverables. So therefore, the working hours are very intense.", "topic": "overall_experience", "first_order_code": "explaining intense hours by volume of deliverables", "flagging_reason": "Attributes the problem to project demands rather than management decisions, showing how the concern is framed.", "confidence": 0.85}, {"quote_text": "I think in general, it's not really sustainable what we're doing at the moment because we're working very late and nearly every day, we finish far after midnight.", "topic": "workload_sustainability", "first_order_code": "finishing after midnight nearly every day is not sustainable", "flagging_reason": "Directly states a work concern about unsustainability of current working pattern.", "confidence": 1.0}, {"quote_text": "it's not possible to get enough sleep during the week. I think during most of the days within the week, we just get five or six hours of sleep or even less, and I think that's not sustainable to keep it that way over a long period.", "topic": "workload_sustainability", "first_order_code": "getting five to six hours of sleep or less most days", "flagging_reason": "Discloses a specific personal impact of the workload concern with concrete detail about sleep deprivation.", "confidence": 1.0}, {"quote_text": "I think the weeks before, they didn't engage that much.", "topic": "leadership_engagement", "first_order_code": "leadership not engaging much in prior weeks", "flagging_reason": "States a concern about leadership behavior in a straightforward but mildly hedged way.", "confidence": 0.9}, {"quote_text": "we also discussed our working hours and the work intensity and what we could do better, but it was more of a reasoning why the working hours are that intense, but not really a plan forward on how we can improve the working hours or how we can distribute it a little bit more.", "topic": "leadership_engagement", "first_order_code": "discussion produced reasons not a plan to improve hours", "flagging_reason": "Reveals frustration that a leadership discussion about the workload problem did not lead to actionable solutions.", "confidence": 0.95}, {"quote_text": "I think they think about ways to improve it, that's for sure. So I think they definitely noticed that something's not going that well. But yeah, hopefully, we can see some results of these discussions.", "topic": "leadership_engagement", "first_order_code": "hoping to see results from leadership noticing the problem", "flagging_reason": "Expresses uncertainty about whether leadership awareness will translate into actual change, hedged with hopefulness.", "confidence": 0.85}, {"quote_text": "I think the MDPs could value our work a little bit more. I think they're doing that in the last couple of days more and more.", "topic": "leadership_engagement", "first_order_code": "MDPs could value our work more than they have", "flagging_reason": "Raises a concern about recognition from senior leaders but immediately softens it by noting recent improvement.", "confidence": 0.9}]} | D7: I think they think about ways to improve it, that's for sure. So I think they definitely noticed that something's not going that well. But yeah, hopefully, we can see some results of these discussions. | E7: leadership | F7: Expresses uncertainty about whether leadership awareness will translate into actual change, hedged with hopefulness. | G7: hoping to see results from leadership noticing the problem | H7: 0.85 | I7: Aspirational framing of unmet needs | J7: =IF(OR(I7="Epistemic hedging",I7="Qualifying severity while disclosing",I7="Downgrading emotional intensity"),"Hedged, qualified disclosure",IF(OR(I7="Externalizing accountability",I7="Self-attributing structural problems"),"Protective attribution shifting",IF(OR(I7="Refusal to elaborate under probing",I7="Retracting or qualifying disclosure"),"Withholding under probing",IF(OR(I7="Managing traceability and exposure",I7="Compartmentalizing the AI channel"),"Channel exposure management",IF(OR(I7="Skepticism toward remedy",I7="Anticipating dismissal or misrecognition"),"Anticipated futility of voice",IF(OR(I7="Calling out known but unaddressed issues",I7="Silence within expression"),"Recognized but unescalated concerns",I7)))))) -> Aspirational framing of unmet needs | K7: =_xlfn.XLOOKUP(J7,#REF!,#REF!,"0",0,1) -> #REF! | N7: =IFERROR(INDEX('Hoja 1 - Supabase Transcripts'!$A:$DN,MATCH(A7,'Hoja 1 - Supabase Transcripts'!$A:$A,0),MATCH("gap_segmentation_"&E7,'Hoja 1 - Supabase Transcripts'!$2:$2,0)),"not found") -> not found
A8: 0585f9f4-9f77-4a6f-a791-93110d73cf76 | B8: 1 | C8: {"session_id": "0585f9f4-9f77-4a6f-a791-93110d73cf76", "quotes": [{"quote_text": "on the other side, especially from Monday to Wednesday, we had really intense working hours, working very late, after midnight. So yeah, I think there is still room for improvement.", "topic": "overall_experience", "first_order_code": "working after midnight with room for improvement", "flagging_reason": "Discloses a work concern about extreme hours but softens it with understated phrasing 'room for improvement.'", "confidence": 0.95}, {"quote_text": "we need, or we have a delivery, which is the... Or we had a delivery last Friday. We have an additional delivery this Friday. So there are a lot of deliverables, and especially the finance team covers a lot of topics for these deliverables. So therefore, the working hours are very intense.", "topic": "overall_experience", "first_order_code": "explaining intense hours by volume of deliverables", "flagging_reason": "Attributes the problem to project demands rather than management decisions, showing how the concern is framed.", "confidence": 0.85}, {"quote_text": "I think in general, it's not really sustainable what we're doing at the moment because we're working very late and nearly every day, we finish far after midnight.", "topic": "workload_sustainability", "first_order_code": "finishing after midnight nearly every day is not sustainable", "flagging_reason": "Directly states a work concern about unsustainability of current working pattern.", "confidence": 1.0}, {"quote_text": "it's not possible to get enough sleep during the week. I think during most of the days within the week, we just get five or six hours of sleep or even less, and I think that's not sustainable to keep it that way over a long period.", "topic": "workload_sustainability", "first_order_code": "getting five to six hours of sleep or less most days", "flagging_reason": "Discloses a specific personal impact of the workload concern with concrete detail about sleep deprivation.", "confidence": 1.0}, {"quote_text": "I think the weeks before, they didn't engage that much.", "topic": "leadership_engagement", "first_order_code": "leadership not engaging much in prior weeks", "flagging_reason": "States a concern about leadership behavior in a straightforward but mildly hedged way.", "confidence": 0.9}, {"quote_text": "we also discussed our working hours and the work intensity and what we could do better, but it was more of a reasoning why the working hours are that intense, but not really a plan forward on how we can improve the working hours or how we can distribute it a little bit more.", "topic": "leadership_engagement", "first_order_code": "discussion produced reasons not a plan to improve hours", "flagging_reason": "Reveals frustration that a leadership discussion about the workload problem did not lead to actionable solutions.", "confidence": 0.95}, {"quote_text": "I think they think about ways to improve it, that's for sure. So I think they definitely noticed that something's not going that well. But yeah, hopefully, we can see some results of these discussions.", "topic": "leadership_engagement", "first_order_code": "hoping to see results from leadership noticing the problem", "flagging_reason": "Expresses uncertainty about whether leadership awareness will translate into actual change, hedged with hopefulness.", "confidence": 0.85}, {"quote_text": "I think the MDPs could value our work a little bit more. I think they're doing that in the last couple of days more and more.", "topic": "leadership_engagement", "first_order_code": "MDPs could value our work more than they have", "flagging_reason": "Raises a concern about recognition from senior leaders but immediately softens it by noting recent improvement.", "confidence": 0.9}]} | D8: we also discussed our working hours and the work intensity and what we could do better, but it was more of a reasoning why the working hours are that intense, but not really a plan forward on how we can improve the working hours or how we can distribute it a little bit more. | E8: leadership | F8: Reveals frustration that a leadership discussion about the workload problem did not lead to actionable solutions. | G8: discussion produced reasons not a plan to improve hours | H8: 0.95 | I8: Skepticism toward remedy | J8: =IF(OR(I8="Epistemic hedging",I8="Qualifying severity while disclosing",I8="Downgrading emotional intensity"),"Hedged, qualified disclosure",IF(OR(I8="Externalizing accountability",I8="Self-attributing structural problems"),"Protective attribution shifting",IF(OR(I8="Refusal to elaborate under probing",I8="Retracting or qualifying disclosure"),"Withholding under probing",IF(OR(I8="Managing traceability and exposure",I8="Compartmentalizing the AI channel"),"Channel exposure management",IF(OR(I8="Skepticism toward remedy",I8="Anticipating dismissal or misrecognition"),"Anticipated futility of voice",IF(OR(I8="Calling out known but unaddressed issues",I8="Silence within expression"),"Recognized but unescalated concerns",I8)))))) -> Anticipated futility of voice | K8: =_xlfn.XLOOKUP(J8,#REF!,#REF!,"0",0,1) -> #REF! | N8: =IFERROR(INDEX('Hoja 1 - Supabase Transcripts'!$A:$DN,MATCH(A8,'Hoja 1 - Supabase Transcripts'!$A:$A,0),MATCH("gap_segmentation_"&E8,'Hoja 1 - Supabase Transcripts'!$2:$2,0)),"not found") -> not found
A9: 0585f9f4-9f77-4a6f-a791-93110d73cf76 | B9: 1 | C9: {"session_id": "0585f9f4-9f77-4a6f-a791-93110d73cf76", "quotes": [{"quote_text": "on the other side, especially from Monday to Wednesday, we had really intense working hours, working very late, after midnight. So yeah, I think there is still room for improvement.", "topic": "overall_experience", "first_order_code": "working after midnight with room for improvement", "flagging_reason": "Discloses a work concern about extreme hours but softens it with understated phrasing 'room for improvement.'", "confidence": 0.95}, {"quote_text": "we need, or we have a delivery, which is the... Or we had a delivery last Friday. We have an additional delivery this Friday. So there are a lot of deliverables, and especially the finance team covers a lot of topics for these deliverables. So therefore, the working hours are very intense.", "topic": "overall_experience", "first_order_code": "explaining intense hours by volume of deliverables", "flagging_reason": "Attributes the problem to project demands rather than management decisions, showing how the concern is framed.", "confidence": 0.85}, {"quote_text": "I think in general, it's not really sustainable what we're doing at the moment because we're working very late and nearly every day, we finish far after midnight.", "topic": "workload_sustainability", "first_order_code": "finishing after midnight nearly every day is not sustainable", "flagging_reason": "Directly states a work concern about unsustainability of current working pattern.", "confidence": 1.0}, {"quote_text": "it's not possible to get enough sleep during the week. I think during most of the days within the week, we just get five or six hours of sleep or even less, and I think that's not sustainable to keep it that way over a long period.", "topic": "workload_sustainability", "first_order_code": "getting five to six hours of sleep or less most days", "flagging_reason": "Discloses a specific personal impact of the workload concern with concrete detail about sleep deprivation.", "confidence": 1.0}, {"quote_text": "I think the weeks before, they didn't engage that much.", "topic": "leadership_engagement", "first_order_code": "leadership not engaging much in prior weeks", "flagging_reason": "States a concern about leadership behavior in a straightforward but mildly hedged way.", "confidence": 0.9}, {"quote_text": "we also discussed our working hours and the work intensity and what we could do better, but it was more of a reasoning why the working hours are that intense, but not really a plan forward on how we can improve the working hours or how we can distribute it a little bit more.", "topic": "leadership_engagement", "first_order_code": "discussion produced reasons not a plan to improve hours", "flagging_reason": "Reveals frustration that a leadership discussion about the workload problem did not lead to actionable solutions.", "confidence": 0.95}, {"quote_text": "I think they think about ways to improve it, that's for sure. So I think they definitely noticed that something's not going that well. But yeah, hopefully, we can see some results of these discussions.", "topic": "leadership_engagement", "first_order_code": "hoping to see results from leadership noticing the problem", "flagging_reason": "Expresses uncertainty about whether leadership awareness will translate into actual change, hedged with hopefulness.", "confidence": 0.85}, {"quote_text": "I think the MDPs could value our work a little bit more. I think they're doing that in the last couple of days more and more.", "topic": "leadership_engagement", "first_order_code": "MDPs could value our work more than they have", "flagging_reason": "Raises a concern about recognition from senior leaders but immediately softens it by noting recent improvement.", "confidence": 0.9}]} | D9: on the other side, especially from Monday to Wednesday, we had really intense working hours, working very late, after midnight. So yeah, I think there is still room for improvement. | E9: overall_experience | F9: Discloses a work concern about extreme hours but softens it with understated phrasing 'room for improvement.' | G9: working after midnight with room for improvement | H9: 0.95 | I9: Normalization of extreme conditions | J9: =IF(OR(I9="Epistemic hedging",I9="Qualifying severity while disclosing",I9="Downgrading emotional intensity"),"Hedged, qualified disclosure",IF(OR(I9="Externalizing accountability",I9="Self-attributing structural problems"),"Protective attribution shifting",IF(OR(I9="Refusal to elaborate under probing",I9="Retracting or qualifying disclosure"),"Withholding under probing",IF(OR(I9="Managing traceability and exposure",I9="Compartmentalizing the AI channel"),"Channel exposure management",IF(OR(I9="Skepticism toward remedy",I9="Anticipating dismissal or misrecognition"),"Anticipated futility of voice",IF(OR(I9="Calling out known but unaddressed issues",I9="Silence within expression"),"Recognized but unescalated concerns",I9)))))) -> Normalization of extreme conditions | K9: =_xlfn.XLOOKUP(J9,#REF!,#REF!,"0",0,1) -> #REF! | N9: =IFERROR(INDEX('Hoja 1 - Supabase Transcripts'!$A:$DN,MATCH(A9,'Hoja 1 - Supabase Transcripts'!$A:$A,0),MATCH("gap_segmentation_"&E9,'Hoja 1 - Supabase Transcripts'!$2:$2,0)),"not found") -> not found
A10: 0585f9f4-9f77-4a6f-a791-93110d73cf76 | B10: 1 | C10: {"session_id": "0585f9f4-9f77-4a6f-a791-93110d73cf76", "quotes": [{"quote_text": "on the other side, especially from Monday to Wednesday, we had really intense working hours, working very late, after midnight. So yeah, I think there is still room for improvement.", "topic": "overall_experience", "first_order_code": "working after midnight with room for improvement", "flagging_reason": "Discloses a work concern about extreme hours but softens it with understated phrasing 'room for improvement.'", "confidence": 0.95}, {"quote_text": "we need, or we have a delivery, which is the... Or we had a delivery last Friday. We have an additional delivery this Friday. So there are a lot of deliverables, and especially the finance team covers a lot of topics for these deliverables. So therefore, the working hours are very intense.", "topic": "overall_experience", "first_order_code": "explaining intense hours by volume of deliverables", "flagging_reason": "Attributes the problem to project demands rather than management decisions, showing how the concern is framed.", "confidence": 0.85}, {"quote_text": "I think in general, it's not really sustainable what we're doing at the moment because we're working very late and nearly every day, we finish far after midnight.", "topic": "workload_sustainability", "first_order_code": "finishing after midnight nearly every day is not sustainable", "flagging_reason": "Directly states a work concern about unsustainability of current working pattern.", "confidence": 1.0}, {"quote_text": "it's not possible to get enough sleep during the week. I think during most of the days within the week, we just get five or six hours of sleep or even less, and I think that's not sustainable to keep it that way over a long period.", "topic": "workload_sustainability", "first_order_code": "getting five to six hours of sleep or less most days", "flagging_reason": "Discloses a specific personal impact of the workload concern with concrete detail about sleep deprivation.", "confidence": 1.0}, {"quote_text": "I think the weeks before, they didn't engage that much.", "topic": "leadership_engagement", "first_order_code": "leadership not engaging much in prior weeks", "flagging_reason": "States a concern about leadership behavior in a straightforward but mildly hedged way.", "confidence": 0.9}, {"quote_text": "we also discussed our working hours and the work intensity and what we could do better, but it was more of a reasoning why the working hours are that intense, but not really a plan forward on how we can improve the working hours or how we can distribute it a little bit more.", "topic": "leadership_engagement", "first_order_code": "discussion produced reasons not a plan to improve hours", "flagging_reason": "Reveals frustration that a leadership discussion about the workload problem did not lead to actionable solutions.", "confidence": 0.95}, {"quote_text": "I think they think about ways to improve it, that's for sure. So I think they definitely noticed that something's not going that well. But yeah, hopefully, we can see some results of these discussions.", "topic": "leadership_engagement", "first_order_code": "hoping to see results from leadership noticing the problem", "flagging_reason": "Expresses uncertainty about whether leadership awareness will translate into actual change, hedged with hopefulness.", "confidence": 0.85}, {"quote_text": "I think the MDPs could value our work a little bit more. I think they're doing that in the last couple of days more and more.", "topic": "leadership_engagement", "first_order_code": "MDPs could value our work more than they have", "flagging_reason": "Raises a concern about recognition from senior leaders but immediately softens it by noting recent improvement.", "confidence": 0.9}]} | D10: we need, or we have a delivery, which is the... Or we had a delivery last Friday. We have an additional delivery this Friday. So there are a lot of deliverables, and especially the finance team covers a lot of topics for these deliverables. So therefore, the working hours are very intense. | E10: overall_experience | F10: Attributes the problem to project demands rather than management decisions, showing how the concern is framed. | G10: explaining intense hours by volume of deliverables | H10: 0.85 | I10: Externalizing accountability | J10: =IF(OR(I10="Epistemic hedging",I10="Qualifying severity while disclosing",I10="Downgrading emotional intensity"),"Hedged, qualified disclosure",IF(OR(I10="Externalizing accountability",I10="Self-attributing structural problems"),"Protective attribution shifting",IF(OR(I10="Refusal to elaborate under probing",I10="Retracting or qualifying disclosure"),"Withholding under probing",IF(OR(I10="Managing traceability and exposure",I10="Compartmentalizing the AI channel"),"Channel exposure management",IF(OR(I10="Skepticism toward remedy",I10="Anticipating dismissal or misrecognition"),"Anticipated futility of voice",IF(OR(I10="Calling out known but unaddressed issues",I10="Silence within expression"),"Recognized but unescalated concerns",I10)))))) -> Protective attribution shifting | K10: =_xlfn.XLOOKUP(J10,#REF!,#REF!,"0",0,1) -> #REF! | N10: =IFERROR(INDEX('Hoja 1 - Supabase Transcripts'!$A:$DN,MATCH(A10,'Hoja 1 - Supabase Transcripts'!$A:$A,0),MATCH("gap_segmentation_"&E10,'Hoja 1 - Supabase Transcripts'!$2:$2,0)),"not found") -> not found
A11: 0585f9f4-9f77-4a6f-a791-93110d73cf76 | B11: 1 | C11: {"session_id": "0585f9f4-9f77-4a6f-a791-93110d73cf76", "quotes": [{"quote_text": "on the other side, especially from Monday to Wednesday, we had really intense working hours, working very late, after midnight. So yeah, I think there is still room for improvement.", "topic": "overall_experience", "first_order_code": "working after midnight with room for improvement", "flagging_reason": "Discloses a work concern about extreme hours but softens it with understated phrasing 'room for improvement.'", "confidence": 0.95}, {"quote_text": "we need, or we have a delivery, which is the... Or we had a delivery last Friday. We have an additional delivery this Friday. So there are a lot of deliverables, and especially the finance team covers a lot of topics for these deliverables. So therefore, the working hours are very intense.", "topic": "overall_experience", "first_order_code": "explaining intense hours by volume of deliverables", "flagging_reason": "Attributes the problem to project demands rather than management decisions, showing how the concern is framed.", "confidence": 0.85}, {"quote_text": "I think in general, it's not really sustainable what we're doing at the moment because we're working very late and nearly every day, we finish far after midnight.", "topic": "workload_sustainability", "first_order_code": "finishing after midnight nearly every day is not sustainable", "flagging_reason": "Directly states a work concern about unsustainability of current working pattern.", "confidence": 1.0}, {"quote_text": "it's not possible to get enough sleep during the week. I think during most of the days within the week, we just get five or six hours of sleep or even less, and I think that's not sustainable to keep it that way over a long period.", "topic": "workload_sustainability", "first_order_code": "getting five to six hours of sleep or less most days", "flagging_reason": "Discloses a specific personal impact of the workload concern with concrete detail about sleep deprivation.", "confidence": 1.0}, {"quote_text": "I think the weeks before, they didn't engage that much.", "topic": "leadership_engagement", "first_order_code": "leadership not engaging much in prior weeks", "flagging_reason": "States a concern about leadership behavior in a straightforward but mildly hedged way.", "confidence": 0.9}, {"quote_text": "we also discussed our working hours and the work intensity and what we could do better, but it was more of a reasoning why the working hours are that intense, but not really a plan forward on how we can improve the working hours or how we can distribute it a little bit more.", "topic": "leadership_engagement", "first_order_code": "discussion produced reasons not a plan to improve hours", "flagging_reason": "Reveals frustration that a leadership discussion about the workload problem did not lead to actionable solutions.", "confidence": 0.95}, {"quote_text": "I think they think about ways to improve it, that's for sure. So I think they definitely noticed that something's not going that well. But yeah, hopefully, we can see some results of these discussions.", "topic": "leadership_engagement", "first_order_code": "hoping to see results from leadership noticing the problem", "flagging_reason": "Expresses uncertainty about whether leadership awareness will translate into actual change, hedged with hopefulness.", "confidence": 0.85}, {"quote_text": "I think the MDPs could value our work a little bit more. I think they're doing that in the last couple of days more and more.", "topic": "leadership_engagement", "first_order_code": "MDPs could value our work more than they have", "flagging_reason": "Raises a concern about recognition from senior leaders but immediately softens it by noting recent improvement.", "confidence": 0.9}]} | D11: I think in general, it's not really sustainable what we're doing at the moment because we're working very late and nearly every day, we finish far after midnight. | E11: workload_sust | F11: Directly states a work concern about unsustainability of current working pattern. | G11: finishing after midnight nearly every day is not sustainable | H11: 1 | I11: Concern content - FAMILY A | J11: =IF(OR(I11="Epistemic hedging",I11="Qualifying severity while disclosing",I11="Downgrading emotional intensity"),"Hedged, qualified disclosure",IF(OR(I11="Externalizing accountability",I11="Self-attributing structural problems"),"Protective attribution shifting",IF(OR(I11="Refusal to elaborate under probing",I11="Retracting or qualifying disclosure"),"Withholding under probing",IF(OR(I11="Managing traceability and exposure",I11="Compartmentalizing the AI channel"),"Channel exposure management",IF(OR(I11="Skepticism toward remedy",I11="Anticipating dismissal or misrecognition"),"Anticipated futility of voice",IF(OR(I11="Calling out known but unaddressed issues",I11="Silence within expression"),"Recognized but unescalated concerns",I11)))))) -> Concern content - FAMILY A | N11: =IFERROR(INDEX('Hoja 1 - Supabase Transcripts'!$A:$DN,MATCH(A11,'Hoja 1 - Supabase Transcripts'!$A:$A,0),MATCH("gap_segmentation_"&E11,'Hoja 1 - Supabase Transcripts'!$2:$2,0)),"not found") -> not found
A12: 0585f9f4-9f77-4a6f-a791-93110d73cf76 | B12: 1 | C12: {"session_id": "0585f9f4-9f77-4a6f-a791-93110d73cf76", "quotes": [{"quote_text": "on the other side, especially from Monday to Wednesday, we had really intense working hours, working very late, after midnight. So yeah, I think there is still room for improvement.", "topic": "overall_experience", "first_order_code": "working after midnight with room for improvement", "flagging_reason": "Discloses a work concern about extreme hours but softens it with understated phrasing 'room for improvement.'", "confidence": 0.95}, {"quote_text": "we need, or we have a delivery, which is the... Or we had a delivery last Friday. We have an additional delivery this Friday. So there are a lot of deliverables, and especially the finance team covers a lot of topics for these deliverables. So therefore, the working hours are very intense.", "topic": "overall_experience", "first_order_code": "explaining intense hours by volume of deliverables", "flagging_reason": "Attributes the problem to project demands rather than management decisions, showing how the concern is framed.", "confidence": 0.85}, {"quote_text": "I think in general, it's not really sustainable what we're doing at the moment because we're working very late and nearly every day, we finish far after midnight.", "topic": "workload_sustainability", "first_order_code": "finishing after midnight nearly every day is not sustainable", "flagging_reason": "Directly states a work concern about unsustainability of current working pattern.", "confidence": 1.0}, {"quote_text": "it's not possible to get enough sleep during the week. I think during most of the days within the week, we just get five or six hours of sleep or even less, and I think that's not sustainable to keep it that way over a long period.", "topic": "workload_sustainability", "first_order_code": "getting five to six hours of sleep or less most days", "flagging_reason": "Discloses a specific personal impact of the workload concern with concrete detail about sleep deprivation.", "confidence": 1.0}, {"quote_text": "I think the weeks before, they didn't engage that much.", "topic": "leadership_engagement", "first_order_code": "leadership not engaging much in prior weeks", "flagging_reason": "States a concern about leadership behavior in a straightforward but mildly hedged way.", "confidence": 0.9}, {"quote_text": "we also discussed our working hours and the work intensity and what we could do better, but it was more of a reasoning why the working hours are that intense, but not really a plan forward on how we can improve the working hours or how we can distribute it a little bit more.", "topic": "leadership_engagement", "first_order_code": "discussion produced reasons not a plan to improve hours", "flagging_reason": "Reveals frustration that a leadership discussion about the workload problem did not lead to actionable solutions.", "confidence": 0.95}, {"quote_text": "I think they think about ways to improve it, that's for sure. So I think they definitely noticed that something's not going that well. But yeah, hopefully, we can see some results of these discussions.", "topic": "leadership_engagement", "first_order_code": "hoping to see results from leadership noticing the problem", "flagging_reason": "Expresses uncertainty about whether leadership awareness will translate into actual change, hedged with hopefulness.", "confidence": 0.85}, {"quote_text": "I think the MDPs could value our work a little bit more. I think they're doing that in the last couple of days more and more.", "topic": "leadership_engagement", "first_order_code": "MDPs could value our work more than they have", "flagging_reason": "Raises a concern about recognition from senior leaders but immediately softens it by noting recent improvement.", "confidence": 0.9}]} | D12: it's not possible to get enough sleep during the week. I think during most of the days within the week, we just get five or six hours of sleep or even less, and I think that's not sustainable to keep it that way over a long period. | E12: workload_sust | F12: Discloses a specific personal impact of the workload concern with concrete detail about sleep deprivation. | G12: getting five to six hours of sleep or less most days | H12: 1 | I12: Concern content - FAMILY A | J12: =IF(OR(I12="Epistemic hedging",I12="Qualifying severity while disclosing",I12="Downgrading emotional intensity"),"Hedged, qualified disclosure",IF(OR(I12="Externalizing accountability",I12="Self-attributing structural problems"),"Protective attribution shifting",IF(OR(I12="Refusal to elaborate under probing",I12="Retracting or qualifying disclosure"),"Withholding under probing",IF(OR(I12="Managing traceability and exposure",I12="Compartmentalizing the AI channel"),"Channel exposure management",IF(OR(I12="Skepticism toward remedy",I12="Anticipating dismissal or misrecognition"),"Anticipated futility of voice",IF(OR(I12="Calling out known but unaddressed issues",I12="Silence within expression"),"Recognized but unescalated concerns",I12)))))) -> Concern content - FAMILY A | N12: =IFERROR(INDEX('Hoja 1 - Supabase Transcripts'!$A:$DN,MATCH(A12,'Hoja 1 - Supabase Transcripts'!$A:$A,0),MATCH("gap_segmentation_"&E12,'Hoja 1 - Supabase Transcripts'!$2:$2,0)),"not found") -> not found
A13: 08dde59d-27bc-4a1e-8d8f-7cd6a04ed4d3 | B13: 2 | C13: {"session_id": "08dde59d-27bc-4a1e-8d8f-7cd6a04ed4d3", "quotes": [{"quote_text": "Because of the deliverable, it was quite challenging and not always foreseeable.", "topic": "workload_sustainability", "first_order_code": "workload hard to predict in advance", "flagging_reason": "Participant describes a work difficulty around unpredictability of demands, though softened by positive framing afterward.", "confidence": 0.85}, {"quote_text": "Um, but in the end, still we managed, uh, an okay-ish balance, so I'm happy.", "topic": "workload_sustainability", "first_order_code": "achieving only an 'okay-ish' balance", "flagging_reason": "Hedged language ('okay-ish') suggests the balance was less than ideal, though wrapped in a positive conclusion.", "confidence": 0.75}, {"quote_text": "That I'm not just sleeping the whole weekend.", "topic": "workload_sustainability", "first_order_code": "measuring success by not sleeping all weekend", "flagging_reason": "Participant uses humor to describe the bar for work-life balance as very low, implying significant fatigue or strain.", "confidence": 0.9}]} | D13: Because of the deliverable, it was quite challenging and not always foreseeable. | E13: workload_sust | F13: Participant describes a work difficulty around unpredictability of demands, though softened by positive framing afterward. | G13: workload hard to predict in advance | H13: 0.85 | I13: Concern content - FAMILY A | J13: =IF(OR(I13="Epistemic hedging",I13="Qualifying severity while disclosing",I13="Downgrading emotional intensity"),"Hedged, qualified disclosure",IF(OR(I13="Externalizing accountability",I13="Self-attributing structural problems"),"Protective attribution shifting",IF(OR(I13="Refusal to elaborate under probing",I13="Retracting or qualifying disclosure"),"Withholding under probing",IF(OR(I13="Managing traceability and exposure",I13="Compartmentalizing the AI channel"),"Channel exposure management",IF(OR(I13="Skepticism toward remedy",I13="Anticipating dismissal or misrecognition"),"Anticipated futility of voice",IF(OR(I13="Calling out known but unaddressed issues",I13="Silence within expression"),"Recognized but unescalated concerns",I13)))))) -> Concern content - FAMILY A | N13: =IFERROR(INDEX('Hoja 1 - Supabase Transcripts'!$A:$DN,MATCH(A13,'Hoja 1 - Supabase Transcripts'!$A:$A,0),MATCH("gap_segmentation_"&E13,'Hoja 1 - Supabase Transcripts'!$2:$2,0)),"not found") -> not found
A14: 08dde59d-27bc-4a1e-8d8f-7cd6a04ed4d3 | B14: 2 | C14: {"session_id": "08dde59d-27bc-4a1e-8d8f-7cd6a04ed4d3", "quotes": [{"quote_text": "Because of the deliverable, it was quite challenging and not always foreseeable.", "topic": "workload_sustainability", "first_order_code": "workload hard to predict in advance", "flagging_reason": "Participant describes a work difficulty around unpredictability of demands, though softened by positive framing afterward.", "confidence": 0.85}, {"quote_text": "Um, but in the end, still we managed, uh, an okay-ish balance, so I'm happy.", "topic": "workload_sustainability", "first_order_code": "achieving only an 'okay-ish' balance", "flagging_reason": "Hedged language ('okay-ish') suggests the balance was less than ideal, though wrapped in a positive conclusion.", "confidence": 0.75}, {"quote_text": "That I'm not just sleeping the whole weekend.", "topic": "workload_sustainability", "first_order_code": "measuring success by not sleeping all weekend", "flagging_reason": "Participant uses humor to describe the bar for work-life balance as very low, implying significant fatigue or strain.", "confidence": 0.9}]} | D14: That I'm not just sleeping the whole weekend. | E14: workload_sust | F14: Participant uses humor to describe the bar for work-life balance as very low, implying significant fatigue or strain. | G14: measuring success by not sleeping all weekend | H14: 0.9 | I14: Normalization of extreme conditions | J14: =IF(OR(I14="Epistemic hedging",I14="Qualifying severity while disclosing",I14="Downgrading emotional intensity"),"Hedged, qualified disclosure",IF(OR(I14="Externalizing accountability",I14="Self-attributing structural problems"),"Protective attribution shifting",IF(OR(I14="Refusal to elaborate under probing",I14="Retracting or qualifying disclosure"),"Withholding under probing",IF(OR(I14="Managing traceability and exposure",I14="Compartmentalizing the AI channel"),"Channel exposure management",IF(OR(I14="Skepticism toward remedy",I14="Anticipating dismissal or misrecognition"),"Anticipated futility of voice",IF(OR(I14="Calling out known but unaddressed issues",I14="Silence within expression"),"Recognized but unescalated concerns",I14)))))) -> Normalization of extreme conditions | K14: =_xlfn.XLOOKUP(J14,#REF!,#REF!,"0",0,1) -> #REF! | N14: =IFERROR(INDEX('Hoja 1 - Supabase Transcripts'!$A:$DN,MATCH(A14,'Hoja 1 - Supabase Transcripts'!$A:$A,0),MATCH("gap_segmentation_"&E14,'Hoja 1 - Supabase Transcripts'!$2:$2,0)),"not found") -> not found
A15: 08dde59d-27bc-4a1e-8d8f-7cd6a04ed4d3 | B15: 2 | C15: {"session_id": "08dde59d-27bc-4a1e-8d8f-7cd6a04ed4d3", "quotes": [{"quote_text": "Because of the deliverable, it was quite challenging and not always foreseeable.", "topic": "workload_sustainability", "first_order_code": "workload hard to predict in advance", "flagging_reason": "Participant describes a work difficulty around unpredictability of demands, though softened by positive framing afterward.", "confidence": 0.85}, {"quote_text": "Um, but in the end, still we managed, uh, an okay-ish balance, so I'm happy.", "topic": "workload_sustainability", "first_order_code": "achieving only an 'okay-ish' balance", "flagging_reason": "Hedged language ('okay-ish') suggests the balance was less than ideal, though wrapped in a positive conclusion.", "confidence": 0.75}, {"quote_text": "That I'm not just sleeping the whole weekend.", "topic": "workload_sustainability", "first_order_code": "measuring success by not sleeping all weekend", "flagging_reason": "Participant uses humor to describe the bar for work-life balance as very low, implying significant fatigue or strain.", "confidence": 0.9}]} | D15: Um, but in the end, still we managed, uh, an okay-ish balance, so I'm happy. | E15: workload_sust | F15: Hedged language ('okay-ish') suggests the balance was less than ideal, though wrapped in a positive conclusion. | G15: achieving only an 'okay-ish' balance | H15: 0.75 | I15: Qualifying severity while disclosing | J15: =IF(OR(I15="Epistemic hedging",I15="Qualifying severity while disclosing",I15="Downgrading emotional intensity"),"Hedged, qualified disclosure",IF(OR(I15="Externalizing accountability",I15="Self-attributing structural problems"),"Protective attribution shifting",IF(OR(I15="Refusal to elaborate under probing",I15="Retracting or qualifying disclosure"),"Withholding under probing",IF(OR(I15="Managing traceability and exposure",I15="Compartmentalizing the AI channel"),"Channel exposure management",IF(OR(I15="Skepticism toward remedy",I15="Anticipating dismissal or misrecognition"),"Anticipated futility of voice",IF(OR(I15="Calling out known but unaddressed issues",I15="Silence within expression"),"Recognized but unescalated concerns",I15)))))) -> Hedged, qualified disclosure | K15: =_xlfn.XLOOKUP(J15,#REF!,#REF!,"0",0,1) -> #REF! | N15: =IFERROR(INDEX('Hoja 1 - Supabase Transcripts'!$A:$DN,MATCH(A15,'Hoja 1 - Supabase Transcripts'!$A:$A,0),MATCH("gap_segmentation_"&E15,'Hoja 1 - Supabase Transcripts'!$2:$2,0)),"not found") -> not found
A16: 09290b39-0fb4-4096-b357-c0e613b92790 | B16: 3 | C16: {"session_id": "09290b39-0fb4-4096-b357-c0e613b92790", "quotes": [{"quote_text": "whenever there was anyone under pressure, we tried to effectively, and even sometimes autonomously without leadership, try to balance the work", "topic": "overall_experience", "first_order_code": "team self-organizing to relieve pressure without leadership", "flagging_reason": "Indicates recurring pressure situations that require team intervention, suggesting workload distribution issues.", "confidence": 0.75}, {"quote_text": "Lily has a lot of, a lot of stuff on her plate. Is there anyone who can help her out?", "topic": "overall_experience", "first_order_code": "team member visibly overloaded needing help", "flagging_reason": "Names a specific colleague under excessive workload requiring peer intervention.", "confidence": 0.85}, {"quote_text": "we do scope up or scope down also for depending on the, uh, capacity that we have", "topic": "client_value", "first_order_code": "adjusting project scope based on available capacity", "flagging_reason": "Suggests capacity constraints that require compromising on deliverable scope.", "confidence": 0.7}]} | D16: we do scope up or scope down also for depending on the, uh, capacity that we have | E16: client_value | F16: Suggests capacity constraints that require compromising on deliverable scope. | G16: adjusting project scope based on available capacity | H16: 0.7 | I16: FAMILY_A_CONCERN_CONTENT | J16: =IF(OR(I16="Epistemic hedging",I16="Qualifying severity while disclosing",I16="Downgrading emotional intensity"),"Hedged, qualified disclosure",IF(OR(I16="Externalizing accountability",I16="Self-attributing structural problems"),"Protective attribution shifting",IF(OR(I16="Refusal to elaborate under probing",I16="Retracting or qualifying disclosure"),"Withholding under probing",IF(OR(I16="Managing traceability and exposure",I16="Compartmentalizing the AI channel"),"Channel exposure management",IF(OR(I16="Skepticism toward remedy",I16="Anticipating dismissal or misrecognition"),"Anticipated futility of voice",IF(OR(I16="Calling out known but unaddressed issues",I16="Silence within expression"),"Recognized but unescalated concerns",I16)))))) -> FAMILY_A_CONCERN_CONTENT | N16: =IFERROR(INDEX('Hoja 1 - Supabase Transcripts'!$A:$DN,MATCH(A16,'Hoja 1 - Supabase Transcripts'!$A:$A,0),MATCH("gap_segmentation_"&E16,'Hoja 1 - Supabase Transcripts'!$2:$2,0)),"not found") -> not found
A17: 09290b39-0fb4-4096-b357-c0e613b92790 | B17: 3 | C17: {"session_id": "09290b39-0fb4-4096-b357-c0e613b92790", "quotes": [{"quote_text": "whenever there was anyone under pressure, we tried to effectively, and even sometimes autonomously without leadership, try to balance the work", "topic": "overall_experience", "first_order_code": "team self-organizing to relieve pressure without leadership", "flagging_reason": "Indicates recurring pressure situations that require team intervention, suggesting workload distribution issues.", "confidence": 0.75}, {"quote_text": "Lily has a lot of, a lot of stuff on her plate. Is there anyone who can help her out?", "topic": "overall_experience", "first_order_code": "team member visibly overloaded needing help", "flagging_reason": "Names a specific colleague under excessive workload requiring peer intervention.", "confidence": 0.85}, {"quote_text": "we do scope up or scope down also for depending on the, uh, capacity that we have", "topic": "client_value", "first_order_code": "adjusting project scope based on available capacity", "flagging_reason": "Suggests capacity constraints that require compromising on deliverable scope.", "confidence": 0.7}]} | D17: Lily has a lot of, a lot of stuff on her plate. Is there anyone who can help her out? | E17: overall_experience | F17: Names a specific colleague under excessive workload requiring peer intervention. | G17: team member visibly overloaded needing help | H17: 0.85 | I17: Concern content - FAMILY A | J17: =IF(OR(I17="Epistemic hedging",I17="Qualifying severity while disclosing",I17="Downgrading emotional intensity"),"Hedged, qualified disclosure",IF(OR(I17="Externalizing accountability",I17="Self-attributing structural problems"),"Protective attribution shifting",IF(OR(I17="Refusal to elaborate under probing",I17="Retracting or qualifying disclosure"),"Withholding under probing",IF(OR(I17="Managing traceability and exposure",I17="Compartmentalizing the AI channel"),"Channel exposure management",IF(OR(I17="Skepticism toward remedy",I17="Anticipating dismissal or misrecognition"),"Anticipated futility of voice",IF(OR(I17="Calling out known but unaddressed issues",I17="Silence within expression"),"Recognized but unescalated concerns",I17)))))) -> Concern content - FAMILY A | N17: =IFERROR(INDEX('Hoja 1 - Supabase Transcripts'!$A:$DN,MATCH(A17,'Hoja 1 - Supabase Transcripts'!$A:$A,0),MATCH("gap_segmentation_"&E17,'Hoja 1 - Supabase Transcripts'!$2:$2,0)),"not found") -> not found
A18: 09290b39-0fb4-4096-b357-c0e613b92790 | B18: 3 | C18: {"session_id": "09290b39-0fb4-4096-b357-c0e613b92790", "quotes": [{"quote_text": "whenever there was anyone under pressure, we tried to effectively, and even sometimes autonomously without leadership, try to balance the work", "topic": "overall_experience", "first_order_code": "team self-organizing to relieve pressure without leadership", "flagging_reason": "Indicates recurring pressure situations that require team intervention, suggesting workload distribution issues.", "confidence": 0.75}, {"quote_text": "Lily has a lot of, a lot of stuff on her plate. Is there anyone who can help her out?", "topic": "overall_experience", "first_order_code": "team member visibly overloaded needing help", "flagging_reason": "Names a specific colleague under excessive workload requiring peer intervention.", "confidence": 0.85}, {"quote_text": "we do scope up or scope down also for depending on the, uh, capacity that we have", "topic": "client_value", "first_order_code": "adjusting project scope based on available capacity", "flagging_reason": "Suggests capacity constraints that require compromising on deliverable scope.", "confidence": 0.7}]} | D18: whenever there was anyone under pressure, we tried to effectively, and even sometimes autonomously without leadership, try to balance the work | E18: overall_experience | F18: Indicates recurring pressure situations that require team intervention, suggesting workload distribution issues. | G18: team self-organizing to relieve pressure without leadership | H18: 0.75 | I18: Concern content - FAMILY A | J18: =IF(OR(I18="Epistemic hedging",I18="Qualifying severity while disclosing",I18="Downgrading emotional intensity"),"Hedged, qualified disclosure",IF(OR(I18="Externalizing accountability",I18="Self-attributing structural problems"),"Protective attribution shifting",IF(OR(I18="Refusal to elaborate under probing",I18="Retracting or qualifying disclosure"),"Withholding under probing",IF(OR(I18="Managing traceability and exposure",I18="Compartmentalizing the AI channel"),"Channel exposure management",IF(OR(I18="Skepticism toward remedy",I18="Anticipating dismissal or misrecognition"),"Anticipated futility of voice",IF(OR(I18="Calling out known but unaddressed issues",I18="Silence within expression"),"Recognized but unescalated concerns",I18)))))) -> Concern content - FAMILY A | N18: =IFERROR(INDEX('Hoja 1 - Supabase Transcripts'!$A:$DN,MATCH(A18,'Hoja 1 - Supabase Transcripts'!$A:$A,0),MATCH("gap_segmentation_"&E18,'Hoja 1 - Supabase Transcripts'!$2:$2,0)),"not found") -> not found
A19: 0cd48389-6426-4350-b917-cf51f877451a | B19: 2 | C19: {"session_id": "0cd48389-6426-4350-b917-cf51f877451a", "quotes": [{"quote_text": "what could be improved is, I would say, that I know better what to do and what the overall goal is that we're trying to achieve.", "topic": "overall_experience", "first_order_code": "not knowing what to do or what the goal is", "flagging_reason": "Expresses a problem with clarity of task and purpose, stated as something that could be improved.", "confidence": 0.95}, {"quote_text": "I think it's more that no one ever properly explained it to me. And I, as I'm a new turn, I cannot join the partner meetings. So I don't really know what overall direction we are going.", "topic": "overall_experience", "first_order_code": "not knowing project direction because too junior for partner meetings", "flagging_reason": "Describes an information gap caused by exclusion from meetings, with mild attribution to being new.", "confidence": 1.0}, {"quote_text": "I don't really know who is going to receive this and what perspective they have, so what knowledge they have so far. So I don't really know how to formulate the slide.", "topic": "overall_experience", "first_order_code": "not knowing the audience or how to prepare the work", "flagging_reason": "Shows concrete friction in task execution due to lack of context about recipients.", "confidence": 0.95}, {"quote_text": "I think it is sustainable, but sometimes it's really time pressured, and then I don't have enough time to do it.", "topic": "workload_sustainability", "first_order_code": "not having enough time when deadlines are tight", "flagging_reason": "States a positive surface claim then immediately qualifies it with a time pressure concern.", "confidence": 0.9}, {"quote_text": "the next meeting is coming up really soon, and we always need to produce new slides for the next upcoming meeting.", "topic": "workload_sustainability", "first_order_code": "always needing to produce new slides for tight deadlines", "flagging_reason": "Describes the recurring pressure source that creates the time constraint mentioned earlier.", "confidence": 0.85}, {"quote_text": "I don't know if it's really giving more value in the end, but this is because of the client, because I think he wants the slides to change again and again.", "topic": "client_value", "first_order_code": "unsure if repeated changes actually add value", "flagging_reason": "Expresses doubt about the value of the work while attributing the problem to client requests rather than internal factors.", "confidence": 0.95}, {"quote_text": "For me personally, not so visible, but I think this depends, or this is because of my setting of how I am only working for one other consultant.", "topic": "leadership_engagement", "first_order_code": "leadership not visible but attributing it to my work setup", "flagging_reason": "Reports a limitation in leadership visibility but immediately reattributes it to own work arrangement rather than leadership itself.", "confidence": 0.9}]} | D19: I don't know if it's really giving more value in the end, but this is because of the client, because I think he wants the slides to change again and again. | E19: client_value | F19: Expresses doubt about the value of the work while attributing the problem to client requests rather than internal factors. | G19: unsure if repeated changes actually add value | H19: 0.95 | I19: Epistemic hedging | J19: =IF(OR(I19="Epistemic hedging",I19="Qualifying severity while disclosing",I19="Downgrading emotional intensity"),"Hedged, qualified disclosure",IF(OR(I19="Externalizing accountability",I19="Self-attributing structural problems"),"Protective attribution shifting",IF(OR(I19="Refusal to elaborate under probing",I19="Retracting or qualifying disclosure"),"Withholding under probing",IF(OR(I19="Managing traceability and exposure",I19="Compartmentalizing the AI channel"),"Channel exposure management",IF(OR(I19="Skepticism toward remedy",I19="Anticipating dismissal or misrecognition"),"Anticipated futility of voice",IF(OR(I19="Calling out known but unaddressed issues",I19="Silence within expression"),"Recognized but unescalated concerns",I19)))))) -> Hedged, qualified disclosure | K19: =_xlfn.XLOOKUP(J19,#REF!,#REF!,"0",0,1) -> #REF! | N19: =IFERROR(INDEX('Hoja 1 - Supabase Transcripts'!$A:$DN,MATCH(A19,'Hoja 1 - Supabase Transcripts'!$A:$A,0),MATCH("gap_segmentation_"&E19,'Hoja 1 - Supabase Transcripts'!$2:$2,0)),"not found") -> not found
A20: 0cd48389-6426-4350-b917-cf51f877451a | B20: 2 | C20: {"session_id": "0cd48389-6426-4350-b917-cf51f877451a", "quotes": [{"quote_text": "what could be improved is, I would say, that I know better what to do and what the overall goal is that we're trying to achieve.", "topic": "overall_experience", "first_order_code": "not knowing what to do or what the goal is", "flagging_reason": "Expresses a problem with clarity of task and purpose, stated as something that could be improved.", "confidence": 0.95}, {"quote_text": "I think it's more that no one ever properly explained it to me. And I, as I'm a new turn, I cannot join the partner meetings. So I don't really know what overall direction we are going.", "topic": "overall_experience", "first_order_code": "not knowing project direction because too junior for partner meetings", "flagging_reason": "Describes an information gap caused by exclusion from meetings, with mild attribution to being new.", "confidence": 1.0}, {"quote_text": "I don't really know who is going to receive this and what perspective they have, so what knowledge they have so far. So I don't really know how to formulate the slide.", "topic": "overall_experience", "first_order_code": "not knowing the audience or how to prepare the work", "flagging_reason": "Shows concrete friction in task execution due to lack of context about recipients.", "confidence": 0.95}, {"quote_text": "I think it is sustainable, but sometimes it's really time pressured, and then I don't have enough time to do it.", "topic": "workload_sustainability", "first_order_code": "not having enough time when deadlines are tight", "flagging_reason": "States a positive surface claim then immediately qualifies it with a time pressure concern.", "confidence": 0.9}, {"quote_text": "the next meeting is coming up really soon, and we always need to produce new slides for the next upcoming meeting.", "topic": "workload_sustainability", "first_order_code": "always needing to produce new slides for tight deadlines", "flagging_reason": "Describes the recurring pressure source that creates the time constraint mentioned earlier.", "confidence": 0.85}, {"quote_text": "I don't know if it's really giving more value in the end, but this is because of the client, because I think he wants the slides to change again and again.", "topic": "client_value", "first_order_code": "unsure if repeated changes actually add value", "flagging_reason": "Expresses doubt about the value of the work while attributing the problem to client requests rather than internal factors.", "confidence": 0.95}, {"quote_text": "For me personally, not so visible, but I think this depends, or this is because of my setting of how I am only working for one other consultant.", "topic": "leadership_engagement", "first_order_code": "leadership not visible but attributing it to my work setup", "flagging_reason": "Reports a limitation in leadership visibility but immediately reattributes it to own work arrangement rather than leadership itself.", "confidence": 0.9}]} | D20: For me personally, not so visible, but I think this depends, or this is because of my setting of how I am only working for one other consultant. | E20: leadership | F20: Reports a limitation in leadership visibility but immediately reattributes it to own work arrangement rather than leadership itself. | G20: leadership not visible but attributing it to my work setup | H20: 0.9 | I20: Self-attributing structural problems | J20: =IF(OR(I20="Epistemic hedging",I20="Qualifying severity while disclosing",I20="Downgrading emotional intensity"),"Hedged, qualified disclosure",IF(OR(I20="Externalizing accountability",I20="Self-attributing structural problems"),"Protective attribution shifting",IF(OR(I20="Refusal to elaborate under probing",I20="Retracting or qualifying disclosure"),"Withholding under probing",IF(OR(I20="Managing traceability and exposure",I20="Compartmentalizing the AI channel"),"Channel exposure management",IF(OR(I20="Skepticism toward remedy",I20="Anticipating dismissal or misrecognition"),"Anticipated futility of voice",IF(OR(I20="Calling out known but unaddressed issues",I20="Silence within expression"),"Recognized but unescalated concerns",I20)))))) -> Protective attribution shifting | K20: =_xlfn.XLOOKUP(J20,#REF!,#REF!,"0",0,1) -> #REF! | N20: =IFERROR(INDEX('Hoja 1 - Supabase Transcripts'!$A:$DN,MATCH(A20,'Hoja 1 - Supabase Transcripts'!$A:$A,0),MATCH("gap_segmentation_"&E20,'Hoja 1 - Supabase Transcripts'!$2:$2,0)),"not found") -> not found
A21: 0cd48389-6426-4350-b917-cf51f877451a | B21: 2 | C21: {"session_id": "0cd48389-6426-4350-b917-cf51f877451a", "quotes": [{"quote_text": "what could be improved is, I would say, that I know better what to do and what the overall goal is that we're trying to achieve.", "topic": "overall_experience", "first_order_code": "not knowing what to do or what the goal is", "flagging_reason": "Expresses a problem with clarity of task and purpose, stated as something that could be improved.", "confidence": 0.95}, {"quote_text": "I think it's more that no one ever properly explained it to me. And I, as I'm a new turn, I cannot join the partner meetings. So I don't really know what overall direction we are going.", "topic": "overall_experience", "first_order_code": "not knowing project direction because too junior for partner meetings", "flagging_reason": "Describes an information gap caused by exclusion from meetings, with mild attribution to being new.", "confidence": 1.0}, {"quote_text": "I don't really know who is going to receive this and what perspective they have, so what knowledge they have so far. So I don't really know how to formulate the slide.", "topic": "overall_experience", "first_order_code": "not knowing the audience or how to prepare the work", "flagging_reason": "Shows concrete friction in task execution due to lack of context about recipients.", "confidence": 0.95}, {"quote_text": "I think it is sustainable, but sometimes it's really time pressured, and then I don't have enough time to do it.", "topic": "workload_sustainability", "first_order_code": "not having enough time when deadlines are tight", "flagging_reason": "States a positive surface claim then immediately qualifies it with a time pressure concern.", "confidence": 0.9}, {"quote_text": "the next meeting is coming up really soon, and we always need to produce new slides for the next upcoming meeting.", "topic": "workload_sustainability", "first_order_code": "always needing to produce new slides for tight deadlines", "flagging_reason": "Describes the recurring pressure source that creates the time constraint mentioned earlier.", "confidence": 0.85}, {"quote_text": "I don't know if it's really giving more value in the end, but this is because of the client, because I think he wants the slides to change again and again.", "topic": "client_value", "first_order_code": "unsure if repeated changes actually add value", "flagging_reason": "Expresses doubt about the value of the work while attributing the problem to client requests rather than internal factors.", "confidence": 0.95}, {"quote_text": "For me personally, not so visible, but I think this depends, or this is because of my setting of how I am only working for one other consultant.", "topic": "leadership_engagement", "first_order_code": "leadership not visible but attributing it to my work setup", "flagging_reason": "Reports a limitation in leadership visibility but immediately reattributes it to own work arrangement rather than leadership itself.", "confidence": 0.9}]} | D21: I don't really know who is going to receive this and what perspective they have, so what knowledge they have so far. So I don't really know how to formulate the slide. | E21: overall_experience | F21: Shows concrete friction in task execution due to lack of context about recipients. | G21: not knowing the audience or how to prepare the work | H21: 0.95 | I21: Concern content - FAMILY A | J21: =IF(OR(I21="Epistemic hedging",I21="Qualifying severity while disclosing",I21="Downgrading emotional intensity"),"Hedged, qualified disclosure",IF(OR(I21="Externalizing accountability",I21="Self-attributing structural problems"),"Protective attribution shifting",IF(OR(I21="Refusal to elaborate under probing",I21="Retracting or qualifying disclosure"),"Withholding under probing",IF(OR(I21="Managing traceability and exposure",I21="Compartmentalizing the AI channel"),"Channel exposure management",IF(OR(I21="Skepticism toward remedy",I21="Anticipating dismissal or misrecognition"),"Anticipated futility of voice",IF(OR(I21="Calling out known but unaddressed issues",I21="Silence within expression"),"Recognized but unescalated concerns",I21)))))) -> Concern content - FAMILY A | N21: =IFERROR(INDEX('Hoja 1 - Supabase Transcripts'!$A:$DN,MATCH(A21,'Hoja 1 - Supabase Transcripts'!$A:$A,0),MATCH("gap_segmentation_"&E21,'Hoja 1 - Supabase Transcripts'!$2:$2,0)),"not found") -> not found
A22: 0cd48389-6426-4350-b917-cf51f877451a | B22: 2 | C22: {"session_id": "0cd48389-6426-4350-b917-cf51f877451a", "quotes": [{"quote_text": "what could be improved is, I would say, that I know better what to do and what the overall goal is that we're trying to achieve.", "topic": "overall_experience", "first_order_code": "not knowing what to do or what the goal is", "flagging_reason": "Expresses a problem with clarity of task and purpose, stated as something that could be improved.", "confidence": 0.95}, {"quote_text": "I think it's more that no one ever properly explained it to me. And I, as I'm a new turn, I cannot join the partner meetings. So I don't really know what overall direction we are going.", "topic": "overall_experience", "first_order_code": "not knowing project direction because too junior for partner meetings", "flagging_reason": "Describes an information gap caused by exclusion from meetings, with mild attribution to being new.", "confidence": 1.0}, {"quote_text": "I don't really know who is going to receive this and what perspective they have, so what knowledge they have so far. So I don't really know how to formulate the slide.", "topic": "overall_experience", "first_order_code": "not knowing the audience or how to prepare the work", "flagging_reason": "Shows concrete friction in task execution due to lack of context about recipients.", "confidence": 0.95}, {"quote_text": "I think it is sustainable, but sometimes it's really time pressured, and then I don't have enough time to do it.", "topic": "workload_sustainability", "first_order_code": "not having enough time when deadlines are tight", "flagging_reason": "States a positive surface claim then immediately qualifies it with a time pressure concern.", "confidence": 0.9}, {"quote_text": "the next meeting is coming up really soon, and we always need to produce new slides for the next upcoming meeting.", "topic": "workload_sustainability", "first_order_code": "always needing to produce new slides for tight deadlines", "flagging_reason": "Describes the recurring pressure source that creates the time constraint mentioned earlier.", "confidence": 0.85}, {"quote_text": "I don't know if it's really giving more value in the end, but this is because of the client, because I think he wants the slides to change again and again.", "topic": "client_value", "first_order_code": "unsure if repeated changes actually add value", "flagging_reason": "Expresses doubt about the value of the work while attributing the problem to client requests rather than internal factors.", "confidence": 0.95}, {"quote_text": "For me personally, not so visible, but I think this depends, or this is because of my setting of how I am only working for one other consultant.", "topic": "leadership_engagement", "first_order_code": "leadership not visible but attributing it to my work setup", "flagging_reason": "Reports a limitation in leadership visibility but immediately reattributes it to own work arrangement rather than leadership itself.", "confidence": 0.9}]} | D22: I think it's more that no one ever properly explained it to me. And I, as I'm a new turn, I cannot join the partner meetings. So I don't really know what overall direction we are going. | E22: overall_experience | F22: Describes an information gap caused by exclusion from meetings, with mild attribution to being new. | G22: not knowing project direction because too junior for partner meetings | H22: 1 | I22: Self-attributing structural problems | J22: =IF(OR(I22="Epistemic hedging",I22="Qualifying severity while disclosing",I22="Downgrading emotional intensity"),"Hedged, qualified disclosure",IF(OR(I22="Externalizing accountability",I22="Self-attributing structural problems"),"Protective attribution shifting",IF(OR(I22="Refusal to elaborate under probing",I22="Retracting or qualifying disclosure"),"Withholding under probing",IF(OR(I22="Managing traceability and exposure",I22="Compartmentalizing the AI channel"),"Channel exposure management",IF(OR(I22="Skepticism toward remedy",I22="Anticipating dismissal or misrecognition"),"Anticipated futility of voice",IF(OR(I22="Calling out known but unaddressed issues",I22="Silence within expression"),"Recognized but unescalated concerns",I22)))))) -> Protective attribution shifting | K22: =_xlfn.XLOOKUP(J22,#REF!,#REF!,"0",0,1) -> #REF! | N22: =IFERROR(INDEX('Hoja 1 - Supabase Transcripts'!$A:$DN,MATCH(A22,'Hoja 1 - Supabase Transcripts'!$A:$A,0),MATCH("gap_segmentation_"&E22,'Hoja 1 - Supabase Transcripts'!$2:$2,0)),"not found") -> not found
A23: 0cd48389-6426-4350-b917-cf51f877451a | B23: 2 | C23: {"session_id": "0cd48389-6426-4350-b917-cf51f877451a", "quotes": [{"quote_text": "what could be improved is, I would say, that I know better what to do and what the overall goal is that we're trying to achieve.", "topic": "overall_experience", "first_order_code": "not knowing what to do or what the goal is", "flagging_reason": "Expresses a problem with clarity of task and purpose, stated as something that could be improved.", "confidence": 0.95}, {"quote_text": "I think it's more that no one ever properly explained it to me. And I, as I'm a new turn, I cannot join the partner meetings. So I don't really know what overall direction we are going.", "topic": "overall_experience", "first_order_code": "not knowing project direction because too junior for partner meetings", "flagging_reason": "Describes an information gap caused by exclusion from meetings, with mild attribution to being new.", "confidence": 1.0}, {"quote_text": "I don't really know who is going to receive this and what perspective they have, so what knowledge they have so far. So I don't really know how to formulate the slide.", "topic": "overall_experience", "first_order_code": "not knowing the audience or how to prepare the work", "flagging_reason": "Shows concrete friction in task execution due to lack of context about recipients.", "confidence": 0.95}, {"quote_text": "I think it is sustainable, but sometimes it's really time pressured, and then I don't have enough time to do it.", "topic": "workload_sustainability", "first_order_code": "not having enough time when deadlines are tight", "flagging_reason": "States a positive surface claim then immediately qualifies it with a time pressure concern.", "confidence": 0.9}, {"quote_text": "the next meeting is coming up really soon, and we always need to produce new slides for the next upcoming meeting.", "topic": "workload_sustainability", "first_order_code": "always needing to produce new slides for tight deadlines", "flagging_reason": "Describes the recurring pressure source that creates the time constraint mentioned earlier.", "confidence": 0.85}, {"quote_text": "I don't know if it's really giving more value in the end, but this is because of the client, because I think he wants the slides to change again and again.", "topic": "client_value", "first_order_code": "unsure if repeated changes actually add value", "flagging_reason": "Expresses doubt about the value of the work while attributing the problem to client requests rather than internal factors.", "confidence": 0.95}, {"quote_text": "For me personally, not so visible, but I think this depends, or this is because of my setting of how I am only working for one other consultant.", "topic": "leadership_engagement", "first_order_code": "leadership not visible but attributing it to my work setup", "flagging_reason": "Reports a limitation in leadership visibility but immediately reattributes it to own work arrangement rather than leadership itself.", "confidence": 0.9}]} | D23: what could be improved is, I would say, that I know better what to do and what the overall goal is that we're trying to achieve. | E23: overall_experience | F23: Expresses a problem with clarity of task and purpose, stated as something that could be improved. | G23: not knowing what to do or what the goal is | H23: 0.95 | I23: Concern content - FAMILY A | J23: =IF(OR(I23="Epistemic hedging",I23="Qualifying severity while disclosing",I23="Downgrading emotional intensity"),"Hedged, qualified disclosure",IF(OR(I23="Externalizing accountability",I23="Self-attributing structural problems"),"Protective attribution shifting",IF(OR(I23="Refusal to elaborate under probing",I23="Retracting or qualifying disclosure"),"Withholding under probing",IF(OR(I23="Managing traceability and exposure",I23="Compartmentalizing the AI channel"),"Channel exposure management",IF(OR(I23="Skepticism toward remedy",I23="Anticipating dismissal or misrecognition"),"Anticipated futility of voice",IF(OR(I23="Calling out known but unaddressed issues",I23="Silence within expression"),"Recognized but unescalated concerns",I23)))))) -> Concern content - FAMILY A | N23: =IFERROR(INDEX('Hoja 1 - Supabase Transcripts'!$A:$DN,MATCH(A23,'Hoja 1 - Supabase Transcripts'!$A:$A,0),MATCH("gap_segmentation_"&E23,'Hoja 1 - Supabase Transcripts'!$2:$2,0)),"not found") -> not found
A24: 0cd48389-6426-4350-b917-cf51f877451a | B24: 2 | C24: {"session_id": "0cd48389-6426-4350-b917-cf51f877451a", "quotes": [{"quote_text": "what could be improved is, I would say, that I know better what to do and what the overall goal is that we're trying to achieve.", "topic": "overall_experience", "first_order_code": "not knowing what to do or what the goal is", "flagging_reason": "Expresses a problem with clarity of task and purpose, stated as something that could be improved.", "confidence": 0.95}, {"quote_text": "I think it's more that no one ever properly explained it to me. And I, as I'm a new turn, I cannot join the partner meetings. So I don't really know what overall direction we are going.", "topic": "overall_experience", "first_order_code": "not knowing project direction because too junior for partner meetings", "flagging_reason": "Describes an information gap caused by exclusion from meetings, with mild attribution to being new.", "confidence": 1.0}, {"quote_text": "I don't really know who is going to receive this and what perspective they have, so what knowledge they have so far. So I don't really know how to formulate the slide.", "topic": "overall_experience", "first_order_code": "not knowing the audience or how to prepare the work", "flagging_reason": "Shows concrete friction in task execution due to lack of context about recipients.", "confidence": 0.95}, {"quote_text": "I think it is sustainable, but sometimes it's really time pressured, and then I don't have enough time to do it.", "topic": "workload_sustainability", "first_order_code": "not having enough time when deadlines are tight", "flagging_reason": "States a positive surface claim then immediately qualifies it with a time pressure concern.", "confidence": 0.9}, {"quote_text": "the next meeting is coming up really soon, and we always need to produce new slides for the next upcoming meeting.", "topic": "workload_sustainability", "first_order_code": "always needing to produce new slides for tight deadlines", "flagging_reason": "Describes the recurring pressure source that creates the time constraint mentioned earlier.", "confidence": 0.85}, {"quote_text": "I don't know if it's really giving more value in the end, but this is because of the client, because I think he wants the slides to change again and again.", "topic": "client_value", "first_order_code": "unsure if repeated changes actually add value", "flagging_reason": "Expresses doubt about the value of the work while attributing the problem to client requests rather than internal factors.", "confidence": 0.95}, {"quote_text": "For me personally, not so visible, but I think this depends, or this is because of my setting of how I am only working for one other consultant.", "topic": "leadership_engagement", "first_order_code": "leadership not visible but attributing it to my work setup", "flagging_reason": "Reports a limitation in leadership visibility but immediately reattributes it to own work arrangement rather than leadership itself.", "confidence": 0.9}]} | D24: I think it is sustainable, but sometimes it's really time pressured, and then I don't have enough time to do it. | E24: workload_sust | F24: States a positive surface claim then immediately qualifies it with a time pressure concern. | G24: not having enough time when deadlines are tight | H24: 0.9 | I24: Concern content - FAMILY A | J24: =IF(OR(I24="Epistemic hedging",I24="Qualifying severity while disclosing",I24="Downgrading emotional intensity"),"Hedged, qualified disclosure",IF(OR(I24="Externalizing accountability",I24="Self-attributing structural problems"),"Protective attribution shifting",IF(OR(I24="Refusal to elaborate under probing",I24="Retracting or qualifying disclosure"),"Withholding under probing",IF(OR(I24="Managing traceability and exposure",I24="Compartmentalizing the AI channel"),"Channel exposure management",IF(OR(I24="Skepticism toward remedy",I24="Anticipating dismissal or misrecognition"),"Anticipated futility of voice",IF(OR(I24="Calling out known but unaddressed issues",I24="Silence within expression"),"Recognized but unescalated concerns",I24)))))) -> Concern content - FAMILY A | N24: =IFERROR(INDEX('Hoja 1 - Supabase Transcripts'!$A:$DN,MATCH(A24,'Hoja 1 - Supabase Transcripts'!$A:$A,0),MATCH("gap_segmentation_"&E24,'Hoja 1 - Supabase Transcripts'!$2:$2,0)),"not found") -> not found
A25: 0cd48389-6426-4350-b917-cf51f877451a | B25: 2 | C25: {"session_id": "0cd48389-6426-4350-b917-cf51f877451a", "quotes": [{"quote_text": "what could be improved is, I would say, that I know better what to do and what the overall goal is that we're trying to achieve.", "topic": "overall_experience", "first_order_code": "not knowing what to do or what the goal is", "flagging_reason": "Expresses a problem with clarity of task and purpose, stated as something that could be improved.", "confidence": 0.95}, {"quote_text": "I think it's more that no one ever properly explained it to me. And I, as I'm a new turn, I cannot join the partner meetings. So I don't really know what overall direction we are going.", "topic": "overall_experience", "first_order_code": "not knowing project direction because too junior for partner meetings", "flagging_reason": "Describes an information gap caused by exclusion from meetings, with mild attribution to being new.", "confidence": 1.0}, {"quote_text": "I don't really know who is going to receive this and what perspective they have, so what knowledge they have so far. So I don't really know how to formulate the slide.", "topic": "overall_experience", "first_order_code": "not knowing the audience or how to prepare the work", "flagging_reason": "Shows concrete friction in task execution due to lack of context about recipients.", "confidence": 0.95}, {"quote_text": "I think it is sustainable, but sometimes it's really time pressured, and then I don't have enough time to do it.", "topic": "workload_sustainability", "first_order_code": "not having enough time when deadlines are tight", "flagging_reason": "States a positive surface claim then immediately qualifies it with a time pressure concern.", "confidence": 0.9}, {"quote_text": "the next meeting is coming up really soon, and we always need to produce new slides for the next upcoming meeting.", "topic": "workload_sustainability", "first_order_code": "always needing to produce new slides for tight deadlines", "flagging_reason": "Describes the recurring pressure source that creates the time constraint mentioned earlier.", "confidence": 0.85}, {"quote_text": "I don't know if it's really giving more value in the end, but this is because of the client, because I think he wants the slides to change again and again.", "topic": "client_value", "first_order_code": "unsure if repeated changes actually add value", "flagging_reason": "Expresses doubt about the value of the work while attributing the problem to client requests rather than internal factors.", "confidence": 0.95}, {"quote_text": "For me personally, not so visible, but I think this depends, or this is because of my setting of how I am only working for one other consultant.", "topic": "leadership_engagement", "first_order_code": "leadership not visible but attributing it to my work setup", "flagging_reason": "Reports a limitation in leadership visibility but immediately reattributes it to own work arrangement rather than leadership itself.", "confidence": 0.9}]} | D25: the next meeting is coming up really soon, and we always need to produce new slides for the next upcoming meeting. | E25: workload_sust | F25: Describes the recurring pressure source that creates the time constraint mentioned earlier. | G25: always needing to produce new slides for tight deadlines | H25: 0.85 | I25: FAMILY_A_CONCERN_CONTENT | J25: =IF(OR(I25="Epistemic hedging",I25="Qualifying severity while disclosing",I25="Downgrading emotional intensity"),"Hedged, qualified disclosure",IF(OR(I25="Externalizing accountability",I25="Self-attributing structural problems"),"Protective attribution shifting",IF(OR(I25="Refusal to elaborate under probing",I25="Retracting or qualifying disclosure"),"Withholding under probing",IF(OR(I25="Managing traceability and exposure",I25="Compartmentalizing the AI channel"),"Channel exposure management",IF(OR(I25="Skepticism toward remedy",I25="Anticipating dismissal or misrecognition"),"Anticipated futility of voice",IF(OR(I25="Calling out known but unaddressed issues",I25="Silence within expression"),"Recognized but unescalated concerns",I25)))))) -> FAMILY_A_CONCERN_CONTENT | N25: =IFERROR(INDEX('Hoja 1 - Supabase Transcripts'!$A:$DN,MATCH(A25,'Hoja 1 - Supabase Transcripts'!$A:$A,0),MATCH("gap_segmentation_"&E25,'Hoja 1 - Supabase Transcripts'!$2:$2,0)),"not found") -> not found
A26: 15871008-ca09-43b2-b187-3f5e23648170 | B26: 4 | C26: {"session_id": "15871008-ca09-43b2-b187-3f5e23648170", "quotes": [{"quote_text": "Actually, we didn't have that much output last week as our main meeting in the middle of the week, basically on Thursday, was on a public holiday day.", "topic": "client_value", "first_order_code": "delivering less output because key meeting fell on a holiday", "flagging_reason": "Identifies a work limitation (reduced output) tied to scheduling constraints, even though stated matter-of-factly.", "confidence": 0.75}]} | D26: Actually, we didn't have that much output last week as our main meeting in the middle of the week, basically on Thursday, was on a public holiday day. | E26: client_value | F26: Identifies a work limitation (reduced output) tied to scheduling constraints, even though stated matter-of-factly. | G26: delivering less output because key meeting fell on a holiday | H26: 0.75 | I26: FAMILY_A_CONCERN_CONTENT | J26: =IF(OR(I26="Epistemic hedging",I26="Qualifying severity while disclosing",I26="Downgrading emotional intensity"),"Hedged, qualified disclosure",IF(OR(I26="Externalizing accountability",I26="Self-attributing structural problems"),"Protective attribution shifting",IF(OR(I26="Refusal to elaborate under probing",I26="Retracting or qualifying disclosure"),"Withholding under probing",IF(OR(I26="Managing traceability and exposure",I26="Compartmentalizing the AI channel"),"Channel exposure management",IF(OR(I26="Skepticism toward remedy",I26="Anticipating dismissal or misrecognition"),"Anticipated futility of voice",IF(OR(I26="Calling out known but unaddressed issues",I26="Silence within expression"),"Recognized but unescalated concerns",I26)))))) -> FAMILY_A_CONCERN_CONTENT | N26: =IFERROR(INDEX('Hoja 1 - Supabase Transcripts'!$A:$DN,MATCH(A26,'Hoja 1 - Supabase Transcripts'!$A:$A,0),MATCH("gap_segmentation_"&E26,'Hoja 1 - Supabase Transcripts'!$2:$2,0)),"not found") -> not found
A27: 15d8b27c-469f-4272-8b96-4ed69ac41634 | B27: 2 | C27: {"session_id": "15d8b27c-469f-4272-8b96-4ed69ac41634", "quotes": [{"quote_text": "not very much engagement, but also not needed, so everything fine", "topic": "leadership_engagement", "first_order_code": "low engagement framed as acceptable because not needed", "flagging_reason": "Participant minimizes a potential concern by immediately justifying that low engagement is fine in this context.", "confidence": 0.75}]} | D27: not very much engagement, but also not needed, so everything fine | E27: leadership | F27: Participant minimizes a potential concern by immediately justifying that low engagement is fine in this context. | G27: low engagement framed as acceptable because not needed | H27: 0.75 | I27: Compensatory reframing | J27: =IF(OR(I27="Epistemic hedging",I27="Qualifying severity while disclosing",I27="Downgrading emotional intensity"),"Hedged, qualified disclosure",IF(OR(I27="Externalizing accountability",I27="Self-attributing structural problems"),"Protective attribution shifting",IF(OR(I27="Refusal to elaborate under probing",I27="Retracting or qualifying disclosure"),"Withholding under probing",IF(OR(I27="Managing traceability and exposure",I27="Compartmentalizing the AI channel"),"Channel exposure management",IF(OR(I27="Skepticism toward remedy",I27="Anticipating dismissal or misrecognition"),"Anticipated futility of voice",IF(OR(I27="Calling out known but unaddressed issues",I27="Silence within expression"),"Recognized but unescalated concerns",I27)))))) -> Compensatory reframing | K27: =_xlfn.XLOOKUP(J27,#REF!,#REF!,"0",0,1) -> #REF! | N27: =IFERROR(INDEX('Hoja 1 - Supabase Transcripts'!$A:$DN,MATCH(A27,'Hoja 1 - Supabase Transcripts'!$A:$A,0),MATCH("gap_segmentation_"&E27,'Hoja 1 - Supabase Transcripts'!$2:$2,0)),"not found") -> not found
A28: 1783f47a-7863-4476-b610-31281650b181 | B28: 1 | C28: {"session_id": "1783f47a-7863-4476-b610-31281650b181", "quotes": [{"quote_text": "that, that not, did not happen the last weeks because I was in the US and, uh, the others were in Germany.", "topic": "overall_experience", "first_order_code": "lost co-location due to geographic split", "flagging_reason": "Points to a disruption in team collaboration caused by physical separation across continents.", "confidence": 0.75}, {"quote_text": "the weeks prior to, to last week were more intense", "topic": "workload_sustainability", "first_order_code": "prior weeks were more intense than last week", "flagging_reason": "Acknowledges a workload concern in recent past, contrasted with current lighter week.", "confidence": 0.7}, {"quote_text": "This is also due to the time difference to the US and, and other commitments that our senior stakeholders had.", "topic": "workload_sustainability", "first_order_code": "lighter workload tied to senior stakeholder unavailability", "flagging_reason": "Attributes reduced workload to external factors rather than improved workflow, suggesting structural friction.", "confidence": 0.8}, {"quote_text": "the client often derails, which makes it harder to prioritize and to also, um, push back because certain topics come up, uh, all the time.", "topic": "client_value", "first_order_code": "client derails priorities making it hard to push back", "flagging_reason": "Expresses difficulty maintaining focus and setting boundaries due to client behavior.", "confidence": 0.95}, {"quote_text": "I know there are several projects running, uh, which makes it harder to, to engage fully.", "topic": "leadership_engagement", "first_order_code": "leadership spread across projects makes full engagement harder", "flagging_reason": "Acknowledges a limitation in leadership availability softened by attributing it to workload context.", "confidence": 0.85}]} | D28: the client often derails, which makes it harder to prioritize and to also, um, push back because certain topics come up, uh, all the time. | E28: client_value | F28: Expresses difficulty maintaining focus and setting boundaries due to client behavior. | G28: client derails priorities making it hard to push back | H28: 0.95 | I28: Externalizing accountability | J28: =IF(OR(I28="Epistemic hedging",I28="Qualifying severity while disclosing",I28="Downgrading emotional intensity"),"Hedged, qualified disclosure",IF(OR(I28="Externalizing accountability",I28="Self-attributing structural problems"),"Protective attribution shifting",IF(OR(I28="Refusal to elaborate under probing",I28="Retracting or qualifying disclosure"),"Withholding under probing",IF(OR(I28="Managing traceability and exposure",I28="Compartmentalizing the AI channel"),"Channel exposure management",IF(OR(I28="Skepticism toward remedy",I28="Anticipating dismissal or misrecognition"),"Anticipated futility of voice",IF(OR(I28="Calling out known but unaddressed issues",I28="Silence within expression"),"Recognized but unescalated concerns",I28)))))) -> Protective attribution shifting | K28: =_xlfn.XLOOKUP(J28,#REF!,#REF!,"0",0,1) -> #REF! | N28: =IFERROR(INDEX('Hoja 1 - Supabase Transcripts'!$A:$DN,MATCH(A28,'Hoja 1 - Supabase Transcripts'!$A:$A,0),MATCH("gap_segmentation_"&E28,'Hoja 1 - Supabase Transcripts'!$2:$2,0)),"not found") -> not found
A29: 1783f47a-7863-4476-b610-31281650b181 | B29: 1 | C29: {"session_id": "1783f47a-7863-4476-b610-31281650b181", "quotes": [{"quote_text": "that, that not, did not happen the last weeks because I was in the US and, uh, the others were in Germany.", "topic": "overall_experience", "first_order_code": "lost co-location due to geographic split", "flagging_reason": "Points to a disruption in team collaboration caused by physical separation across continents.", "confidence": 0.75}, {"quote_text": "the weeks prior to, to last week were more intense", "topic": "workload_sustainability", "first_order_code": "prior weeks were more intense than last week", "flagging_reason": "Acknowledges a workload concern in recent past, contrasted with current lighter week.", "confidence": 0.7}, {"quote_text": "This is also due to the time difference to the US and, and other commitments that our senior stakeholders had.", "topic": "workload_sustainability", "first_order_code": "lighter workload tied to senior stakeholder unavailability", "flagging_reason": "Attributes reduced workload to external factors rather than improved workflow, suggesting structural friction.", "confidence": 0.8}, {"quote_text": "the client often derails, which makes it harder to prioritize and to also, um, push back because certain topics come up, uh, all the time.", "topic": "client_value", "first_order_code": "client derails priorities making it hard to push back", "flagging_reason": "Expresses difficulty maintaining focus and setting boundaries due to client behavior.", "confidence": 0.95}, {"quote_text": "I know there are several projects running, uh, which makes it harder to, to engage fully.", "topic": "leadership_engagement", "first_order_code": "leadership spread across projects makes full engagement harder", "flagging_reason": "Acknowledges a limitation in leadership availability softened by attributing it to workload context.", "confidence": 0.85}]} | D29: I know there are several projects running, uh, which makes it harder to, to engage fully. | E29: leadership | F29: Acknowledges a limitation in leadership availability softened by attributing it to workload context. | G29: leadership spread across projects makes full engagement harder | H29: 0.85 | I29: Rationalizing leadership absence | J29: =IF(OR(I29="Epistemic hedging",I29="Qualifying severity while disclosing",I29="Downgrading emotional intensity"),"Hedged, qualified disclosure",IF(OR(I29="Externalizing accountability",I29="Self-attributing structural problems"),"Protective attribution shifting",IF(OR(I29="Refusal to elaborate under probing",I29="Retracting or qualifying disclosure"),"Withholding under probing",IF(OR(I29="Managing traceability and exposure",I29="Compartmentalizing the AI channel"),"Channel exposure management",IF(OR(I29="Skepticism toward remedy",I29="Anticipating dismissal or misrecognition"),"Anticipated futility of voice",IF(OR(I29="Calling out known but unaddressed issues",I29="Silence within expression"),"Recognized but unescalated concerns",I29)))))) -> Rationalizing leadership absence | K29: =_xlfn.XLOOKUP(J29,#REF!,#REF!,"0",0,1) -> #REF! | N29: =IFERROR(INDEX('Hoja 1 - Supabase Transcripts'!$A:$DN,MATCH(A29,'Hoja 1 - Supabase Transcripts'!$A:$A,0),MATCH("gap_segmentation_"&E29,'Hoja 1 - Supabase Transcripts'!$2:$2,0)),"not found") -> not found
A30: 1783f47a-7863-4476-b610-31281650b181 | B30: 1 | C30: {"session_id": "1783f47a-7863-4476-b610-31281650b181", "quotes": [{"quote_text": "that, that not, did not happen the last weeks because I was in the US and, uh, the others were in Germany.", "topic": "overall_experience", "first_order_code": "lost co-location due to geographic split", "flagging_reason": "Points to a disruption in team collaboration caused by physical separation across continents.", "confidence": 0.75}, {"quote_text": "the weeks prior to, to last week were more intense", "topic": "workload_sustainability", "first_order_code": "prior weeks were more intense than last week", "flagging_reason": "Acknowledges a workload concern in recent past, contrasted with current lighter week.", "confidence": 0.7}, {"quote_text": "This is also due to the time difference to the US and, and other commitments that our senior stakeholders had.", "topic": "workload_sustainability", "first_order_code": "lighter workload tied to senior stakeholder unavailability", "flagging_reason": "Attributes reduced workload to external factors rather than improved workflow, suggesting structural friction.", "confidence": 0.8}, {"quote_text": "the client often derails, which makes it harder to prioritize and to also, um, push back because certain topics come up, uh, all the time.", "topic": "client_value", "first_order_code": "client derails priorities making it hard to push back", "flagging_reason": "Expresses difficulty maintaining focus and setting boundaries due to client behavior.", "confidence": 0.95}, {"quote_text": "I know there are several projects running, uh, which makes it harder to, to engage fully.", "topic": "leadership_engagement", "first_order_code": "leadership spread across projects makes full engagement harder", "flagging_reason": "Acknowledges a limitation in leadership availability softened by attributing it to workload context.", "confidence": 0.85}]} | D30: that, that not, did not happen the last weeks because I was in the US and, uh, the others were in Germany. | E30: overall_experience | F30: Points to a disruption in team collaboration caused by physical separation across continents. | G30: lost co-location due to geographic split | H30: 0.75 | I30: Concern content - FAMILY A | J30: =IF(OR(I30="Epistemic hedging",I30="Qualifying severity while disclosing",I30="Downgrading emotional intensity"),"Hedged, qualified disclosure",IF(OR(I30="Externalizing accountability",I30="Self-attributing structural problems"),"Protective attribution shifting",IF(OR(I30="Refusal to elaborate under probing",I30="Retracting or qualifying disclosure"),"Withholding under probing",IF(OR(I30="Managing traceability and exposure",I30="Compartmentalizing the AI channel"),"Channel exposure management",IF(OR(I30="Skepticism toward remedy",I30="Anticipating dismissal or misrecognition"),"Anticipated futility of voice",IF(OR(I30="Calling out known but unaddressed issues",I30="Silence within expression"),"Recognized but unescalated concerns",I30)))))) -> Concern content - FAMILY A | N30: =IFERROR(INDEX('Hoja 1 - Supabase Transcripts'!$A:$DN,MATCH(A30,'Hoja 1 - Supabase Transcripts'!$A:$A,0),MATCH("gap_segmentation_"&E30,'Hoja 1 - Supabase Transcripts'!$2:$2,0)),"not found") -> not found
A31: 1783f47a-7863-4476-b610-31281650b181 | B31: 1 | C31: {"session_id": "1783f47a-7863-4476-b610-31281650b181", "quotes": [{"quote_text": "that, that not, did not happen the last weeks because I was in the US and, uh, the others were in Germany.", "topic": "overall_experience", "first_order_code": "lost co-location due to geographic split", "flagging_reason": "Points to a disruption in team collaboration caused by physical separation across continents.", "confidence": 0.75}, {"quote_text": "the weeks prior to, to last week were more intense", "topic": "workload_sustainability", "first_order_code": "prior weeks were more intense than last week", "flagging_reason": "Acknowledges a workload concern in recent past, contrasted with current lighter week.", "confidence": 0.7}, {"quote_text": "This is also due to the time difference to the US and, and other commitments that our senior stakeholders had.", "topic": "workload_sustainability", "first_order_code": "lighter workload tied to senior stakeholder unavailability", "flagging_reason": "Attributes reduced workload to external factors rather than improved workflow, suggesting structural friction.", "confidence": 0.8}, {"quote_text": "the client often derails, which makes it harder to prioritize and to also, um, push back because certain topics come up, uh, all the time.", "topic": "client_value", "first_order_code": "client derails priorities making it hard to push back", "flagging_reason": "Expresses difficulty maintaining focus and setting boundaries due to client behavior.", "confidence": 0.95}, {"quote_text": "I know there are several projects running, uh, which makes it harder to, to engage fully.", "topic": "leadership_engagement", "first_order_code": "leadership spread across projects makes full engagement harder", "flagging_reason": "Acknowledges a limitation in leadership availability softened by attributing it to workload context.", "confidence": 0.85}]} | D31: This is also due to the time difference to the US and, and other commitments that our senior stakeholders had. | E31: workload_sust | F31: Attributes reduced workload to external factors rather than improved workflow, suggesting structural friction. | G31: lighter workload tied to senior stakeholder unavailability | H31: 0.8 | I31: Externalizing accountability | J31: =IF(OR(I31="Epistemic hedging",I31="Qualifying severity while disclosing",I31="Downgrading emotional intensity"),"Hedged, qualified disclosure",IF(OR(I31="Externalizing accountability",I31="Self-attributing structural problems"),"Protective attribution shifting",IF(OR(I31="Refusal to elaborate under probing",I31="Retracting or qualifying disclosure"),"Withholding under probing",IF(OR(I31="Managing traceability and exposure",I31="Compartmentalizing the AI channel"),"Channel exposure management",IF(OR(I31="Skepticism toward remedy",I31="Anticipating dismissal or misrecognition"),"Anticipated futility of voice",IF(OR(I31="Calling out known but unaddressed issues",I31="Silence within expression"),"Recognized but unescalated concerns",I31)))))) -> Protective attribution shifting | K31: =_xlfn.XLOOKUP(J31,#REF!,#REF!,"0",0,1) -> #REF! | N31: =IFERROR(INDEX('Hoja 1 - Supabase Transcripts'!$A:$DN,MATCH(A31,'Hoja 1 - Supabase Transcripts'!$A:$A,0),MATCH("gap_segmentation_"&E31,'Hoja 1 - Supabase Transcripts'!$2:$2,0)),"not found") -> not found
A32: 1783f47a-7863-4476-b610-31281650b181 | B32: 1 | C32: {"session_id": "1783f47a-7863-4476-b610-31281650b181", "quotes": [{"quote_text": "that, that not, did not happen the last weeks because I was in the US and, uh, the others were in Germany.", "topic": "overall_experience", "first_order_code": "lost co-location due to geographic split", "flagging_reason": "Points to a disruption in team collaboration caused by physical separation across continents.", "confidence": 0.75}, {"quote_text": "the weeks prior to, to last week were more intense", "topic": "workload_sustainability", "first_order_code": "prior weeks were more intense than last week", "flagging_reason": "Acknowledges a workload concern in recent past, contrasted with current lighter week.", "confidence": 0.7}, {"quote_text": "This is also due to the time difference to the US and, and other commitments that our senior stakeholders had.", "topic": "workload_sustainability", "first_order_code": "lighter workload tied to senior stakeholder unavailability", "flagging_reason": "Attributes reduced workload to external factors rather than improved workflow, suggesting structural friction.", "confidence": 0.8}, {"quote_text": "the client often derails, which makes it harder to prioritize and to also, um, push back because certain topics come up, uh, all the time.", "topic": "client_value", "first_order_code": "client derails priorities making it hard to push back", "flagging_reason": "Expresses difficulty maintaining focus and setting boundaries due to client behavior.", "confidence": 0.95}, {"quote_text": "I know there are several projects running, uh, which makes it harder to, to engage fully.", "topic": "leadership_engagement", "first_order_code": "leadership spread across projects makes full engagement harder", "flagging_reason": "Acknowledges a limitation in leadership availability softened by attributing it to workload context.", "confidence": 0.85}]} | D32: the weeks prior to, to last week were more intense | E32: workload_sust | F32: Acknowledges a workload concern in recent past, contrasted with current lighter week. | G32: prior weeks were more intense than last week | H32: 0.7 | I32: Qualifying severity while disclosing | J32: =IF(OR(I32="Epistemic hedging",I32="Qualifying severity while disclosing",I32="Downgrading emotional intensity"),"Hedged, qualified disclosure",IF(OR(I32="Externalizing accountability",I32="Self-attributing structural problems"),"Protective attribution shifting",IF(OR(I32="Refusal to elaborate under probing",I32="Retracting or qualifying disclosure"),"Withholding under probing",IF(OR(I32="Managing traceability and exposure",I32="Compartmentalizing the AI channel"),"Channel exposure management",IF(OR(I32="Skepticism toward remedy",I32="Anticipating dismissal or misrecognition"),"Anticipated futility of voice",IF(OR(I32="Calling out known but unaddressed issues",I32="Silence within expression"),"Recognized but unescalated concerns",I32)))))) -> Hedged, qualified disclosure | K32: =_xlfn.XLOOKUP(J32,#REF!,#REF!,"0",0,1) -> #REF! | N32: =IFERROR(INDEX('Hoja 1 - Supabase Transcripts'!$A:$DN,MATCH(A32,'Hoja 1 - Supabase Transcripts'!$A:$A,0),MATCH("gap_segmentation_"&E32,'Hoja 1 - Supabase Transcripts'!$2:$2,0)),"not found") -> not found
A33: 1a9374ce-a316-4c07-a7cb-d1370fd93475 | B33: 2 | C33: {"session_id": "1a9374ce-a316-4c07-a7cb-d1370fd93475", "quotes": [{"quote_text": "I think sometimes we can be even more efficient within feedback circles.", "topic": "overall_experience", "first_order_code": "feeling feedback circles could be more efficient", "flagging_reason": "Participant identifies a friction point in team processes while discussing a generally positive experience.", "confidence": 0.85}, {"quote_text": "I think sometimes we have a lot of alignment sessions, alignment loops, um, which is sometimes maybe, you know, we can improve even better on making this more efficient.", "topic": "leadership_engagement", "first_order_code": "too many alignment sessions slowing things down", "flagging_reason": "Participant softens a concern about excessive meetings with hedging language and suggestion for improvement.", "confidence": 0.9}]} | D33: I think sometimes we have a lot of alignment sessions, alignment loops, um, which is sometimes maybe, you know, we can improve even better on making this more efficient. | E33: leadership | F33: Participant softens a concern about excessive meetings with hedging language and suggestion for improvement. | G33: too many alignment sessions slowing things down | H33: 0.9 | I33: Concern content - FAMILY A | J33: =IF(OR(I33="Epistemic hedging",I33="Qualifying severity while disclosing",I33="Downgrading emotional intensity"),"Hedged, qualified disclosure",IF(OR(I33="Externalizing accountability",I33="Self-attributing structural problems"),"Protective attribution shifting",IF(OR(I33="Refusal to elaborate under probing",I33="Retracting or qualifying disclosure"),"Withholding under probing",IF(OR(I33="Managing traceability and exposure",I33="Compartmentalizing the AI channel"),"Channel exposure management",IF(OR(I33="Skepticism toward remedy",I33="Anticipating dismissal or misrecognition"),"Anticipated futility of voice",IF(OR(I33="Calling out known but unaddressed issues",I33="Silence within expression"),"Recognized but unescalated concerns",I33)))))) -> Concern content - FAMILY A | N33: =IFERROR(INDEX('Hoja 1 - Supabase Transcripts'!$A:$DN,MATCH(A33,'Hoja 1 - Supabase Transcripts'!$A:$A,0),MATCH("gap_segmentation_"&E33,'Hoja 1 - Supabase Transcripts'!$2:$2,0)),"not found") -> not found
A34: 1a9374ce-a316-4c07-a7cb-d1370fd93475 | B34: 2 | C34: {"session_id": "1a9374ce-a316-4c07-a7cb-d1370fd93475", "quotes": [{"quote_text": "I think sometimes we can be even more efficient within feedback circles.", "topic": "overall_experience", "first_order_code": "feeling feedback circles could be more efficient", "flagging_reason": "Participant identifies a friction point in team processes while discussing a generally positive experience.", "confidence": 0.85}, {"quote_text": "I think sometimes we have a lot of alignment sessions, alignment loops, um, which is sometimes maybe, you know, we can improve even better on making this more efficient.", "topic": "leadership_engagement", "first_order_code": "too many alignment sessions slowing things down", "flagging_reason": "Participant softens a concern about excessive meetings with hedging language and suggestion for improvement.", "confidence": 0.9}]} | D34: I think sometimes we can be even more efficient within feedback circles. | E34: overall_experience | F34: Participant identifies a friction point in team processes while discussing a generally positive experience. | G34: feeling feedback circles could be more efficient | H34: 0.85 | I34: Concern content - FAMILY A | J34: =IF(OR(I34="Epistemic hedging",I34="Qualifying severity while disclosing",I34="Downgrading emotional intensity"),"Hedged, qualified disclosure",IF(OR(I34="Externalizing accountability",I34="Self-attributing structural problems"),"Protective attribution shifting",IF(OR(I34="Refusal to elaborate under probing",I34="Retracting or qualifying disclosure"),"Withholding under probing",IF(OR(I34="Managing traceability and exposure",I34="Compartmentalizing the AI channel"),"Channel exposure management",IF(OR(I34="Skepticism toward remedy",I34="Anticipating dismissal or misrecognition"),"Anticipated futility of voice",IF(OR(I34="Calling out known but unaddressed issues",I34="Silence within expression"),"Recognized but unescalated concerns",I34)))))) -> Concern content - FAMILY A | N34: =IFERROR(INDEX('Hoja 1 - Supabase Transcripts'!$A:$DN,MATCH(A34,'Hoja 1 - Supabase Transcripts'!$A:$A,0),MATCH("gap_segmentation_"&E34,'Hoja 1 - Supabase Transcripts'!$2:$2,0)),"not found") -> not found
A35: 1bd3f940-d5d8-4bd7-a2b2-1fc66fc0f4a2 | B35: 2 | C35: {"session_id": "1bd3f940-d5d8-4bd7-a2b2-1fc66fc0f4a2", "quotes": [{"quote_text": "I would say, um, load balancing, especially for Lily. Uh, I think she's now staffed on, um, two projects basically, and it's a bit hard, I think, then to clearly show, you know, the capacity for her.", "topic": "overall_experience", "first_order_code": "colleague staffed on two projects making capacity unclear", "flagging_reason": "Raises a work concern about a named colleague's workload allocation and visibility.", "confidence": 0.95}, {"quote_text": "I would say su- sustainable-ish.", "topic": "workload_sustainability", "first_order_code": "workload only sustainable-ish", "flagging_reason": "Hedges the sustainability assessment with a qualifier that suggests it is not fully sustainable.", "confidence": 0.85}, {"quote_text": "I think the Wattenfall project was pretty hectic, um, as expected, and also the Avato demo one is also pretty hectic.", "topic": "workload_sustainability", "first_order_code": "two projects running pretty hectic", "flagging_reason": "States work intensity concern across two named projects, softened with 'as expected'.", "confidence": 0.9}, {"quote_text": "Um, so I think we need to do a better job of owning the process.", "topic": "workload_sustainability", "first_order_code": "team needs to do better job owning the process", "flagging_reason": "Identifies a process gap or friction that needs improvement.", "confidence": 0.9}, {"quote_text": "Um, basically, we don't follow a new normal. And... Oh, no, actually, that's not true. New normal is kinda...is okay", "topic": "workload_sustainability", "first_order_code": "self-correcting initial claim about not following new normal", "flagging_reason": "Initially raises a concern about process adherence, then immediately retracts and softens it.", "confidence": 0.8}, {"quote_text": "for example, starting before 9:00 and having to work while team dinners, et cetera. Not great, but also, I think, manageable and will be better in the future.", "topic": "workload_sustainability", "first_order_code": "starting early and working during team dinners not great but manageable", "flagging_reason": "States a work-life boundary concern but immediately minimizes it as manageable and temporary.", "confidence": 0.95}]} | D35: I would say, um, load balancing, especially for Lily. Uh, I think she's now staffed on, um, two projects basically, and it's a bit hard, I think, then to clearly show, you know, the capacity for her. | E35: overall_experience | F35: Raises a work concern about a named colleague's workload allocation and visibility. | G35: colleague staffed on two projects making capacity unclear | H35: 0.95 | I35: FAMILY_A_CONCERN_CONTENT | J35: =IF(OR(I35="Epistemic hedging",I35="Qualifying severity while disclosing",I35="Downgrading emotional intensity"),"Hedged, qualified disclosure",IF(OR(I35="Externalizing accountability",I35="Self-attributing structural problems"),"Protective attribution shifting",IF(OR(I35="Refusal to elaborate under probing",I35="Retracting or qualifying disclosure"),"Withholding under probing",IF(OR(I35="Managing traceability and exposure",I35="Compartmentalizing the AI channel"),"Channel exposure management",IF(OR(I35="Skepticism toward remedy",I35="Anticipating dismissal or misrecognition"),"Anticipated futility of voice",IF(OR(I35="Calling out known but unaddressed issues",I35="Silence within expression"),"Recognized but unescalated concerns",I35)))))) -> FAMILY_A_CONCERN_CONTENT | N35: =IFERROR(INDEX('Hoja 1 - Supabase Transcripts'!$A:$DN,MATCH(A35,'Hoja 1 - Supabase Transcripts'!$A:$A,0),MATCH("gap_segmentation_"&E35,'Hoja 1 - Supabase Transcripts'!$2:$2,0)),"not found") -> not found
A36: 1bd3f940-d5d8-4bd7-a2b2-1fc66fc0f4a2 | B36: 2 | C36: {"session_id": "1bd3f940-d5d8-4bd7-a2b2-1fc66fc0f4a2", "quotes": [{"quote_text": "I would say, um, load balancing, especially for Lily. Uh, I think she's now staffed on, um, two projects basically, and it's a bit hard, I think, then to clearly show, you know, the capacity for her.", "topic": "overall_experience", "first_order_code": "colleague staffed on two projects making capacity unclear", "flagging_reason": "Raises a work concern about a named colleague's workload allocation and visibility.", "confidence": 0.95}, {"quote_text": "I would say su- sustainable-ish.", "topic": "workload_sustainability", "first_order_code": "workload only sustainable-ish", "flagging_reason": "Hedges the sustainability assessment with a qualifier that suggests it is not fully sustainable.", "confidence": 0.85}, {"quote_text": "I think the Wattenfall project was pretty hectic, um, as expected, and also the Avato demo one is also pretty hectic.", "topic": "workload_sustainability", "first_order_code": "two projects running pretty hectic", "flagging_reason": "States work intensity concern across two named projects, softened with 'as expected'.", "confidence": 0.9}, {"quote_text": "Um, so I think we need to do a better job of owning the process.", "topic": "workload_sustainability", "first_order_code": "team needs to do better job owning the process", "flagging_reason": "Identifies a process gap or friction that needs improvement.", "confidence": 0.9}, {"quote_text": "Um, basically, we don't follow a new normal. And... Oh, no, actually, that's not true. New normal is kinda...is okay", "topic": "workload_sustainability", "first_order_code": "self-correcting initial claim about not following new normal", "flagging_reason": "Initially raises a concern about process adherence, then immediately retracts and softens it.", "confidence": 0.8}, {"quote_text": "for example, starting before 9:00 and having to work while team dinners, et cetera. Not great, but also, I think, manageable and will be better in the future.", "topic": "workload_sustainability", "first_order_code": "starting early and working during team dinners not great but manageable", "flagging_reason": "States a work-life boundary concern but immediately minimizes it as manageable and temporary.", "confidence": 0.95}]} | D36: I think the Wattenfall project was pretty hectic, um, as expected, and also the Avato demo one is also pretty hectic. | E36: workload_sust | F36: States work intensity concern across two named projects, softened with 'as expected'. | G36: two projects running pretty hectic | H36: 0.9 | I36: Concern content - FAMILY A | J36: =IF(OR(I36="Epistemic hedging",I36="Qualifying severity while disclosing",I36="Downgrading emotional intensity"),"Hedged, qualified disclosure",IF(OR(I36="Externalizing accountability",I36="Self-attributing structural problems"),"Protective attribution shifting",IF(OR(I36="Refusal to elaborate under probing",I36="Retracting or qualifying disclosure"),"Withholding under probing",IF(OR(I36="Managing traceability and exposure",I36="Compartmentalizing the AI channel"),"Channel exposure management",IF(OR(I36="Skepticism toward remedy",I36="Anticipating dismissal or misrecognition"),"Anticipated futility of voice",IF(OR(I36="Calling out known but unaddressed issues",I36="Silence within expression"),"Recognized but unescalated concerns",I36)))))) -> Concern content - FAMILY A | N36: =IFERROR(INDEX('Hoja 1 - Supabase Transcripts'!$A:$DN,MATCH(A36,'Hoja 1 - Supabase Transcripts'!$A:$A,0),MATCH("gap_segmentation_"&E36,'Hoja 1 - Supabase Transcripts'!$2:$2,0)),"not found") -> not found
A37: 1bd3f940-d5d8-4bd7-a2b2-1fc66fc0f4a2 | B37: 2 | C37: {"session_id": "1bd3f940-d5d8-4bd7-a2b2-1fc66fc0f4a2", "quotes": [{"quote_text": "I would say, um, load balancing, especially for Lily. Uh, I think she's now staffed on, um, two projects basically, and it's a bit hard, I think, then to clearly show, you know, the capacity for her.", "topic": "overall_experience", "first_order_code": "colleague staffed on two projects making capacity unclear", "flagging_reason": "Raises a work concern about a named colleague's workload allocation and visibility.", "confidence": 0.95}, {"quote_text": "I would say su- sustainable-ish.", "topic": "workload_sustainability", "first_order_code": "workload only sustainable-ish", "flagging_reason": "Hedges the sustainability assessment with a qualifier that suggests it is not fully sustainable.", "confidence": 0.85}, {"quote_text": "I think the Wattenfall project was pretty hectic, um, as expected, and also the Avato demo one is also pretty hectic.", "topic": "workload_sustainability", "first_order_code": "two projects running pretty hectic", "flagging_reason": "States work intensity concern across two named projects, softened with 'as expected'.", "confidence": 0.9}, {"quote_text": "Um, so I think we need to do a better job of owning the process.", "topic": "workload_sustainability", "first_order_code": "team needs to do better job owning the process", "flagging_reason": "Identifies a process gap or friction that needs improvement.", "confidence": 0.9}, {"quote_text": "Um, basically, we don't follow a new normal. And... Oh, no, actually, that's not true. New normal is kinda...is okay", "topic": "workload_sustainability", "first_order_code": "self-correcting initial claim about not following new normal", "flagging_reason": "Initially raises a concern about process adherence, then immediately retracts and softens it.", "confidence": 0.8}, {"quote_text": "for example, starting before 9:00 and having to work while team dinners, et cetera. Not great, but also, I think, manageable and will be better in the future.", "topic": "workload_sustainability", "first_order_code": "starting early and working during team dinners not great but manageable", "flagging_reason": "States a work-life boundary concern but immediately minimizes it as manageable and temporary.", "confidence": 0.95}]} | D37: I would say su- sustainable-ish. | E37: workload_sust | F37: Hedges the sustainability assessment with a qualifier that suggests it is not fully sustainable. | G37: workload only sustainable-ish | H37: 0.85 | I37: Concern content - FAMILY A | J37: =IF(OR(I37="Epistemic hedging",I37="Qualifying severity while disclosing",I37="Downgrading emotional intensity"),"Hedged, qualified disclosure",IF(OR(I37="Externalizing accountability",I37="Self-attributing structural problems"),"Protective attribution shifting",IF(OR(I37="Refusal to elaborate under probing",I37="Retracting or qualifying disclosure"),"Withholding under probing",IF(OR(I37="Managing traceability and exposure",I37="Compartmentalizing the AI channel"),"Channel exposure management",IF(OR(I37="Skepticism toward remedy",I37="Anticipating dismissal or misrecognition"),"Anticipated futility of voice",IF(OR(I37="Calling out known but unaddressed issues",I37="Silence within expression"),"Recognized but unescalated concerns",I37)))))) -> Concern content - FAMILY A | N37: =IFERROR(INDEX('Hoja 1 - Supabase Transcripts'!$A:$DN,MATCH(A37,'Hoja 1 - Supabase Transcripts'!$A:$A,0),MATCH("gap_segmentation_"&E37,'Hoja 1 - Supabase Transcripts'!$2:$2,0)),"not found") -> not found
A38: 1bd3f940-d5d8-4bd7-a2b2-1fc66fc0f4a2 | B38: 2 | C38: {"session_id": "1bd3f940-d5d8-4bd7-a2b2-1fc66fc0f4a2", "quotes": [{"quote_text": "I would say, um, load balancing, especially for Lily. Uh, I think she's now staffed on, um, two projects basically, and it's a bit hard, I think, then to clearly show, you know, the capacity for her.", "topic": "overall_experience", "first_order_code": "colleague staffed on two projects making capacity unclear", "flagging_reason": "Raises a work concern about a named colleague's workload allocation and visibility.", "confidence": 0.95}, {"quote_text": "I would say su- sustainable-ish.", "topic": "workload_sustainability", "first_order_code": "workload only sustainable-ish", "flagging_reason": "Hedges the sustainability assessment with a qualifier that suggests it is not fully sustainable.", "confidence": 0.85}, {"quote_text": "I think the Wattenfall project was pretty hectic, um, as expected, and also the Avato demo one is also pretty hectic.", "topic": "workload_sustainability", "first_order_code": "two projects running pretty hectic", "flagging_reason": "States work intensity concern across two named projects, softened with 'as expected'.", "confidence": 0.9}, {"quote_text": "Um, so I think we need to do a better job of owning the process.", "topic": "workload_sustainability", "first_order_code": "team needs to do better job owning the process", "flagging_reason": "Identifies a process gap or friction that needs improvement.", "confidence": 0.9}, {"quote_text": "Um, basically, we don't follow a new normal. And... Oh, no, actually, that's not true. New normal is kinda...is okay", "topic": "workload_sustainability", "first_order_code": "self-correcting initial claim about not following new normal", "flagging_reason": "Initially raises a concern about process adherence, then immediately retracts and softens it.", "confidence": 0.8}, {"quote_text": "for example, starting before 9:00 and having to work while team dinners, et cetera. Not great, but also, I think, manageable and will be better in the future.", "topic": "workload_sustainability", "first_order_code": "starting early and working during team dinners not great but manageable", "flagging_reason": "States a work-life boundary concern but immediately minimizes it as manageable and temporary.", "confidence": 0.95}]} | D38: Um, basically, we don't follow a new normal. And... Oh, no, actually, that's not true. New normal is kinda...is okay | E38: workload_sust | F38: Initially raises a concern about process adherence, then immediately retracts and softens it. | G38: self-correcting initial claim about not following new normal | H38: 0.8 | I38: Retracting or qualifying disclosure | J38: =IF(OR(I38="Epistemic hedging",I38="Qualifying severity while disclosing",I38="Downgrading emotional intensity"),"Hedged, qualified disclosure",IF(OR(I38="Externalizing accountability",I38="Self-attributing structural problems"),"Protective attribution shifting",IF(OR(I38="Refusal to elaborate under probing",I38="Retracting or qualifying disclosure"),"Withholding under probing",IF(OR(I38="Managing traceability and exposure",I38="Compartmentalizing the AI channel"),"Channel exposure management",IF(OR(I38="Skepticism toward remedy",I38="Anticipating dismissal or misrecognition"),"Anticipated futility of voice",IF(OR(I38="Calling out known but unaddressed issues",I38="Silence within expression"),"Recognized but unescalated concerns",I38)))))) -> Withholding under probing | K38: =_xlfn.XLOOKUP(J38,#REF!,#REF!,"0",0,1) -> #REF! | N38: =IFERROR(INDEX('Hoja 1 - Supabase Transcripts'!$A:$DN,MATCH(A38,'Hoja 1 - Supabase Transcripts'!$A:$A,0),MATCH("gap_segmentation_"&E38,'Hoja 1 - Supabase Transcripts'!$2:$2,0)),"not found") -> not found
A39: 1bd3f940-d5d8-4bd7-a2b2-1fc66fc0f4a2 | B39: 2 | C39: {"session_id": "1bd3f940-d5d8-4bd7-a2b2-1fc66fc0f4a2", "quotes": [{"quote_text": "I would say, um, load balancing, especially for Lily. Uh, I think she's now staffed on, um, two projects basically, and it's a bit hard, I think, then to clearly show, you know, the capacity for her.", "topic": "overall_experience", "first_order_code": "colleague staffed on two projects making capacity unclear", "flagging_reason": "Raises a work concern about a named colleague's workload allocation and visibility.", "confidence": 0.95}, {"quote_text": "I would say su- sustainable-ish.", "topic": "workload_sustainability", "first_order_code": "workload only sustainable-ish", "flagging_reason": "Hedges the sustainability assessment with a qualifier that suggests it is not fully sustainable.", "confidence": 0.85}, {"quote_text": "I think the Wattenfall project was pretty hectic, um, as expected, and also the Avato demo one is also pretty hectic.", "topic": "workload_sustainability", "first_order_code": "two projects running pretty hectic", "flagging_reason": "States work intensity concern across two named projects, softened with 'as expected'.", "confidence": 0.9}, {"quote_text": "Um, so I think we need to do a better job of owning the process.", "topic": "workload_sustainability", "first_order_code": "team needs to do better job owning the process", "flagging_reason": "Identifies a process gap or friction that needs improvement.", "confidence": 0.9}, {"quote_text": "Um, basically, we don't follow a new normal. And... Oh, no, actually, that's not true. New normal is kinda...is okay", "topic": "workload_sustainability", "first_order_code": "self-correcting initial claim about not following new normal", "flagging_reason": "Initially raises a concern about process adherence, then immediately retracts and softens it.", "confidence": 0.8}, {"quote_text": "for example, starting before 9:00 and having to work while team dinners, et cetera. Not great, but also, I think, manageable and will be better in the future.", "topic": "workload_sustainability", "first_order_code": "starting early and working during team dinners not great but manageable", "flagging_reason": "States a work-life boundary concern but immediately minimizes it as manageable and temporary.", "confidence": 0.95}]} | D39: Um, so I think we need to do a better job of owning the process. | E39: workload_sust | F39: Identifies a process gap or friction that needs improvement. | G39: team needs to do better job owning the process | H39: 0.9 | I39: Self-attributing structural problems | J39: =IF(OR(I39="Epistemic hedging",I39="Qualifying severity while disclosing",I39="Downgrading emotional intensity"),"Hedged, qualified disclosure",IF(OR(I39="Externalizing accountability",I39="Self-attributing structural problems"),"Protective attribution shifting",IF(OR(I39="Refusal to elaborate under probing",I39="Retracting or qualifying disclosure"),"Withholding under probing",IF(OR(I39="Managing traceability and exposure",I39="Compartmentalizing the AI channel"),"Channel exposure management",IF(OR(I39="Skepticism toward remedy",I39="Anticipating dismissal or misrecognition"),"Anticipated futility of voice",IF(OR(I39="Calling out known but unaddressed issues",I39="Silence within expression"),"Recognized but unescalated concerns",I39)))))) -> Protective attribution shifting | K39: =_xlfn.XLOOKUP(J39,#REF!,#REF!,"0",0,1) -> #REF! | N39: =IFERROR(INDEX('Hoja 1 - Supabase Transcripts'!$A:$DN,MATCH(A39,'Hoja 1 - Supabase Transcripts'!$A:$A,0),MATCH("gap_segmentation_"&E39,'Hoja 1 - Supabase Transcripts'!$2:$2,0)),"not found") -> not found
A40: 1bd3f940-d5d8-4bd7-a2b2-1fc66fc0f4a2 | B40: 2 | C40: {"session_id": "1bd3f940-d5d8-4bd7-a2b2-1fc66fc0f4a2", "quotes": [{"quote_text": "I would say, um, load balancing, especially for Lily. Uh, I think she's now staffed on, um, two projects basically, and it's a bit hard, I think, then to clearly show, you know, the capacity for her.", "topic": "overall_experience", "first_order_code": "colleague staffed on two projects making capacity unclear", "flagging_reason": "Raises a work concern about a named colleague's workload allocation and visibility.", "confidence": 0.95}, {"quote_text": "I would say su- sustainable-ish.", "topic": "workload_sustainability", "first_order_code": "workload only sustainable-ish", "flagging_reason": "Hedges the sustainability assessment with a qualifier that suggests it is not fully sustainable.", "confidence": 0.85}, {"quote_text": "I think the Wattenfall project was pretty hectic, um, as expected, and also the Avato demo one is also pretty hectic.", "topic": "workload_sustainability", "first_order_code": "two projects running pretty hectic", "flagging_reason": "States work intensity concern across two named projects, softened with 'as expected'.", "confidence": 0.9}, {"quote_text": "Um, so I think we need to do a better job of owning the process.", "topic": "workload_sustainability", "first_order_code": "team needs to do better job owning the process", "flagging_reason": "Identifies a process gap or friction that needs improvement.", "confidence": 0.9}, {"quote_text": "Um, basically, we don't follow a new normal. And... Oh, no, actually, that's not true. New normal is kinda...is okay", "topic": "workload_sustainability", "first_order_code": "self-correcting initial claim about not following new normal", "flagging_reason": "Initially raises a concern about process adherence, then immediately retracts and softens it.", "confidence": 0.8}, {"quote_text": "for example, starting before 9:00 and having to work while team dinners, et cetera. Not great, but also, I think, manageable and will be better in the future.", "topic": "workload_sustainability", "first_order_code": "starting early and working during team dinners not great but manageable", "flagging_reason": "States a work-life boundary concern but immediately minimizes it as manageable and temporary.", "confidence": 0.95}]} | D40: for example, starting before 9:00 and having to work while team dinners, et cetera. Not great, but also, I think, manageable and will be better in the future. | E40: workload_sust | F40: States a work-life boundary concern but immediately minimizes it as manageable and temporary. | G40: starting early and working during team dinners not great but manageable | H40: 0.95 | I40: Qualifying severity while disclosing | J40: =IF(OR(I40="Epistemic hedging",I40="Qualifying severity while disclosing",I40="Downgrading emotional intensity"),"Hedged, qualified disclosure",IF(OR(I40="Externalizing accountability",I40="Self-attributing structural problems"),"Protective attribution shifting",IF(OR(I40="Refusal to elaborate under probing",I40="Retracting or qualifying disclosure"),"Withholding under probing",IF(OR(I40="Managing traceability and exposure",I40="Compartmentalizing the AI channel"),"Channel exposure management",IF(OR(I40="Skepticism toward remedy",I40="Anticipating dismissal or misrecognition"),"Anticipated futility of voice",IF(OR(I40="Calling out known but unaddressed issues",I40="Silence within expression"),"Recognized but unescalated concerns",I40)))))) -> Hedged, qualified disclosure | K40: =_xlfn.XLOOKUP(J40,#REF!,#REF!,"0",0,1) -> #REF! | N40: =IFERROR(INDEX('Hoja 1 - Supabase Transcripts'!$A:$DN,MATCH(A40,'Hoja 1 - Supabase Transcripts'!$A:$A,0),MATCH("gap_segmentation_"&E40,'Hoja 1 - Supabase Transcripts'!$2:$2,0)),"not found") -> not found
A41: 1e5026c9-80f3-4733-b2aa-41d8b86ca310 | B41: 2 | C41: {"session_id": "1e5026c9-80f3-4733-b2aa-41d8b86ca310", "quotes": [{"quote_text": "I feel like across the team, sometimes we're not, um, uh, doing a good enough job of equalizing the workload. But then again, that's very difficult to, to tell from the outside. So, um, maybe that's something we have to explore in more depths, but I don't really know how to create more transparency.", "topic": "client_value", "first_order_code": "workload not equally distributed across team members", "flagging_reason": "Identifies an internal team friction around unequal workload but immediately softens it by saying it's hard to judge from outside and expresses uncertainty about how to address it.", "confidence": 0.9}, {"quote_text": "I wanted to notice, uh, note one more thing. We also had a fantastic team dinner last week, so I think that also helped with bonding and just making sure that, um, everyone, uh, felt seen and welcome. And I want to note that one of the principals was there, uh, and the rest of the leadership unfortunately wasn't.", "topic": "leadership_engagement", "first_order_code": "most of leadership absent from the team dinner", "flagging_reason": "Embeds a critique of leadership absence within positive framing about the event, qualifying the praise with a concern about who was missing.", "confidence": 0.85}, {"quote_text": "I think it would be great if Andre would join one of those CTMs in person, um, just to get to know the team, because obviously we have a lot of turnaround, and some people just have never seen him in person. That's, I think, uh, something we should resolve.", "topic": "leadership_engagement", "first_order_code": "leader hasn't met team members in person due to turnover", "flagging_reason": "Raises a leadership visibility issue framed as a suggestion, noting that high turnover means some team members have never physically met the leader.", "confidence": 0.9}]} | D41: I feel like across the team, sometimes we're not, um, uh, doing a good enough job of equalizing the workload. But then again, that's very difficult to, to tell from the outside. So, um, maybe that's something we have to explore in more depths, but I don't really know how to create more transparency. | E41: client_value | F41: Identifies an internal team friction around unequal workload but immediately softens it by saying it's hard to judge from outside and expresses uncertainty about how to address it. | G41: workload not equally distributed across team members | H41: 0.9 | I41: Concern content - FAMILY A | J41: =IF(OR(I41="Epistemic hedging",I41="Qualifying severity while disclosing",I41="Downgrading emotional intensity"),"Hedged, qualified disclosure",IF(OR(I41="Externalizing accountability",I41="Self-attributing structural problems"),"Protective attribution shifting",IF(OR(I41="Refusal to elaborate under probing",I41="Retracting or qualifying disclosure"),"Withholding under probing",IF(OR(I41="Managing traceability and exposure",I41="Compartmentalizing the AI channel"),"Channel exposure management",IF(OR(I41="Skepticism toward remedy",I41="Anticipating dismissal or misrecognition"),"Anticipated futility of voice",IF(OR(I41="Calling out known but unaddressed issues",I41="Silence within expression"),"Recognized but unescalated concerns",I41)))))) -> Concern content - FAMILY A | N41: =IFERROR(INDEX('Hoja 1 - Supabase Transcripts'!$A:$DN,MATCH(A41,'Hoja 1 - Supabase Transcripts'!$A:$A,0),MATCH("gap_segmentation_"&E41,'Hoja 1 - Supabase Transcripts'!$2:$2,0)),"not found") -> not found
A42: 1e5026c9-80f3-4733-b2aa-41d8b86ca310 | B42: 2 | C42: {"session_id": "1e5026c9-80f3-4733-b2aa-41d8b86ca310", "quotes": [{"quote_text": "I feel like across the team, sometimes we're not, um, uh, doing a good enough job of equalizing the workload. But then again, that's very difficult to, to tell from the outside. So, um, maybe that's something we have to explore in more depths, but I don't really know how to create more transparency.", "topic": "client_value", "first_order_code": "workload not equally distributed across team members", "flagging_reason": "Identifies an internal team friction around unequal workload but immediately softens it by saying it's hard to judge from outside and expresses uncertainty about how to address it.", "confidence": 0.9}, {"quote_text": "I wanted to notice, uh, note one more thing. We also had a fantastic team dinner last week, so I think that also helped with bonding and just making sure that, um, everyone, uh, felt seen and welcome. And I want to note that one of the principals was there, uh, and the rest of the leadership unfortunately wasn't.", "topic": "leadership_engagement", "first_order_code": "most of leadership absent from the team dinner", "flagging_reason": "Embeds a critique of leadership absence within positive framing about the event, qualifying the praise with a concern about who was missing.", "confidence": 0.85}, {"quote_text": "I think it would be great if Andre would join one of those CTMs in person, um, just to get to know the team, because obviously we have a lot of turnaround, and some people just have never seen him in person. That's, I think, uh, something we should resolve.", "topic": "leadership_engagement", "first_order_code": "leader hasn't met team members in person due to turnover", "flagging_reason": "Raises a leadership visibility issue framed as a suggestion, noting that high turnover means some team members have never physically met the leader.", "confidence": 0.9}]} | D42: I think it would be great if Andre would join one of those CTMs in person, um, just to get to know the team, because obviously we have a lot of turnaround, and some people just have never seen him in person. That's, I think, uh, something we should resolve. | E42: leadership | F42: Raises a leadership visibility issue framed as a suggestion, noting that high turnover means some team members have never physically met the leader. | G42: leader hasn't met team members in person due to turnover | H42: 0.9 | I42: Concern content - FAMILY A | J42: =IF(OR(I42="Epistemic hedging",I42="Qualifying severity while disclosing",I42="Downgrading emotional intensity"),"Hedged, qualified disclosure",IF(OR(I42="Externalizing accountability",I42="Self-attributing structural problems"),"Protective attribution shifting",IF(OR(I42="Refusal to elaborate under probing",I42="Retracting or qualifying disclosure"),"Withholding under probing",IF(OR(I42="Managing traceability and exposure",I42="Compartmentalizing the AI channel"),"Channel exposure management",IF(OR(I42="Skepticism toward remedy",I42="Anticipating dismissal or misrecognition"),"Anticipated futility of voice",IF(OR(I42="Calling out known but unaddressed issues",I42="Silence within expression"),"Recognized but unescalated concerns",I42)))))) -> Concern content - FAMILY A | N42: =IFERROR(INDEX('Hoja 1 - Supabase Transcripts'!$A:$DN,MATCH(A42,'Hoja 1 - Supabase Transcripts'!$A:$A,0),MATCH("gap_segmentation_"&E42,'Hoja 1 - Supabase Transcripts'!$2:$2,0)),"not found") -> not found
